Workbook

Sheet Master_List
A1: S.no | B1: Player_Name | C1: player_type | D1: Position | E1: Club Name | F1: New Rating Overall | G1: Base Price | H1: Known As | I1: Full Name | J1: Overall | K1: Potential | L1: Value(in Euro) | M1: Positions Played | N1: Best Position | O1: Nationality | P1: Image Link | Q1: Age | R1: Height(in cm) | S1: Weight(in kg) | T1: TotalStats | U1: BaseStats | V1: Club Name | W1: Wage(in Euro) | X1: Release Clause | Y1: Club Position | Z1: Contract Until | AA1: Club Jersey Number | AB1: Joined On | AC1: On Loan | AD1: Preferred Foot | AE1: Weak Foot Rating | AF1: Skill Moves | AG1: International Reputation | AH1: National Team Name | AI1: National Team Image Link | AJ1: National Team Position | AK1: National Team Jersey Number | AL1: Attacking Work Rate | AM1: Defensive Work Rate | AN1: Pace Total | AO1: Shooting Total | AP1: Passing Total | AQ1: Dribbling Total | AR1: Defending Total | AS1: Physicality Total | AT1: Crossing | AU1: Finishing | AV1: Heading Accuracy | AW1: Short Passing | AX1: Volleys | AY1: Dribbling | AZ1: Curve | BA1: Freekick Accuracy | BB1: LongPassing | BC1: BallControl | BD1: Acceleration | BE1: Sprint Speed | BF1: Agility | BG1: Reactions | BH1: Balance | BI1: Shot Power | BJ1: Jumping | BK1: Stamina | BL1: Strength | BM1: Long Shots | BN1: Aggression | BO1: Interceptions | BP1: Positioning | BQ1: Vision | BR1: Penalties | BS1: Composure | BT1: Marking | BU1: Standing Tackle | BV1: Sliding Tackle | BW1: Goalkeeper Diving | BX1: Goalkeeper Handling | BY1: GoalkeeperKicking | BZ1: Goalkeeper Positioning | CA1: Goalkeeper Reflexes | CB1: ST Rating | CC1: LW Rating | CD1: LF Rating | CE1: CF Rating | CF1: RF Rating | CG1: RW Rating | CH1: CAM Rating | CI1: LM Rating | CJ1: CM Rating | CK1: RM Rating | CL1: LWB Rating | CM1: CDM Rating | CN1: RWB Rating | CO1: LB Rating | CP1: CB Rating | CQ1: RB Rating | CR1: GK Rating
A2: 1 | B2: Kevin De Bruyne | C2: Midfield | D2: CM | E2: Manchester City | F2: 91 | G2: 40 | H2: K. De Bruyne | I2: Kevin De Bruyne | J2: 91 | K2: 91 | L2: 107500000 | M2: CM,CAM | N2: CM | O2: Belgium | P2: https://cdn.sofifa.net/players/192/985/23_60.png | Q2: 31 | R2: 181 | S2: 70 | T2: 2303 | U2: 483 | V2: Manchester City | W2: 350000 | X2: 198900000 | Y2: CM | Z2: 2025 | AA2: 17 | AB2: 2015 | AC2: - | AD2: Right | AE2: 5 | AF2: 4 | AG2: 4 | AH2: Belgium | AI2: https://cdn.sofifa.net/flags/be.png | AJ2: RF | AK2: 7 | AL2: High | AM2: High | AN2: 74 | AO2: 88 | AP2: 93 | AQ2: 87 | AR2: 64 | AS2: 77 | AT2: 94 | AU2: 85 | AV2: 55 | AW2: 93 | AX2: 83 | AY2: 88 | AZ2: 89 | BA2: 83 | BB2: 93 | BC2: 90 | BD2: 76 | BE2: 73 | BF2: 76 | BG2: 91 | BH2: 78 | BI2: 92 | BJ2: 63 | BK2: 88 | BL2: 74 | BM2: 91 | BN2: 75 | BO2: 66 | BP2: 88 | BQ2: 94 | BR2: 83 | BS2: 89 | BT2: 68 | BU2: 65 | BV2: 53 | BW2: 15 | BX2: 13 | BY2: 5 | BZ2: 10 | CA2: 13 | CB2: 86 | CC2: 88 | CD2: 87 | CE2: 87 | CF2: 87 | CG2: 88 | CH2: 91 | CI2: 91 | CJ2: 91 | CK2: 91 | CL2: 82 | CM2: 82 | CN2: 82 | CO2: 78 | CP2: 72 | CQ2: 78 | CR2: 24
A3: 2 | B3: Casemiro | C3: Midfield | D3: CDM | E3: Manchester United | F3: 89 | G3: 40 | H3: Casemiro | I3: Carlos Henrique Venancio Casimiro | J3: 89 | K3: 89 | L3: 86000000 | M3: CDM | N3: CDM | O3: Brazil | P3: https://cdn.sofifa.net/players/200/145/23_60.png | Q3: 30 | R3: 185 | S3: 84 | T3: 2209 | U3: 460 | V3: Manchester United | W3: 240000 | X3: 163400000 | Y3: SUB | Z3: 2026 | AA3: 18 | AB3: 2022 | AC3: - | AD3: Right | AE3: 3 | AF3: 2 | AG3: 3 | AH3: - | AI3: https://cdn.sofifa.net/flags/br.png | AJ3: - | AK3: - | AL3: Medium | AM3: High | AN3: 63 | AO3: 73 | AP3: 75 | AQ3: 72 | AR3: 87 | AS3: 90 | AT3: 58 | AU3: 64 | AV3: 79 | AW3: 84 | AX3: 62 | AY3: 67 | AZ3: 62 | BA3: 74 | BB3: 83 | BC3: 78 | BD3: 60 | BE3: 66 | BF3: 61 | BG3: 87 | BH3: 66 | BI3: 88 | BJ3: 85 | BK3: 90 | BL3: 90 | BM3: 81 | BN3: 91 | BO3: 88 | BP3: 75 | BQ3: 75 | BR3: 66 | BS3: 84 | BT3: 87 | BU3: 88 | BV3: 87 | BW3: 13 | BX3: 14 | BY3: 16 | BZ3: 12 | CA3: 12 | CB3: 78 | CC3: 71 | CD3: 75 | CE3: 75 | CF3: 75 | CG3: 71 | CH3: 78 | CI3: 76 | CJ3: 84 | CK3: 76 | CL3: 83 | CM3: 89 | CN3: 83 | CO3: 84 | CP3: 89 | CQ3: 84 | CR3: 24
A4: 3 | B4: Luka Modric | C4: Midfield | D4: CM | E4: Real Madrid | F4: 88 | G4: 40 | H4: L. Modrić | I4: Luka Modrić | J4: 88 | K4: 88 | L4: 29000000 | M4: CM | N4: CM | O4: Croatia | P4: https://cdn.sofifa.net/players/177/003/23_60.png | Q4: 36 | R4: 172 | S4: 66 | T4: 2257 | U4: 464 | V4: Real Madrid CF | W4: 230000 | X4: 59500000 | Y4: CM | Z4: 2023 | AA4: 10 | AB4: 2012 | AC4: - | AD4: Right | AE4: 4 | AF4: 4 | AG4: 4 | AH4: Croatia | AI4: https://cdn.sofifa.net/flags/hr.png | AJ4: CM | AK4: 10 | AL4: Medium | AM4: Medium | AN4: 73 | AO4: 76 | AP4: 89 | AQ4: 88 | AR4: 72 | AS4: 66 | AT4: 86 | AU4: 72 | AV4: 55 | AW4: 91 | AX4: 76 | AY4: 85 | AZ4: 85 | BA4: 78 | BB4: 92 | BC4: 90 | BD4: 76 | BE4: 70 | BF4: 91 | BG4: 88 | BH4: 92 | BI4: 79 | BJ4: 67 | BK4: 83 | BL4: 58 | BM4: 82 | BN4: 62 | BO4: 80 | BP4: 78 | BQ4: 90 | BR4: 82 | BS4: 92 | BT4: 70 | BU4: 75 | BV4: 72 | BW4: 13 | BX4: 9 | BY4: 7 | BZ4: 14 | CA4: 9 | CB4: 79 | CC4: 83 | CD4: 82 | CE4: 82 | CF4: 82 | CG4: 83 | CH4: 88 | CI4: 87 | CJ4: 88 | CK4: 87 | CL4: 84 | CM4: 84 | CN4: 84 | CO4: 82 | CP4: 75 | CQ4: 82 | CR4: 22
A5: 4 | B5: Toni Kroos | C5: Midfield | D5: CM | E5: Real Madrid | F5: 88 | G5: 40 | H5: T. Kroos | I5: Toni Kroos | J5: 88 | K5: 88 | L5: 72000000 | M5: CM | N5: CM | O5: Germany | P5: https://cdn.sofifa.net/players/182/521/23_60.png | Q5: 32 | R5: 183 | S5: 76 | T5: 2147 | U5: 444 | V5: Real Madrid CF | W5: 310000 | X5: 147600000 | Y5: CM | Z5: 2023 | AA5: 8 | AB5: 2014 | AC5: - | AD5: Right | AE5: 5 | AF5: 3 | AG5: 4 | AH5: - | AI5: https://cdn.sofifa.net/flags/de.png | AJ5: - | AK5: - | AL5: Medium | AM5: Medium | AN5: 53 | AO5: 81 | AP5: 90 | AQ5: 81 | AR5: 71 | AS5: 68 | AT5: 88 | AU5: 77 | AV5: 58 | AW5: 93 | AX5: 82 | AY5: 80 | AZ5: 86 | BA5: 84 | BB5: 93 | BC5: 88 | BD5: 55 | BE5: 52 | BF5: 63 | BG5: 90 | BH5: 71 | BI5: 89 | BJ5: 32 | BK5: 75 | BL5: 72 | BM5: 86 | BN5: 60 | BO5: 80 | BP5: 76 | BQ5: 89 | BR5: 73 | BS5: 88 | BT5: 71 | BU5: 73 | BV5: 60 | BW5: 10 | BX5: 11 | BY5: 13 | BZ5: 7 | CA5: 10 | CB5: 80 | CC5: 80 | CD5: 81 | CE5: 81 | CF5: 81 | CG5: 80 | CH5: 86 | CI5: 84 | CJ5: 88 | CK5: 84 | CL5: 80 | CM5: 84 | CN5: 80 | CO5: 77 | CP5: 74 | CQ5: 77 | CR5: 22
A6: 5 | B6: Bernardo Silva | C6: Midfield | D6: CM | E6: Manchester City | F6: 88 | G6: 40 | H6: Bernardo Silva | I6: Bernardo Mota Carvalho e Silva | J6: 88 | K6: 88 | L6: 97500000 | M6: CAM,CM | N6: CAM | O6: Portugal | P6: https://cdn.sofifa.net/players/218/667/23_60.png | Q6: 27 | R6: 173 | S6: 64 | T6: 2185 | U6: 460 | V6: Manchester City | W6: 260000 | X6: 180400000 | Y6: RW | Z6: 2025 | AA6: 20 | AB6: 2017 | AC6: - | AD6: Left | AE6: 3 | AF6: 4 | AG6: 2 | AH6: Portugal | AI6: https://cdn.sofifa.net/flags/pt.png | AJ6: CM | AK6: 10 | AL6: High | AM6: High | AN6: 77 | AO6: 78 | AP6: 84 | AQ6: 92 | AR6: 61 | AS6: 68 | AT6: 85 | AU6: 79 | AV6: 51 | AW6: 89 | AX6: 78 | AY6: 92 | AZ6: 85 | BA6: 67 | BB6: 77 | BC6: 91 | BD6: 84 | BE6: 71 | BF6: 94 | BG6: 87 | BH6: 92 | BI6: 79 | BJ6: 51 | BK6: 93 | BL6: 54 | BM6: 78 | BN6: 75 | BO6: 60 | BP6: 83 | BQ6: 85 | BR6: 68 | BS6: 90 | BT6: 59 | BU6: 71 | BV6: 53 | BW6: 9 | BX6: 10 | BY6: 14 | BZ6: 12 | CA6: 9 | CB6: 80 | CC6: 86 | CD6: 84 | CE6: 84 | CF6: 84 | CG6: 86 | CH6: 88 | CI6: 88 | CJ6: 86 | CK6: 88 | CL6: 79 | CM6: 77 | CN6: 79 | CO6: 75 | CP6: 67 | CQ6: 75 | CR6: 21
A7: 6 | B7: Frenkie de Jong | C7: Midfield | D7: CM | E7: Barcelona | F7: 87 | G7: 30 | H7: F. de Jong | I7: Frenkie de Jong | J7: 87 | K7: 92 | L7: 116500000 | M7: CM | N7: CM | O7: Netherlands | P7: https://cdn.sofifa.net/players/228/702/23_60.png | Q7: 25 | R7: 180 | S7: 74 | T7: 2238 | U7: 479 | V7: FC Barcelona | W7: 230000 | X7: 247600000 | Y7: CM | Z7: 2026 | AA7: 21 | AB7: 2019 | AC7: - | AD7: Right | AE7: 3 | AF7: 4 | AG7: 3 | AH7: Netherlands | AI7: https://cdn.sofifa.net/flags/nl.png | AJ7: CDM | AK7: 21 | AL7: High | AM7: Medium | AN7: 82 | AO7: 69 | AP7: 86 | AQ7: 87 | AR7: 77 | AS7: 78 | AT7: 78 | AU7: 72 | AV7: 72 | AW7: 91 | AX7: 70 | AY7: 87 | AZ7: 84 | BA7: 64 | BB7: 89 | BC7: 89 | BD7: 80 | BE7: 83 | BF7: 87 | BG7: 88 | BH7: 79 | BI7: 68 | BJ7: 76 | BK7: 89 | BL7: 74 | BM7: 66 | BN7: 74 | BO7: 82 | BP7: 77 | BQ7: 88 | BR7: 53 | BS7: 90 | BT7: 76 | BU7: 76 | BV7: 77 | BW7: 7 | BX7: 13 | BY7: 10 | BZ7: 10 | CA7: 9 | CB7: 81 | CC7: 83 | CD7: 82 | CE7: 82 | CF7: 82 | CG7: 83 | CH7: 88 | CI7: 88 | CJ7: 89 | CK7: 88 | CL7: 86 | CM7: 87 | CN7: 86 | CO7: 85 | CP7: 81 | CQ7: 85 | CR7: 21
A8: 7 | B8: Leon Goretzka | C8: Midfield | D8: CM | E8: Bayern Munich | F8: 87 | G8: 30 | H8: L. Goretzka | I8: Leon Goretzka | J8: 87 | K8: 88 | L8: 91000000 | M8: CM,CDM | N8: CM | O8: Germany | P8: https://cdn.sofifa.net/players/209/658/23_60.png | Q8: 27 | R8: 189 | S8: 82 | T8: 2312 | U8: 492 | V8: FC Bayern München | W8: 115000 | X8: 157000000 | Y8: CDM | Z8: 2026 | AA8: 8 | AB8: 2018 | AC8: - | AD8: Right | AE8: 4 | AF8: 3 | AG8: 4 | AH8: Germany | AI8: https://cdn.sofifa.net/flags/de.png | AJ8: SUB | AK8: 8 | AL8: High | AM8: Medium | AN8: 78 | AO8: 82 | AP8: 82 | AQ8: 83 | AR8: 81 | AS8: 86 | AT8: 75 | AU8: 82 | AV8: 86 | AW8: 86 | AX8: 71 | AY8: 84 | AZ8: 76 | BA8: 75 | BB8: 85 | BC8: 86 | BD8: 78 | BE8: 78 | BF8: 76 | BG8: 87 | BH8: 73 | BI8: 85 | BJ8: 80 | BK8: 86 | BL8: 88 | BM8: 86 | BN8: 82 | BO8: 86 | BP8: 85 | BQ8: 84 | BR8: 60 | BS8: 82 | BT8: 74 | BU8: 84 | BV8: 78 | BW8: 13 | BX8: 8 | BY8: 15 | BZ8: 11 | CA8: 9 | CB8: 87 | CC8: 83 | CD8: 84 | CE8: 84 | CF8: 84 | CG8: 83 | CH8: 87 | CI8: 86 | CJ8: 88 | CK8: 86 | CL8: 85 | CM8: 87 | CN8: 85 | CO8: 85 | CP8: 86 | CQ8: 85 | CR8: 22
A9: 8 | B9: Verratti | C9: Midfield | D9: CM | E9: PSG | F9: 87 | G9: 30 | H9: M. Verratti | I9: Marco Verratti | J9: 87 | K9: 87 | L9: 77500000 | M9: CM,CAM | N9: CM | O9: Italy | P9: https://cdn.sofifa.net/players/199/556/23_60.png | Q9: 29 | R9: 165 | S9: 60 | T9: 2189 | U9: 444 | V9: Paris Saint-Germain | W9: 155000 | X9: 143400000 | Y9: CM | Z9: 2024 | AA9: 6 | AB9: 2012 | AC9: - | AD9: Right | AE9: 4 | AF9: 4 | AG9: 3 | AH9: Italy | AI9: https://cdn.sofifa.net/flags/it.png | AJ9: CM | AK9: 6 | AL9: Medium | AM9: High | AN9: 60 | AO9: 61 | AP9: 87 | AQ9: 91 | AR9: 79 | AS9: 66 | AT9: 82 | AU9: 60 | AV9: 57 | AW9: 90 | AX9: 64 | AY9: 91 | AZ9: 85 | BA9: 64 | BB9: 89 | BC9: 92 | BD9: 65 | BE9: 55 | BF9: 90 | BG9: 87 | BH9: 93 | BI9: 60 | BJ9: 66 | BK9: 75 | BL9: 53 | BM9: 58 | BN9: 89 | BO9: 85 | BP9: 78 | BQ9: 89 | BR9: 64 | BS9: 94 | BT9: 78 | BU9: 82 | BV9: 84 | BW9: 12 | BX9: 12 | BY9: 15 | BZ9: 15 | CA9: 10 | CB9: 74 | CC9: 80 | CD9: 79 | CE9: 79 | CF9: 79 | CG9: 80 | CH9: 86 | CI9: 85 | CJ9: 87 | CK9: 85 | CL9: 85 | CM9: 87 | CN9: 85 | CO9: 83 | CP9: 80 | CQ9: 83 | CR9: 24
A10: 9 | B10: Bruno Fernandes | C10: Midfield | D10: CAM | E10: Manchester United | F10: 86 | G10: 30 | H10: Bruno Fernandes | I10: Bruno Miguel Borges Fernandes | J10: 86 | K10: 86 | L10: 72500000 | M10: CAM,CM | N10: CAM | O10: Portugal | P10: https://cdn.sofifa.net/players/212/198/23_60.png | Q10: 27 | R10: 179 | S10: 69 | T10: 2305 | U10: 470 | V10: Manchester United | W10: 190000 | X10: 137800000 | Y10: CAM | Z10: 2026 | AA10: 8 | AB10: 2020 | AC10: - | AD10: Right | AE10: 3 | AF10: 4 | AG10: 3 | AH10: Portugal | AI10: https://cdn.sofifa.net/flags/pt.png | AJ10: CM | AK10: 11 | AL10: High | AM10: High | AN10: 72 | AO10: 86 | AP10: 88 | AQ10: 81 | AR10: 67 | AS10: 76 | AT10: 85 | AU10: 83 | AV10: 64 | AW10: 88 | AX10: 87 | AY10: 79 | AZ10: 87 | BA10: 85 | BB10: 88 | BC10: 84 | BD10: 75 | BE10: 69 | BF10: 78 | BG10: 91 | BH10: 79 | BI10: 88 | BJ10: 71 | BK10: 92 | BL10: 66 | BM10: 88 | BN10: 80 | BO10: 64 | BP10: 86 | BQ10: 91 | BR10: 90 | BS10: 79 | BT10: 66 | BU10: 73 | BV10: 65 | BW10: 12 | BX10: 14 | BY10: 15 | BZ10: 8 | CA10: 14 | CB10: 84 | CC10: 83 | CD10: 84 | CE10: 84 | CF10: 84 | CG10: 83 | CH10: 86 | CI10: 86 | CJ10: 86 | CK10: 86 | CL10: 81 | CM10: 82 | CN10: 81 | CO10: 79 | CP10: 74 | CQ10: 79 | CR10: 24
A11: 10 | B11: Jude Bellingham | C11: Midfield | D11: CM | E11: Real Madrid | F11: 86 | G11: 30 | H11: J. Bellingham | I11: Jude Bellingham | J11: 84 | K11: 91 | L11: 81500000 | M11: CM,LM | N11: CM | O11: England | P11: https://cdn.sofifa.net/players/252/371/23_60.png | Q11: 19 | R11: 186 | S11: 75 | T11: 2182 | U11: 469 | V11: Borussia Dortmund | W11: 41000 | X11: 154900000 | Y11: CDM | Z11: 2025 | AA11: 22 | AB11: 2020 | AC11: - | AD11: Right | AE11: 4 | AF11: 4 | AG11: 2 | AH11: England | AI11: https://cdn.sofifa.net/flags/gb-eng.png | AJ11: SUB | AK11: 26 | AL11: High | AM11: High | AN11: 75 | AO11: 75 | AP11: 78 | AQ11: 84 | AR11: 77 | AS11: 80 | AT11: 66 | AU11: 77 | AV11: 67 | AW11: 84 | AX11: 71 | AY11: 85 | AZ11: 68 | BA11: 49 | BB11: 82 | BC11: 84 | BD11: 78 | BE11: 73 | BF11: 81 | BG11: 84 | BH11: 79 | BI11: 78 | BJ11: 76 | BK11: 89 | BL11: 74 | BM11: 74 | BN11: 85 | BO11: 80 | BP11: 77 | BQ11: 84 | BR11: 56 | BS11: 79 | BT11: 79 | BU11: 78 | BV11: 76 | BW11: 14 | BX11: 11 | BY11: 10 | BZ11: 5 | CA11: 8 | CB11: 80 | CC11: 80 | CD11: 81 | CE11: 81 | CF11: 81 | CG11: 80 | CH11: 84 | CI11: 82 | CJ11: 85 | CK11: 82 | CL11: 81 | CM11: 84 | CN11: 81 | CO11: 80 | CP11: 80 | CQ11: 80 | CR11: 20
A12: 11 | B12: Federico Valverde | C12: Midfield | D12: CM | E12: Real Madrid | F12: 86 | G12: 30 | H12: F. Valverde | I12: Federico Valverde | J12: 84 | K12: 90 | L12: 66000000 | M12: CM,RW | N12: CM | O12: Uruguay | P12: https://cdn.sofifa.net/players/239/053/23_60.png | Q12: 23 | R12: 182 | S12: 78 | T12: 2192 | U12: 478 | V12: Real Madrid CF | W12: 175000 | X12: 148500000 | Y12: SUB | Z12: 2027 | AA12: 15 | AB12: 2016 | AC12: - | AD12: Right | AE12: 4 | AF12: 3 | AG12: 1 | AH12: - | AI12: https://cdn.sofifa.net/flags/uy.png | AJ12: - | AK12: - | AL12: High | AM12: High | AN12: 87 | AO12: 74 | AP12: 80 | AQ12: 79 | AR12: 78 | AS12: 80 | AT12: 70 | AU12: 69 | AV12: 59 | AW12: 86 | AX12: 70 | AY12: 78 | AZ12: 70 | BA12: 66 | BB12: 85 | BC12: 83 | BD12: 82 | BE12: 91 | BF12: 76 | BG12: 84 | BH12: 68 | BI12: 83 | BJ12: 62 | BK12: 86 | BL12: 79 | BM12: 81 | BN12: 81 | BO12: 81 | BP12: 78 | BQ12: 81 | BR12: 59 | BS12: 82 | BT12: 79 | BU12: 81 | BV12: 79 | BW12: 6 | BX12: 10 | BY12: 6 | BZ12: 15 | CA12: 8 | CB12: 79 | CC12: 80 | CD12: 80 | CE12: 80 | CF12: 80 | CG12: 80 | CH12: 83 | CI12: 83 | CJ12: 85 | CK12: 83 | CL12: 83 | CM12: 84 | CN12: 83 | CO12: 83 | CP12: 80 | CQ12: 83 | CR12: 20
A13: 12 | B13: Fabinho | C13: Midfield | D13: CDM | E13: Al-Ittihad | F13: 86 | G13: 30 | H13: Fabinho | I13: Fábio Henrique Tavares | J13: 87 | K13: 88 | L13: 77000000 | M13: CDM,CB | N13: CDM | O13: Brazil | P13: https://cdn.sofifa.net/players/209/499/23_60.png | Q13: 28 | R13: 188 | S13: 78 | T13: 2165 | U13: 459 | V13: Liverpool | W13: 185000 | X13: 148200000 | Y13: CDM | Z13: 2026 | AA13: 3 | AB13: 2018 | AC13: - | AD13: Right | AE13: 2 | AF13: 3 | AG13: 3 | AH13: - | AI13: https://cdn.sofifa.net/flags/br.png | AJ13: - | AK13: - | AL13: Medium | AM13: High | AN13: 66 | AO13: 69 | AP13: 78 | AQ13: 77 | AR13: 86 | AS13: 83 | AT13: 75 | AU13: 63 | AV13: 75 | AW13: 84 | AX13: 47 | AY13: 78 | AZ13: 71 | BA13: 53 | BB13: 82 | BC13: 81 | BD13: 64 | BE13: 68 | BF13: 63 | BG13: 86 | BH13: 64 | BI13: 81 | BJ13: 75 | BK13: 88 | BL13: 81 | BM13: 70 | BN13: 85 | BO13: 88 | BP13: 70 | BQ13: 76 | BR13: 90 | BS13: 85 | BT13: 86 | BU13: 88 | BV13: 86 | BW13: 13 | BX13: 12 | BY13: 6 | BZ13: 8 | CA13: 8 | CB13: 77 | CC13: 75 | CD13: 75 | CE13: 75 | CF13: 75 | CG13: 75 | CH13: 79 | CI13: 80 | CJ13: 84 | CK13: 80 | CL13: 85 | CM13: 88 | CN13: 85 | CO13: 85 | CP13: 87 | CQ13: 85 | CR13: 21
A14: 13 | B14: Nicolò Barella | C14: Midfield | D14: CM | E14: Inter Milan | F14: 86 | G14: 30 | H14: N. Barella | I14: Nicolò Barella | J14: 86 | K14: 89 | L14: 89500000 | M14: CM | N14: CM | O14: Italy | P14: https://cdn.sofifa.net/players/224/232/23_60.png | Q14: 25 | R14: 172 | S14: 68 | T14: 2296 | U14: 480 | V14: Inter | W14: 110000 | X14: 154400000 | Y14: CM | Z14: 2026 | AA14: 23 | AB14: 2020 | AC14: - | AD14: Right | AE14: 3 | AF14: 3 | AG14: 3 | AH14: Italy | AI14: https://cdn.sofifa.net/flags/it.png | AJ14: CM | AK14: 18 | AL14: High | AM14: High | AN14: 79 | AO14: 76 | AP14: 83 | AQ14: 84 | AR14: 77 | AS14: 81 | AT14: 79 | AU14: 73 | AV14: 53 | AW14: 86 | AX14: 80 | AY14: 80 | AZ14: 79 | BA14: 67 | BB14: 85 | BC14: 87 | BD14: 80 | BE14: 78 | BF14: 90 | BG14: 88 | BH14: 90 | BI14: 77 | BJ14: 78 | BK14: 94 | BL14: 73 | BM14: 79 | BN14: 84 | BO14: 83 | BP14: 81 | BQ14: 86 | BR14: 73 | BS14: 86 | BT14: 79 | BU14: 79 | BV14: 81 | BW14: 11 | BX14: 5 | BY14: 13 | BZ14: 14 | CA14: 11 | CB14: 80 | CC14: 82 | CD14: 81 | CE14: 81 | CF14: 81 | CG14: 82 | CH14: 86 | CI14: 86 | CJ14: 88 | CK14: 86 | CL14: 86 | CM14: 87 | CN14: 86 | CO14: 85 | CP14: 81 | CQ14: 85 | CR14: 22
A15: 14 | B15: Milinkovic Savic | C15: Midfield | D15: CM | E15: Al-Nasar | F15: 86 | G15: 30 | H15: V. Milinković-Savić | I15: Vanja Milinković-Savić | J15: 73 | K15: 77 | L15: 3300000 | M15: GK | N15: GK | O15: Serbia | P15: https://cdn.sofifa.net/players/224/836/23_60.png | Q15: 25 | R15: 202 | S15: 90 | T15: 1330 | U15: 412 | V15: Torino F.C. | W15: 22000 | X15: 6200000 | Y15: GK | Z15: 2024 | AA15: 32 | AB15: 2017 | AC15: - | AD15: Right | AE15: 3 | AF15: 1 | AG15: 1 | AH15: - | AI15: - | AJ15: - | AK15: - | AL15: Medium | AM15: Medium | AN15: 73 | AO15: 71 | AP15: 78 | AQ15: 73 | AR15: 43 | AS15: 74 | AT15: 18 | AU15: 20 | AV15: 12 | AW15: 31 | AX15: 16 | AY15: 15 | AZ15: 55 | BA15: 59 | BB15: 30 | BC15: 18 | BD15: 41 | BE15: 45 | BF15: 38 | BG15: 63 | BH15: 38 | BI15: 59 | BJ15: 58 | BK15: 33 | BL15: 73 | BM15: 45 | BN15: 34 | BO15: 21 | BP15: 12 | BQ15: 58 | BR15: 24 | BS15: 65 | BT15: 11 | BU15: 15 | BV15: 19 | BW15: 73 | BX15: 71 | BY15: 78 | BZ15: 74 | CA15: 73 | CB15: 33 | CC15: 29 | CD15: 31 | CE15: 31 | CF15: 31 | CG15: 29 | CH15: 34 | CI15: 31 | CJ15: 34 | CK15: 31 | CL15: 29 | CM15: 31 | CN15: 29 | CO15: 28 | CP15: 30 | CQ15: 28 | CR15: 74
A16: 15 | B16: Thiago Alcantara | C16: Midfield | D16: CDM | E16: Liverpool | F16: 86 | G16: 30 | H16: Thiago | I16: Thiago Alcântara | J16: 86 | K16: 86 | L16: 55500000 | M16: CM | N16: CM | O16: Spain | P16: https://cdn.sofifa.net/players/189/509/23_60.png | Q16: 31 | R16: 174 | S16: 70 | T16: 2225 | U16: 451 | V16: Liverpool | W16: 180000 | X16: 102700000 | Y16: CM | Z16: 2024 | AA16: 6 | AB16: 2020 | AC16: - | AD16: Right | AE16: 3 | AF16: 5 | AG16: 3 | AH16: - | AI16: https://cdn.sofifa.net/flags/es.png | AJ16: - | AK16: - | AL16: Medium | AM16: Medium | AN16: 61 | AO16: 72 | AP16: 87 | AQ16: 90 | AR16: 72 | AS16: 69 | AT16: 78 | AU16: 68 | AV16: 54 | AW16: 91 | AX16: 82 | AY16: 89 | AZ16: 85 | BA16: 77 | BB16: 89 | BC16: 92 | BD16: 69 | BE16: 55 | BF16: 90 | BG16: 84 | BH16: 90 | BI16: 75 | BJ16: 86 | BK16: 76 | BL16: 60 | BM16: 73 | BN16: 80 | BO16: 82 | BP16: 75 | BQ16: 88 | BR16: 75 | BS16: 90 | BT16: 68 | BU16: 74 | BV16: 74 | BW16: 6 | BX16: 11 | BY16: 7 | BZ16: 9 | CA16: 13 | CB16: 77 | CC16: 81 | CD16: 80 | CE16: 80 | CF16: 80 | CG16: 81 | CH16: 86 | CI16: 85 | CJ16: 86 | CK16: 85 | CL16: 81 | CM16: 84 | CN16: 81 | CO16: 79 | CP16: 76 | CQ16: 79 | CR16: 21
A17: 16 | B17: Thomas Muller | C17: Midfield | D17: CM | E17: Bayern Munich | F17: 85 | G17: 30 | H17: T. Müller | I17: Thomas Müller | J17: 87 | K17: 87 | L17: 63000000 | M17: CAM,CF | N17: CAM | O17: Germany | P17: https://cdn.sofifa.net/players/189/596/23_60.png | Q17: 32 | R17: 185 | S17: 76 | T17: 2140 | U17: 443 | V17: FC Bayern München | W17: 115000 | X17: 104000000 | Y17: CAM | Z17: 2024 | AA17: 25 | AB17: 2008 | AC17: - | AD17: Right | AE17: 4 | AF17: 3 | AG17: 4 | AH17: Germany | AI17: https://cdn.sofifa.net/flags/de.png | AJ17: CAM | AK17: 13 | AL17: High | AM17: High | AN17: 69 | AO17: 84 | AP17: 83 | AQ17: 80 | AR17: 56 | AS17: 71 | AT17: 85 | AU17: 88 | AV17: 81 | AW17: 85 | AX17: 84 | AY17: 77 | AZ17: 81 | BA17: 59 | BB17: 79 | BC17: 84 | BD17: 66 | BE17: 71 | BF17: 72 | BG17: 94 | BH17: 71 | BI17: 78 | BJ17: 77 | BK17: 86 | BL17: 66 | BM17: 82 | BN17: 62 | BO17: 58 | BP17: 96 | BQ17: 86 | BR17: 70 | BS17: 84 | BT17: 47 | BU17: 57 | BV17: 46 | BW17: 6 | BX17: 7 | BY17: 11 | BZ17: 14 | CA17: 14 | CB17: 86 | CC17: 83 | CD17: 84 | CE17: 84 | CF17: 84 | CG17: 83 | CH17: 87 | CI17: 86 | CJ17: 85 | CK17: 86 | CL17: 74 | CM17: 74 | CN17: 74 | CO17: 72 | CP17: 66 | CQ17: 72 | CR17: 23
A18: 17 | B18: Ilkay Gundogan | C18: Midfield | D18: CM | E18: Barcelona | F18: 85 | G18: 30 | H18: İ. Gündoğan | I18: İlkay Gündoğan | J18: 85 | K18: 85 | L18: 44000000 | M18: CM,CDM | N18: CM | O18: Germany | P18: https://cdn.sofifa.net/players/186/942/23_60.png | Q18: 31 | R18: 180 | S18: 80 | T18: 2195 | U18: 458 | V18: Manchester City | W18: 185000 | X18: 81400000 | Y18: CM | Z18: 2023 | AA18: 8 | AB18: 2016 | AC18: - | AD18: Right | AE18: 4 | AF18: 4 | AG18: 3 | AH18: Germany | AI18: https://cdn.sofifa.net/flags/de.png | AJ18: CDM | AK18: 21 | AL18: High | AM18: Medium | AN18: 64 | AO18: 80 | AP18: 85 | AQ18: 85 | AR18: 72 | AS18: 72 | AT18: 78 | AU18: 81 | AV18: 50 | AW18: 88 | AX18: 75 | AY18: 85 | AZ18: 86 | BA18: 80 | BB18: 85 | BC18: 90 | BD18: 66 | BE18: 63 | BF18: 77 | BG18: 86 | BH18: 77 | BI18: 79 | BJ18: 61 | BK18: 74 | BL18: 73 | BM18: 81 | BN18: 70 | BO18: 75 | BP18: 83 | BQ18: 86 | BR18: 80 | BS18: 87 | BT18: 76 | BU18: 75 | BV18: 67 | BW18: 11 | BX18: 14 | BY18: 5 | BZ18: 5 | CA18: 13 | CB18: 81 | CC18: 82 | CD18: 82 | CE18: 82 | CF18: 82 | CG18: 82 | CH18: 85 | CI18: 85 | CJ18: 85 | CK18: 85 | CL18: 80 | CM18: 83 | CN18: 80 | CO18: 78 | CP18: 75 | CQ18: 78 | CR18: 22
A19: 18 | B19: Marco Reus | C19: Midfield | D19: CM | E19: Dortmund | F19: 85 | G19: 30 | H19: M. Reus | I19: Marco Reus | J19: 85 | K19: 85 | L19: 33500000 | M19: CAM,CF,RM | N19: CAM | O19: Germany | P19: https://cdn.sofifa.net/players/188/350/23_60.png | Q19: 33 | R19: 180 | S19: 71 | T19: 2154 | U19: 441 | V19: Borussia Dortmund | W19: 78000 | X19: 57000000 | Y19: CAM | Z19: 2023 | AA19: 11 | AB19: 2012 | AC19: - | AD19: Right | AE19: 4 | AF19: 4 | AG19: 4 | AH19: Germany | AI19: https://cdn.sofifa.net/flags/de.png | AJ19: SUB | AK19: 11 | AL19: High | AM19: Medium | AN19: 70 | AO19: 84 | AP19: 84 | AQ19: 85 | AR19: 53 | AS19: 65 | AT19: 84 | AU19: 84 | AV19: 44 | AW19: 85 | AX19: 87 | AY19: 86 | AZ19: 88 | BA19: 85 | BB19: 79 | BC19: 86 | BD19: 75 | BE19: 66 | BF19: 83 | BG19: 86 | BH19: 81 | BI19: 86 | BJ19: 68 | BK19: 72 | BL19: 66 | BM19: 81 | BN19: 51 | BO19: 56 | BP19: 84 | BQ19: 86 | BR19: 79 | BS19: 86 | BT19: 59 | BU19: 47 | BV19: 59 | BW19: 12 | BX19: 12 | BY19: 13 | BZ19: 13 | CA19: 11 | CB19: 82 | CC19: 83 | CD19: 83 | CE19: 83 | CF19: 83 | CG19: 83 | CH19: 85 | CI19: 85 | CJ19: 83 | CK19: 85 | CL19: 74 | CM19: 72 | CN19: 74 | CO19: 70 | CP19: 62 | CQ19: 70 | CR19: 23
A20: 19 | B20: Jorginho | C20: Midfield | D20: CDM | E20: Arsenal | F20: 85 | G20: 30 | H20: Jorginho | I20: Luiz Frello Filho Jorge | J20: 85 | K20: 85 | L20: 51500000 | M20: CM | N20: CM | O20: Italy | P20: https://cdn.sofifa.net/players/205/498/23_60.png | Q20: 30 | R20: 180 | S20: 68 | T20: 2128 | U20: 434 | V20: Chelsea | W20: 165000 | X20: 95300000 | Y20: CM | Z20: 2023 | AA20: 5 | AB20: 2018 | AC20: - | AD20: Right | AE20: 3 | AF20: 3 | AG20: 2 | AH20: Italy | AI20: https://cdn.sofifa.net/flags/it.png | AJ20: CM | AK20: 8 | AL20: Medium | AM20: Medium | AN20: 54 | AO20: 67 | AP20: 86 | AQ20: 81 | AR20: 73 | AS20: 73 | AT20: 75 | AU20: 64 | AV20: 56 | AW20: 92 | AX20: 71 | AY20: 79 | AZ20: 75 | BA20: 76 | BB20: 89 | BC20: 87 | BD20: 63 | BE20: 47 | BF20: 75 | BG20: 82 | BH20: 72 | BI20: 71 | BJ20: 58 | BK20: 87 | BL20: 66 | BM20: 62 | BN20: 79 | BO20: 81 | BP20: 69 | BQ20: 88 | BR20: 89 | BS20: 84 | BT20: 67 | BU20: 81 | BV20: 71 | BW20: 14 | BX20: 7 | BY20: 13 | BZ20: 14 | CA20: 8 | CB20: 72 | CC20: 75 | CD20: 75 | CE20: 75 | CF20: 75 | CG20: 75 | CH20: 82 | CI20: 80 | CJ20: 85 | CK20: 80 | CL20: 80 | CM20: 84 | CN20: 80 | CO20: 77 | CP20: 75 | CQ20: 77 | CR20: 21
A21: 20 | B21: Pedri | C21: Midfield | D21: CM | E21: Barcelona | F21: 85 | G21: 30 | H21: Pedri | I21: Pedro González López | J21: 85 | K21: 93 | L21: 116000000 | M21: CM | N21: CM | O21: Spain | P21: https://cdn.sofifa.net/players/251/854/23_60.png | Q21: 19 | R21: 174 | S21: 61 | T21: 2109 | U21: 455 | V21: FC Barcelona | W21: 115000 | X21: 261000000 | Y21: CM | Z21: 2026 | AA21: 8 | AB21: 2020 | AC21: - | AD21: Right | AE21: 4 | AF21: 4 | AG21: 2 | AH21: Spain | AI21: https://cdn.sofifa.net/flags/es.png | AJ21: CM | AK21: 10 | AL21: High | AM21: High | AN21: 79 | AO21: 67 | AP21: 81 | AQ21: 87 | AR21: 68 | AS21: 73 | AT21: 68 | AU21: 68 | AV21: 50 | AW21: 87 | AX21: 56 | AY21: 87 | AZ21: 79 | BA21: 62 | BB21: 85 | BC21: 88 | BD21: 82 | BE21: 76 | BF21: 88 | BG21: 85 | BH21: 90 | BI21: 66 | BJ21: 65 | BK21: 88 | BL21: 70 | BM21: 67 | BN21: 62 | BO21: 72 | BP21: 77 | BQ21: 88 | BR21: 53 | BS21: 87 | BT21: 68 | BU21: 73 | BV21: 63 | BW21: 12 | BX21: 7 | BY21: 11 | BZ21: 8 | CA21: 8 | CB21: 76 | CC21: 81 | CD21: 80 | CE21: 80 | CF21: 80 | CG21: 81 | CH21: 85 | CI21: 84 | CJ21: 86 | CK21: 84 | CL21: 79 | CM21: 80 | CN21: 79 | CO21: 77 | CP21: 72 | CQ21: 77 | CR21: 19
A22: 21 | B22: Martin Odegard | C22: Midfield | D22: CAM | E22: Arsenal | F22: 85 | G22: 30 | H22: M. Ødegaard | I22: Martin Ødegaard | J22: 84 | K22: 89 | L22: 63500000 | M22: CAM,CM | N22: CAM | O22: Norway | P22: https://cdn.sofifa.net/players/222/665/23_60.png | Q22: 23 | R22: 178 | S22: 68 | T22: 2109 | U22: 442 | V22: Arsenal | W22: 105000 | X22: 125400000 | Y22: CAM | Z22: 2026 | AA22: 8 | AB22: 2021 | AC22: - | AD22: Left | AE22: 2 | AF22: 5 | AG22: 3 | AH22: Norway | AI22: https://cdn.sofifa.net/flags/no.png | AJ22: CM | AK22: 10 | AL22: High | AM22: Medium | AN22: 76 | AO22: 75 | AP22: 86 | AQ22: 84 | AR22: 58 | AS22: 63 | AT22: 84 | AU22: 75 | AV22: 52 | AW22: 88 | AX22: 76 | AY22: 85 | AZ22: 83 | BA22: 85 | BB22: 84 | BC22: 85 | BD22: 78 | BE22: 75 | BF22: 85 | BG22: 74 | BH22: 83 | BI22: 76 | BJ22: 46 | BK22: 79 | BL22: 56 | BM22: 77 | BN22: 63 | BO22: 65 | BP22: 79 | BQ22: 86 | BR22: 63 | BS22: 78 | BT22: 65 | BU22: 49 | BV22: 51 | BW22: 14 | BX22: 15 | BY22: 15 | BZ22: 8 | CA22: 10 | CB22: 78 | CC22: 82 | CD22: 80 | CE22: 80 | CF22: 80 | CG22: 82 | CH22: 86 | CI22: 85 | CJ22: 84 | CK22: 85 | CL22: 75 | CM22: 74 | CN22: 75 | CO22: 72 | CP22: 64 | CQ22: 72 | CR22: 22
A23: 22 | B23: Florian Writz | C23: Midfield | D23: CAM | E23: Bayern Leverkusen | F23: 85 | G23: 30 | H23: F. Wirtz | I23: Florian Wirtz | J23: 82 | K23: 91 | L23: 66000000 | M23: CAM,CM | N23: CAM | O23: Germany | P23: https://cdn.sofifa.net/players/256/630/23_60.png | Q23: 19 | R23: 176 | S23: 72 | T23: 1994 | U23: 428 | V23: Bayer 04 Leverkusen | W23: 38000 | X23: 125400000 | Y23: RES | Z23: 2027 | AA23: 27 | AB23: 2020 | AC23: - | AD23: Right | AE23: 4 | AF23: 4 | AG23: 2 | AH23: - | AI23: https://cdn.sofifa.net/flags/de.png | AJ23: - | AK23: - | AL23: High | AM23: Medium | AN23: 78 | AO23: 73 | AP23: 80 | AQ23: 86 | AR23: 51 | AS23: 60 | AT23: 77 | AU23: 78 | AV23: 39 | AW23: 82 | AX23: 68 | AY23: 86 | AZ23: 76 | BA23: 54 | BB23: 82 | BC23: 88 | BD23: 76 | BE23: 79 | BF23: 85 | BG23: 80 | BH23: 82 | BI23: 67 | BJ23: 52 | BK23: 79 | BL23: 50 | BM23: 70 | BN23: 63 | BO23: 45 | BP23: 78 | BQ23: 85 | BR23: 60 | BS23: 80 | BT23: 55 | BU23: 57 | BV23: 44 | BW23: 14 | BX23: 14 | BY23: 13 | BZ23: 6 | CA23: 10 | CB23: 75 | CC23: 81 | CD23: 80 | CE23: 80 | CF23: 80 | CG23: 81 | CH23: 84 | CI23: 84 | CJ23: 81 | CK23: 84 | CL23: 71 | CM23: 70 | CN23: 71 | CO23: 67 | CP23: 58 | CQ23: 67 | CR23: 21
A24: 23 | B24: James Maddison | C24: Midfield | D24: CAM | E24: Leicester City | F24: 84 | G24: 30 | H24: J. Maddison | I24: James Maddison | J24: 82 | K24: 84 | L24: 38000000 | M24: CAM,RM | N24: CAM | O24: England | P24: https://cdn.sofifa.net/players/220/697/23_60.png | Q24: 25 | R24: 175 | S24: 73 | T24: 2090 | U24: 436 | V24: Leicester City | W24: 100000 | X24: 75100000 | Y24: RM | Z24: 2024 | AA24: 10 | AB24: 2018 | AC24: - | AD24: Right | AE24: 4 | AF24: 4 | AG24: 1 | AH24: - | AI24: https://cdn.sofifa.net/flags/gb-eng.png | AJ24: - | AK24: - | AL24: High | AM24: Medium | AN24: 73 | AO24: 78 | AP24: 84 | AQ24: 85 | AR24: 54 | AS24: 62 | AT24: 81 | AU24: 76 | AV24: 35 | AW24: 84 | AX24: 73 | AY24: 85 | AZ24: 86 | BA24: 84 | BB24: 83 | BC24: 86 | BD24: 77 | BE24: 69 | BF24: 84 | BG24: 78 | BH24: 83 | BI24: 83 | BJ24: 51 | BK24: 76 | BL24: 53 | BM24: 80 | BN24: 68 | BO24: 44 | BP24: 81 | BQ24: 85 | BR24: 74 | BS24: 84 | BT24: 59 | BU24: 65 | BV24: 42 | BW24: 11 | BX24: 14 | BY24: 14 | BZ24: 12 | CA24: 14 | CB24: 76 | CC24: 81 | CD24: 80 | CE24: 80 | CF24: 80 | CG24: 81 | CH24: 84 | CI24: 83 | CJ24: 82 | CK24: 83 | CL24: 71 | CM24: 71 | CN24: 71 | CO24: 67 | CP24: 59 | CQ24: 67 | CR24: 22
A25: 24 | B25: Declan Rice | C25: Midfield | D25: CDM | E25: Arsenal | F25: 84 | G25: 30 | H25: D. Rice | I25: Declan Rice | J25: 84 | K25: 87 | L25: 52000000 | M25: CDM | N25: CDM | O25: England | P25: https://cdn.sofifa.net/players/234/378/23_60.png | Q25: 23 | R25: 185 | S25: 80 | T25: 2075 | U25: 450 | V25: West Ham United | W25: 83000 | X25: 102700000 | Y25: CDM | Z25: 2024 | AA25: 41 | AB25: 2016 | AC25: - | AD25: Right | AE25: 3 | AF25: 2 | AG25: 1 | AH25: England | AI25: https://cdn.sofifa.net/flags/gb-eng.png | AJ25: CM | AK25: 4 | AL25: Medium | AM25: High | AN25: 71 | AO25: 64 | AP25: 74 | AQ25: 76 | AR25: 82 | AS25: 83 | AT25: 55 | AU25: 61 | AV25: 72 | AW25: 83 | AX25: 50 | AY25: 78 | AZ25: 58 | BA25: 58 | BB25: 84 | BC25: 79 | BD25: 68 | BE25: 74 | BF25: 55 | BG25: 81 | BH25: 67 | BI25: 74 | BJ25: 74 | BK25: 90 | BL25: 79 | BM25: 65 | BN25: 84 | BO25: 85 | BP25: 58 | BQ25: 79 | BR25: 71 | BS25: 83 | BT25: 82 | BU25: 84 | BV25: 80 | BW25: 8 | BX25: 11 | BY25: 14 | BZ25: 5 | CA25: 9 | CB25: 72 | CC25: 71 | CD25: 73 | CE25: 73 | CF25: 73 | CG25: 71 | CH25: 77 | CI25: 76 | CJ25: 81 | CK25: 76 | CL25: 80 | CM25: 85 | CN25: 80 | CO25: 81 | CP25: 83 | CQ25: 81 | CR25: 19
A26: 25 | B26: Youri Tielemans | C26: Midfield | D26: CM | E26: Aston Villa | F26: 84 | G26: 30 | H26: Y. Tielemans | I26: Youri Tielemans | J26: 84 | K26: 86 | L26: 52500000 | M26: CM,CDM | N26: CM | O26: Belgium | P26: https://cdn.sofifa.net/players/216/393/23_60.png | Q26: 25 | R26: 176 | S26: 72 | T26: 2187 | U26: 446 | V26: Leicester City | W26: 115000 | X26: 103700000 | Y26: CM | Z26: 2023 | AA26: 8 | AB26: 2019 | AC26: - | AD26: Right | AE26: 5 | AF26: 4 | AG26: 2 | AH26: Belgium | AI26: https://cdn.sofifa.net/flags/be.png | AJ26: CM | AK26: 8 | AL26: Medium | AM26: Medium | AN26: 56 | AO26: 80 | AP26: 86 | AQ26: 81 | AR26: 70 | AS26: 73 | AT26: 82 | AU26: 74 | AV26: 67 | AW26: 89 | AX26: 79 | AY26: 81 | AZ26: 84 | BA26: 78 | BB26: 88 | BC26: 85 | BD26: 58 | BE26: 54 | BF26: 67 | BG26: 84 | BH26: 77 | BI26: 87 | BJ26: 68 | BK26: 85 | BL26: 69 | BM26: 87 | BN26: 69 | BO26: 71 | BP26: 80 | BQ26: 87 | BR26: 77 | BS26: 85 | BT26: 69 | BU26: 73 | BV26: 68 | BW26: 6 | BX26: 8 | BY26: 10 | BZ26: 14 | CA26: 12 | CB26: 79 | CC26: 79 | CD26: 80 | CE26: 80 | CF26: 80 | CG26: 79 | CH26: 84 | CI26: 82 | CJ26: 86 | CK26: 82 | CL26: 78 | CM26: 81 | CN26: 78 | CO26: 76 | CP26: 74 | CQ26: 76 | CR26: 20
A27: 26 | B27: Marcos Llorente | C27: Midfield | D27: CM | E27: Atletico de Madrid | F27: 84 | G27: 30 | H27: Marcos Llorente | I27: Marcos Llorente Moreno | J27: 84 | K27: 85 | L27: 48000000 | M27: CM,RM,RB | N27: CAM | O27: Spain | P27: https://cdn.sofifa.net/players/226/161/23_60.png | Q27: 27 | R27: 184 | S27: 74 | T27: 2244 | U27: 489 | V27: Atlético de Madrid | W27: 81000 | X27: 102000000 | Y27: SUB | Z27: 2027 | AA27: 14 | AB27: 2019 | AC27: - | AD27: Right | AE27: 4 | AF27: 3 | AG27: 3 | AH27: Spain | AI27: https://cdn.sofifa.net/flags/es.png | AJ27: SUB | AK27: 6 | AL27: High | AM27: Medium | AN27: 88 | AO27: 79 | AP27: 81 | AQ27: 82 | AR27: 78 | AS27: 81 | AT27: 74 | AU27: 80 | AV27: 67 | AW27: 86 | AX27: 66 | AY27: 82 | AZ27: 75 | BA27: 63 | BB27: 81 | BC27: 84 | BD27: 85 | BE27: 90 | BF27: 82 | BG27: 85 | BH27: 68 | BI27: 84 | BJ27: 69 | BK27: 90 | BL27: 77 | BM27: 77 | BN27: 82 | BO27: 81 | BP27: 84 | BQ27: 84 | BR27: 65 | BS27: 83 | BT27: 79 | BU27: 79 | BV27: 74 | BW27: 13 | BX27: 6 | BY27: 6 | BZ27: 11 | CA27: 15 | CB27: 84 | CC27: 83 | CD27: 83 | CE27: 83 | CF27: 83 | CG27: 83 | CH27: 85 | CI27: 85 | CJ27: 85 | CK27: 85 | CL27: 85 | CM27: 85 | CN27: 85 | CO27: 84 | CP27: 81 | CQ27: 84 | CR27: 22
A28: 27 | B28: Thomas Partey | C28: Midfield | D28: CDM | E28: Arsenal | F28: 84 | G28: 30 | H28: T. Partey | I28: Thomas Partey | J28: 84 | K28: 84 | L28: 36000000 | M28: CDM,CM | N28: CDM | O28: Ghana | P28: https://cdn.sofifa.net/players/209/989/23_60.png | Q28: 29 | R28: 185 | S28: 77 | T28: 2143 | U28: 460 | V28: Arsenal | W28: 115000 | X28: 68400000 | Y28: CDM | Z28: 2024 | AA28: 5 | AB28: 2020 | AC28: - | AD28: Right | AE28: 3 | AF28: 3 | AG28: 2 | AH28: Ghana | AI28: https://cdn.sofifa.net/flags/gh.png | AJ28: CDM | AK28: 6 | AL28: Medium | AM28: High | AN28: 65 | AO28: 71 | AP28: 81 | AQ28: 80 | AR28: 80 | AS28: 83 | AT28: 74 | AU28: 66 | AV28: 68 | AW28: 85 | AX28: 56 | AY28: 84 | AZ28: 69 | BA28: 70 | BB28: 85 | BC28: 83 | BD28: 61 | BE28: 68 | BF28: 67 | BG28: 82 | BH28: 50 | BI28: 86 | BJ28: 83 | BK28: 82 | BL28: 84 | BM28: 78 | BN28: 84 | BO28: 81 | BP28: 70 | BQ28: 85 | BR28: 49 | BS28: 86 | BT28: 80 | BU28: 84 | BV28: 80 | BW28: 11 | BX28: 13 | BY28: 9 | BZ28: 9 | CA28: 7 | CB28: 77 | CC28: 77 | CD28: 78 | CE28: 78 | CF28: 78 | CG28: 77 | CH28: 81 | CI28: 80 | CJ28: 84 | CK28: 80 | CL28: 82 | CM28: 84 | CN28: 82 | CO28: 81 | CP28: 83 | CQ28: 81 | CR28: 20
A29: 28 | B29: Sandro Tonali | C29: Midfield | D29: CM | E29: Newcastle United | F29: 84 | G29: 30 | H29: S. Tonali | I29: Sandro Tonali | J29: 84 | K29: 90 | L29: 62500000 | M29: CDM,CM | N29: CDM | O29: Italy | P29: https://cdn.sofifa.net/players/241/096/23_60.png | Q29: 22 | R29: 181 | S29: 79 | T29: 2225 | U29: 475 | V29: AC Milan | W29: 75000 | X29: 118800000 | Y29: CM | Z29: 2027 | AA29: 8 | AB29: 2021 | AC29: - | AD29: Right | AE29: 4 | AF29: 3 | AG29: 1 | AH29: - | AI29: https://cdn.sofifa.net/flags/it.png | AJ29: - | AK29: - | AL29: Medium | AM29: High | AN29: 81 | AO29: 73 | AP29: 81 | AQ29: 79 | AR29: 79 | AS29: 82 | AT29: 78 | AU29: 69 | AV29: 70 | AW29: 84 | AX29: 68 | AY29: 75 | AZ29: 75 | BA29: 81 | BB29: 81 | BC29: 83 | BD29: 78 | BE29: 83 | BF29: 81 | BG29: 82 | BH29: 83 | BI29: 79 | BJ29: 65 | BK29: 85 | BL29: 81 | BM29: 81 | BN29: 84 | BO29: 81 | BP29: 75 | BQ29: 78 | BR29: 64 | BS29: 84 | BT29: 81 | BU29: 81 | BV29: 75 | BW29: 13 | BX29: 9 | BY29: 8 | BZ29: 7 | CA29: 7 | CB29: 78 | CC29: 78 | CD29: 78 | CE29: 78 | CF29: 78 | CG29: 78 | CH29: 81 | CI29: 81 | CJ29: 83 | CK29: 81 | CL29: 83 | CM29: 84 | CN29: 83 | CO29: 82 | CP29: 81 | CQ29: 82 | CR29: 19
A30: 29 | B30: Hakan Calhanoglu | C30: Midfield | D30: CAM | E30: Inter Milan | F30: 84 | G30: 30 | H30: H. Çalhanoğlu | I30: Hakan Çalhanoğlu | J30: 84 | K30: 84 | L30: 42000000 | M30: CM | N30: CM | O30: Turkey | P30: https://cdn.sofifa.net/players/208/128/23_60.png | Q30: 28 | R30: 178 | S30: 76 | T30: 2172 | U30: 450 | V30: Inter | W30: 100000 | X30: 69300000 | Y30: CM | Z30: 2024 | AA30: 20 | AB30: 2021 | AC30: - | AD30: Right | AE30: 4 | AF30: 4 | AG30: 3 | AH30: - | AI30: https://cdn.sofifa.net/flags/tr.png | AJ30: - | AK30: - | AL30: High | AM30: High | AN30: 67 | AO30: 80 | AP30: 85 | AQ30: 86 | AR30: 68 | AS30: 64 | AT30: 80 | AU30: 75 | AV30: 53 | AW30: 87 | AX30: 74 | AY30: 86 | AZ30: 85 | BA30: 85 | BB30: 84 | BC30: 88 | BD30: 72 | BE30: 62 | BF30: 83 | BG30: 84 | BH30: 79 | BI30: 85 | BJ30: 45 | BK30: 78 | BL30: 55 | BM30: 87 | BN30: 73 | BO30: 76 | BP30: 79 | BQ30: 86 | BR30: 81 | BS30: 83 | BT30: 69 | BU30: 68 | BV30: 63 | BW30: 9 | BX30: 14 | BY30: 11 | BZ30: 6 | CA30: 10 | CB30: 79 | CC30: 81 | CD30: 82 | CE30: 82 | CF30: 82 | CG30: 81 | CH30: 84 | CI30: 84 | CJ30: 84 | CK30: 84 | CL30: 79 | CM30: 80 | CN30: 79 | CO30: 76 | CP30: 71 | CQ30: 76 | CR30: 21
A31: 30 | B31: Pierre-Emile Hojbjerg | C31: Midfield | D31: CDM | E31: Spurs | F31: 84 | G31: 30 | H31: P. Højbjerg | I31: Pierre-Emile Højbjerg | J31: 83 | K31: 85 | L31: 40500000 | M31: CDM,CM | N31: CDM | O31: Denmark | P31: https://cdn.sofifa.net/players/213/648/23_60.png | Q31: 26 | R31: 187 | S31: 84 | T31: 2108 | U31: 444 | V31: Tottenham Hotspur | W31: 110000 | X31: 80000000 | Y31: CM | Z31: 2025 | AA31: 5 | AB31: 2020 | AC31: - | AD31: Right | AE31: 4 | AF31: 3 | AG31: 2 | AH31: Denmark | AI31: https://cdn.sofifa.net/flags/dk.png | AJ31: CM | AK31: 23 | AL31: High | AM31: High | AN31: 55 | AO31: 73 | AP31: 77 | AQ31: 77 | AR31: 80 | AS31: 82 | AT31: 68 | AU31: 68 | AV31: 65 | AW31: 83 | AX31: 64 | AY31: 78 | AZ31: 70 | BA31: 74 | BB31: 81 | BC31: 80 | BD31: 56 | BE31: 54 | BF31: 65 | BG31: 84 | BH31: 67 | BI31: 85 | BJ31: 65 | BK31: 87 | BL31: 79 | BM31: 80 | BN31: 87 | BO31: 82 | BP31: 68 | BQ31: 73 | BR31: 56 | BS31: 84 | BT31: 83 | BU31: 84 | BV31: 72 | BW31: 9 | BX31: 7 | BY31: 12 | BZ31: 11 | CA31: 11 | CB31: 75 | CC31: 73 | CD31: 74 | CE31: 74 | CF31: 74 | CG31: 73 | CH31: 77 | CI31: 76 | CJ31: 82 | CK31: 76 | CL31: 79 | CM31: 84 | CN31: 79 | CO31: 78 | CP31: 81 | CQ31: 78 | CR31: 20
A32: 31 | B32: Maddison | C32: Midfield | D32: CAM | E32: Spurs | F32: 84 | G32: 30 | H32: J. Maddison | I32: James Maddison | J32: 82 | K32: 84 | L32: 38000000 | M32: CAM,RM | N32: CAM | O32: England | P32: https://cdn.sofifa.net/players/220/697/23_60.png | Q32: 25 | R32: 175 | S32: 73 | T32: 2090 | U32: 436 | V32: Leicester City | W32: 100000 | X32: 75100000 | Y32: RM | Z32: 2024 | AA32: 10 | AB32: 2018 | AC32: - | AD32: Right | AE32: 4 | AF32: 4 | AG32: 1 | AH32: - | AI32: https://cdn.sofifa.net/flags/gb-eng.png | AJ32: - | AK32: - | AL32: High | AM32: Medium | AN32: 73 | AO32: 78 | AP32: 84 | AQ32: 85 | AR32: 54 | AS32: 62 | AT32: 81 | AU32: 76 | AV32: 35 | AW32: 84 | AX32: 73 | AY32: 85 | AZ32: 86 | BA32: 84 | BB32: 83 | BC32: 86 | BD32: 77 | BE32: 69 | BF32: 84 | BG32: 78 | BH32: 83 | BI32: 83 | BJ32: 51 | BK32: 76 | BL32: 53 | BM32: 80 | BN32: 68 | BO32: 44 | BP32: 81 | BQ32: 85 | BR32: 74 | BS32: 84 | BT32: 59 | BU32: 65 | BV32: 42 | BW32: 11 | BX32: 14 | BY32: 14 | BZ32: 12 | CA32: 14 | CB32: 76 | CC32: 81 | CD32: 80 | CE32: 80 | CF32: 80 | CG32: 81 | CH32: 84 | CI32: 83 | CJ32: 82 | CK32: 83 | CL32: 71 | CM32: 71 | CN32: 71 | CO32: 67 | CP32: 59 | CQ32: 67 | CR32: 22
A33: 32 | B33: De Paul | C33: Midfield | D33: CM | E33: Atletico Madrid | F33: 84 | G33: 30 | H33: R. De Paul | I33: Rodrigo Javier De Paul | J33: 84 | K33: 84 | L33: 42000000 | M33: CM | N33: CM | O33: Argentina | P33: https://cdn.sofifa.net/players/212/616/23_60.png | Q33: 28 | R33: 180 | S33: 70 | T33: 2240 | U33: 476 | V33: Atlético de Madrid | W33: 85000 | X33: 86100000 | Y33: CM | Z33: 2026 | AA33: 5 | AB33: 2021 | AC33: - | AD33: Right | AE33: 3 | AF33: 4 | AG33: 1 | AH33: Argentina | AI33: https://cdn.sofifa.net/flags/ar.png | AJ33: CM | AK33: 7 | AL33: High | AM33: Medium | AN33: 78 | AO33: 77 | AP33: 83 | AQ33: 82 | AR33: 75 | AS33: 81 | AT33: 78 | AU33: 76 | AV33: 58 | AW33: 85 | AX33: 71 | AY33: 82 | AZ33: 84 | BA33: 76 | BB33: 85 | BC33: 85 | BD33: 80 | BE33: 76 | BF33: 78 | BG33: 81 | BH33: 80 | BI33: 80 | BJ33: 68 | BK33: 91 | BL33: 80 | BM33: 78 | BN33: 76 | BO33: 79 | BP33: 78 | BQ33: 86 | BR33: 66 | BS33: 81 | BT33: 71 | BU33: 81 | BV33: 75 | BW33: 13 | BX33: 12 | BY33: 10 | BZ33: 7 | CA33: 14 | CB33: 79 | CC33: 81 | CD33: 81 | CE33: 81 | CF33: 81 | CG33: 81 | CH33: 84 | CI33: 84 | CJ33: 84 | CK33: 84 | CL33: 82 | CM33: 83 | CN33: 82 | CO33: 81 | CP33: 78 | CQ33: 81 | CR33: 21
A34: 33 | B34: Carrasco | C34: Midfield | D34: LM | E34: Atletico Madrid | F34: 84 | G34: 30 | H34: Y. Carrasco | I34: Yannick Carrasco | J34: 85 | K34: 85 | L34: 54500000 | M34: LM | N34: LM | O34: Belgium | P34: https://cdn.sofifa.net/players/208/418/23_60.png | Q34: 28 | R34: 181 | S34: 73 | T34: 2153 | U34: 458 | V34: Atlético de Madrid | W34: 90000 | X34: 111700000 | Y34: LM | Z34: 2024 | AA34: 21 | AB34: 2020 | AC34: - | AD34: Right | AE34: 4 | AF34: 4 | AG34: 3 | AH34: Belgium | AI34: https://cdn.sofifa.net/flags/be.png | AJ34: LM | AK34: 11 | AL34: High | AM34: High | AN34: 89 | AO34: 82 | AP34: 80 | AQ34: 87 | AR34: 53 | AS34: 67 | AT34: 81 | AU34: 81 | AV34: 53 | AW34: 80 | AX34: 74 | AY34: 90 | AZ34: 87 | BA34: 80 | BB34: 74 | BC34: 86 | BD34: 89 | BE34: 89 | BF34: 87 | BG34: 81 | BH34: 71 | BI34: 85 | BJ34: 71 | BK34: 79 | BL34: 61 | BM34: 82 | BN34: 65 | BO34: 47 | BP34: 82 | BQ34: 80 | BR34: 81 | BS34: 84 | BT34: 44 | BU34: 64 | BV34: 60 | BW34: 9 | BX34: 11 | BY34: 9 | BZ34: 10 | CA34: 10 | CB34: 82 | CC34: 84 | CD34: 83 | CE34: 83 | CF34: 83 | CG34: 84 | CH34: 85 | CI34: 85 | CJ34: 82 | CK34: 85 | CL34: 75 | CM34: 71 | CN34: 75 | CO34: 72 | CP34: 64 | CQ34: 72 | CR34: 21
A35: 34 | B35: Bruno Guimaraes | C35: Midfield | D35: CDM | E35: New Castle United | F35: 83 | G35: 20 | H35: Bruno Guimarães | I35: Bruno Guimarães Moura | J35: 81 | K35: 86 | L35: 38500000 | M35: CM,CDM | N35: CM | O35: Brazil | P35: https://cdn.sofifa.net/players/247/851/23_60.png | Q35: 24 | R35: 182 | S35: 74 | T35: 2110 | U35: 449 | V35: Newcastle United | W35: 88000 | X35: 76000000 | Y35: CM | Z35: 2026 | AA35: 39 | AB35: 2022 | AC35: - | AD35: Right | AE35: 2 | AF35: 3 | AG35: 2 | AH35: - | AI35: https://cdn.sofifa.net/flags/br.png | AJ35: - | AK35: - | AL35: High | AM35: High | AN35: 69 | AO35: 67 | AP35: 79 | AQ35: 81 | AR35: 76 | AS35: 77 | AT35: 68 | AU35: 68 | AV35: 61 | AW35: 84 | AX35: 66 | AY35: 81 | AZ35: 75 | BA35: 62 | BB35: 83 | BC35: 82 | BD35: 68 | BE35: 69 | BF35: 74 | BG35: 80 | BH35: 78 | BI35: 64 | BJ35: 62 | BK35: 84 | BL35: 75 | BM35: 67 | BN35: 77 | BO35: 78 | BP35: 72 | BQ35: 82 | BR35: 65 | BS35: 83 | BT35: 77 | BU35: 79 | BV35: 74 | BW35: 7 | BX35: 11 | BY35: 15 | BZ35: 11 | CA35: 11 | CB35: 74 | CC35: 76 | CD35: 76 | CE35: 76 | CF35: 76 | CG35: 76 | CH35: 80 | CI35: 79 | CJ35: 83 | CK35: 79 | CL35: 79 | CM35: 82 | CN35: 79 | CO35: 78 | CP35: 77 | CQ35: 78 | CR35: 20
A36: 35 | B36: Rodri | C36: Midfield | D36: CDM | E36: Manchester City | F36: 83 | G36: 20 | H36: Rodri | I36: Rodrigo Hernández Cascante | J36: 87 | K36: 89 | L36: 88500000 | M36: CDM | N36: CDM | O36: Spain | P36: https://cdn.sofifa.net/players/231/866/23_60.png | Q36: 26 | R36: 191 | S36: 82 | T36: 2133 | U36: 454 | V36: Manchester City | W36: 200000 | X36: 170400000 | Y36: CDM | Z36: 2027 | AA36: 16 | AB36: 2019 | AC36: - | AD36: Right | AE36: 4 | AF36: 3 | AG36: 3 | AH36: Spain | AI36: https://cdn.sofifa.net/flags/es.png | AJ36: SUB | AK36: 16 | AL36: Medium | AM36: High | AN36: 58 | AO36: 72 | AP36: 78 | AQ36: 79 | AR36: 83 | AS36: 84 | AT36: 63 | AU36: 64 | AV36: 80 | AW36: 86 | AX36: 59 | AY36: 78 | AZ36: 65 | BA36: 61 | BB36: 83 | BC36: 85 | BD36: 54 | BE36: 62 | BF36: 65 | BG36: 82 | BH36: 65 | BI36: 89 | BJ36: 72 | BK36: 88 | BL36: 84 | BM36: 82 | BN36: 82 | BO36: 83 | BP36: 75 | BQ36: 83 | BR36: 46 | BS36: 85 | BT36: 84 | BU36: 86 | BV36: 78 | BW36: 10 | BX36: 10 | BY36: 7 | BZ36: 14 | CA36: 8 | CB36: 79 | CC36: 74 | CD36: 77 | CE36: 77 | CF36: 77 | CG36: 74 | CH36: 82 | CI36: 79 | CJ36: 86 | CK36: 79 | CL36: 82 | CM36: 87 | CN36: 82 | CO36: 82 | CP36: 85 | CQ36: 82 | CR36: 21
A37: 36 | B37: Mason Mount | C37: Midfield | D37: CAM | E37: Manchester United | F37: 83 | G37: 20 | H37: M. Mount | I37: Mason Mount | J37: 84 | K37: 87 | L37: 57500000 | M37: CAM,RW | N37: CAM | O37: England | P37: https://cdn.sofifa.net/players/233/064/23_60.png | Q37: 23 | R37: 180 | S37: 74 | T37: 2119 | U37: 444 | V37: Chelsea | W37: 130000 | X37: 110700000 | Y37: RW | Z37: 2024 | AA37: 19 | AB37: 2016 | AC37: - | AD37: Right | AE37: 4 | AF37: 3 | AG37: 3 | AH37: England | AI37: https://cdn.sofifa.net/flags/gb-eng.png | AJ37: CAM | AK37: 19 | AL37: High | AM37: High | AN37: 74 | AO37: 81 | AP37: 85 | AQ37: 82 | AR37: 55 | AS37: 67 | AT37: 83 | AU37: 81 | AV37: 59 | AW37: 87 | AX37: 75 | AY37: 82 | AZ37: 82 | BA37: 84 | BB37: 84 | BC37: 85 | BD37: 76 | BE37: 72 | BF37: 77 | BG37: 84 | BH37: 76 | BI37: 81 | BJ37: 54 | BK37: 86 | BL37: 58 | BM37: 83 | BN37: 68 | BO37: 59 | BP37: 82 | BQ37: 83 | BR37: 69 | BS37: 84 | BT37: 55 | BU37: 57 | BV37: 41 | BW37: 11 | BX37: 12 | BY37: 13 | BZ37: 8 | CA37: 12 | CB37: 81 | CC37: 82 | CD37: 82 | CE37: 82 | CF37: 82 | CG37: 82 | CH37: 86 | CI37: 85 | CJ37: 85 | CK37: 85 | CL37: 74 | CM37: 74 | CN37: 74 | CO37: 71 | CP37: 64 | CQ37: 71 | CR37: 22
A38: 37 | B38: Kai Havertz | C38: Midfield | D38: CAM | E38: Arsenal | F38: 83 | G38: 20 | H38: K. Havertz | I38: Kai Havertz | J38: 84 | K38: 91 | L38: 84500000 | M38: CAM,CF,ST | N38: CAM | O38: Germany | P38: https://cdn.sofifa.net/players/235/790/23_60.png | Q38: 23 | R38: 189 | S38: 82 | T38: 2042 | U38: 434 | V38: Chelsea | W38: 130000 | X38: 173200000 | Y38: LW | Z38: 2025 | AA38: 29 | AB38: 2020 | AC38: - | AD38: Left | AE38: 4 | AF38: 4 | AG38: 3 | AH38: Germany | AI38: https://cdn.sofifa.net/flags/de.png | AJ38: SUB | AK38: 7 | AL38: Medium | AM38: Medium | AN38: 81 | AO38: 79 | AP38: 79 | AQ38: 84 | AR38: 45 | AS38: 66 | AT38: 74 | AU38: 81 | AV38: 80 | AW38: 84 | AX38: 80 | AY38: 85 | AZ38: 84 | BA38: 53 | BB38: 79 | BC38: 85 | BD38: 76 | BE38: 85 | BF38: 77 | BG38: 84 | BH38: 75 | BI38: 74 | BJ38: 75 | BK38: 77 | BL38: 69 | BM38: 78 | BN38: 42 | BO38: 38 | BP38: 82 | BQ38: 82 | BR38: 73 | BS38: 84 | BT38: 39 | BU38: 46 | BV38: 38 | BW38: 6 | BX38: 8 | BY38: 11 | BZ38: 10 | CA38: 12 | CB38: 84 | CC38: 82 | CD38: 82 | CE38: 82 | CF38: 82 | CG38: 82 | CH38: 86 | CI38: 85 | CJ38: 81 | CK38: 85 | CL38: 68 | CM38: 66 | CN38: 68 | CO38: 65 | CP38: 59 | CQ38: 65 | CR38: 20
A39: 38 | B39: Mateo Kovacic | C39: Midfield | D39: CM | E39: Manchester City | F39: 83 | G39: 20 | H39: M. Kovačić | I39: Mateo Kovačić | J39: 84 | K39: 84 | L39: 42000000 | M39: CM | N39: CM | O39: Croatia | P39: https://cdn.sofifa.net/players/207/410/23_60.png | Q39: 28 | R39: 176 | S39: 80 | T39: 2141 | U39: 452 | V39: Chelsea | W39: 155000 | X39: 77700000 | Y39: SUB | Z39: 2024 | AA39: 8 | AB39: 2019 | AC39: - | AD39: Right | AE39: 4 | AF39: 4 | AG39: 3 | AH39: Croatia | AI39: https://cdn.sofifa.net/flags/hr.png | AJ39: CM | AK39: 8 | AL39: High | AM39: High | AN39: 70 | AO39: 69 | AP39: 83 | AQ39: 88 | AR39: 71 | AS39: 71 | AT39: 73 | AU39: 61 | AV39: 42 | AW39: 90 | AX39: 76 | AY39: 89 | AZ39: 79 | BA39: 70 | BB39: 84 | BC39: 89 | BD39: 77 | BE39: 65 | BF39: 86 | BG39: 82 | BH39: 84 | BI39: 79 | BJ39: 75 | BK39: 79 | BL39: 65 | BM39: 75 | BN39: 77 | BO39: 75 | BP39: 73 | BQ39: 86 | BR39: 59 | BS39: 84 | BT39: 73 | BU39: 76 | BV39: 68 | BW39: 9 | BX39: 5 | BY39: 6 | BZ39: 7 | CA39: 7 | CB39: 75 | CC39: 80 | CD39: 79 | CE39: 79 | CF39: 79 | CG39: 80 | CH39: 84 | CI39: 84 | CJ39: 84 | CK39: 84 | CL39: 81 | CM39: 83 | CN39: 81 | CO39: 78 | CP39: 74 | CQ39: 78 | CR39: 18
A40: 39 | B40: Thomas Lemar | C40: Midfield | D40: LM | E40: Atletico Madrid | F40: 83 | G40: 20 | H40: T. Lemar | I40: Thomas Lemar | J40: 83 | K40: 86 | L40: 47000000 | M40: CM,LM,RM | N40: CAM | O40: France | P40: https://cdn.sofifa.net/players/213/565/23_60.png | Q40: 26 | R40: 171 | S40: 66 | T40: 2215 | U40: 462 | V40: Atlético de Madrid | W40: 74000 | X40: 99900000 | Y40: SUB | Z40: 2023 | AA40: 11 | AB40: 2018 | AC40: - | AD40: Left | AE40: 3 | AF40: 4 | AG40: 3 | AH40: - | AI40: https://cdn.sofifa.net/flags/fr.png | AJ40: - | AK40: - | AL40: High | AM40: High | AN40: 82 | AO40: 78 | AP40: 83 | AQ40: 87 | AR40: 68 | AS40: 64 | AT40: 82 | AU40: 77 | AV40: 54 | AW40: 84 | AX40: 77 | AY40: 88 | AZ40: 85 | BA40: 81 | BB40: 80 | BC40: 86 | BD40: 84 | BE40: 81 | BF40: 90 | BG40: 82 | BH40: 85 | BI40: 79 | BJ40: 68 | BK40: 80 | BL40: 56 | BM40: 79 | BN40: 63 | BO40: 78 | BP40: 81 | BQ40: 85 | BR40: 69 | BS40: 80 | BT40: 55 | BU40: 77 | BV40: 69 | BW40: 11 | BX40: 15 | BY40: 13 | BZ40: 7 | CA40: 14 | CB40: 80 | CC40: 83 | CD40: 82 | CE40: 82 | CF40: 82 | CG40: 83 | CH40: 86 | CI40: 86 | CJ40: 86 | CK40: 86 | CL40: 81 | CM40: 79 | CN40: 81 | CO40: 79 | CP40: 72 | CQ40: 79 | CR40: 23
A41: 40 | B41: Piotr Zielinski | C41: Midfield | D41: CAM | E41: Napoli | F41: 83 | G41: 20 | H41: P. Zieliński | I41: Piotr Zieliński | J41: 83 | K41: 83 | L41: 36500000 | M41: CAM,CM | N41: CAM | O41: Poland | P41: https://cdn.sofifa.net/players/210/406/23_60.png | Q41: 28 | R41: 180 | S41: 75 | T41: 2132 | U41: 457 | V41: Napoli | W41: 78000 | X41: 62100000 | Y41: CM | Z41: 2024 | AA41: 20 | AB41: 2016 | AC41: - | AD41: Right | AE41: 5 | AF41: 4 | AG41: 3 | AH41: Poland | AI41: https://cdn.sofifa.net/flags/pl.png | AJ41: CAM | AK41: 20 | AL41: Medium | AM41: Medium | AN41: 81 | AO41: 77 | AP41: 81 | AQ41: 86 | AR41: 70 | AS41: 62 | AT41: 73 | AU41: 75 | AV41: 52 | AW41: 85 | AX41: 75 | AY41: 87 | AZ41: 80 | BA41: 65 | BB41: 81 | BC41: 87 | BD41: 83 | BE41: 79 | BF41: 85 | BG41: 81 | BH41: 79 | BI41: 79 | BJ41: 52 | BK41: 79 | BL41: 57 | BM41: 83 | BN41: 56 | BO41: 75 | BP41: 80 | BQ41: 84 | BR41: 58 | BS41: 75 | BT41: 69 | BU41: 72 | BV41: 71 | BW41: 12 | BX41: 9 | BY41: 12 | BZ41: 11 | CA41: 6 | CB41: 80 | CC41: 82 | CD41: 82 | CE41: 82 | CF41: 82 | CG41: 82 | CH41: 83 | CI41: 83 | CJ41: 83 | CK41: 83 | CL41: 81 | CM41: 79 | CN41: 81 | CO41: 79 | CP41: 71 | CQ41: 79 | CR41: 20
A42: 41 | B42: Fabian Ruiz | C42: Midfield | D42: CM | E42: PSG | F42: 83 | G42: 20 | H42: F. Frei | I42: Fabian Frei | J42: 71 | K42: 71 | L42: 900000 | M42: CB,CDM | N42: CDM | O42: Switzerland | P42: https://cdn.sofifa.net/players/183/346/23_60.png | Q42: 33 | R42: 183 | S42: 80 | T42: 1972 | U42: 408 | V42: FC Basel 1893 | W42: 12000 | X42: 1400000 | Y42: CDM | Z42: 2024 | AA42: 20 | AB42: 2018 | AC42: - | AD42: Right | AE42: 3 | AF42: 3 | AG42: 1 | AH42: - | AI42: https://cdn.sofifa.net/flags/ch.png | AJ42: - | AK42: - | AL42: Medium | AM42: High | AN42: 55 | AO42: 69 | AP42: 70 | AQ42: 69 | AR42: 72 | AS42: 73 | AT42: 70 | AU42: 68 | AV42: 68 | AW42: 72 | AX42: 71 | AY42: 69 | AZ42: 70 | BA42: 67 | BB42: 71 | BC42: 72 | BD42: 54 | BE42: 55 | BF42: 58 | BG42: 67 | BH42: 61 | BI42: 73 | BJ42: 73 | BK42: 79 | BL42: 74 | BM42: 70 | BN42: 63 | BO42: 74 | BP42: 65 | BQ42: 68 | BR42: 66 | BS42: 74 | BT42: 76 | BU42: 70 | BV42: 68 | BW42: 12 | BX42: 15 | BY42: 8 | BZ42: 11 | CA42: 14 | CB42: 70 | CC42: 67 | CD42: 68 | CE42: 68 | CF42: 68 | CG42: 67 | CH42: 70 | CI42: 70 | CJ42: 71 | CK42: 70 | CL42: 71 | CM42: 71 | CN42: 71 | CO42: 71 | CP42: 71 | CQ42: 71 | CR42: 21
A43: 42 | B43: Aurélien Tchouaméni | C43: Midfield | D43: CDM | E43: Real Madrid | F43: 83 | G43: 20 | H43: A. Tchouaméni | I43: Aurélien Tchouaméni | J43: 82 | K43: 89 | L43: 61500000 | M43: CM,CDM | N43: CDM | O43: France | P43: https://cdn.sofifa.net/players/241/637/23_60.png | Q43: 22 | R43: 187 | S43: 81 | T43: 2142 | U43: 460 | V43: Real Madrid CF | W43: 145000 | X43: 138400000 | Y43: CDM | Z43: 2028 | AA43: 18 | AB43: 2022 | AC43: - | AD43: Right | AE43: 3 | AF43: 3 | AG43: 2 | AH43: France | AI43: https://cdn.sofifa.net/flags/fr.png | AJ43: SUB | AK43: 8 | AL43: Medium | AM43: High | AN43: 70 | AO43: 70 | AP43: 79 | AQ43: 78 | AR43: 81 | AS43: 82 | AT43: 68 | AU43: 67 | AV43: 74 | AW43: 85 | AX43: 50 | AY43: 78 | AZ43: 76 | BA43: 53 | BB43: 84 | BC43: 80 | BD43: 68 | BE43: 71 | BF43: 73 | BG43: 83 | BH43: 70 | BI43: 78 | BJ43: 74 | BK43: 84 | BL43: 82 | BM43: 75 | BN43: 82 | BO43: 85 | BP43: 75 | BQ43: 82 | BR43: 55 | BS43: 83 | BT43: 81 | BU43: 83 | BV43: 78 | BW43: 9 | BX43: 8 | BY43: 12 | BZ43: 12 | CA43: 7 | CB43: 77 | CC43: 76 | CD43: 77 | CE43: 77 | CF43: 77 | CG43: 76 | CH43: 81 | CI43: 79 | CJ43: 84 | CK43: 79 | CL43: 81 | CM43: 85 | CN43: 81 | CO43: 81 | CP43: 83 | CQ43: 81 | CR43: 19
A44: 43 | B44: Eriksen | C44: Midfield | D44: CAM | E44: Manchester United | F44: 83 | G44: 20 | H44: K. Eriksen | I44: Kristian Eriksen | J44: 66 | K44: 67 | L44: 1000000 | M44: CAM,RM | N44: CAM | O44: Norway | P44: https://cdn.sofifa.net/players/267/685/23_60.png | Q44: 26 | R44: 177 | S44: 67 | T44: 1715 | U44: 362 | V44: Molde FK | W44: 2000 | X44: 1300000 | Y44: SUB | Z44: 2026 | AA44: 20 | AB44: 2022 | AC44: - | AD44: Right | AE44: 3 | AF44: 3 | AG44: 1 | AH44: - | AI44: https://cdn.sofifa.net/flags/no.png | AJ44: - | AK44: - | AL44: High | AM44: Medium | AN44: 69 | AO44: 62 | AP44: 61 | AQ44: 66 | AR44: 36 | AS44: 68 | AT44: 54 | AU44: 63 | AV44: 60 | AW44: 66 | AX44: 54 | AY44: 64 | AZ44: 48 | BA44: 43 | BB44: 63 | BC44: 65 | BD44: 68 | BE44: 69 | BF44: 70 | BG44: 68 | BH44: 80 | BI44: 68 | BJ44: 75 | BK44: 82 | BL44: 61 | BM44: 61 | BN44: 65 | BO44: 21 | BP44: 66 | BQ44: 67 | BR44: 43 | BS44: 59 | BT44: 35 | BU44: 39 | BV44: 40 | BW44: 14 | BX44: 13 | BY44: 13 | BZ44: 8 | CA44: 9 | CB44: 67 | CC44: 65 | CD44: 66 | CE44: 66 | CF44: 66 | CG44: 65 | CH44: 67 | CI44: 67 | CJ44: 65 | CK44: 67 | CL44: 56 | CM44: 55 | CN44: 56 | CO44: 54 | CP44: 50 | CQ44: 54 | CR44: 19
A45: 44 | B45: Bentancur | C45: Midfield | D45: CM | E45: Spurs | F45: 82 | G45: 20 | H45: R. Bentancur | I45: Rodrigo Bentancur | J45: 79 | K45: 83 | L45: 24500000 | M45: CM | N45: CDM | O45: Uruguay | P45: https://cdn.sofifa.net/players/227/535/23_60.png | Q45: 25 | R45: 187 | S45: 73 | T45: 2107 | U45: 443 | V45: Tottenham Hotspur | W45: 85000 | X45: 48400000 | Y45: CM | Z45: 2026 | AA45: 30 | AB45: 2022 | AC45: - | AD45: Right | AE45: 4 | AF45: 4 | AG45: 2 | AH45: - | AI45: https://cdn.sofifa.net/flags/uy.png | AJ45: - | AK45: - | AL45: Medium | AM45: Medium | AN45: 67 | AO45: 62 | AP45: 79 | AQ45: 80 | AR45: 78 | AS45: 77 | AT45: 76 | AU45: 55 | AV45: 62 | AW45: 83 | AX45: 71 | AY45: 82 | AZ45: 71 | BA45: 68 | BB45: 81 | BC45: 83 | BD45: 66 | BE45: 68 | BF45: 70 | BG45: 77 | BH45: 74 | BI45: 69 | BJ45: 73 | BK45: 86 | BL45: 72 | BM45: 65 | BN45: 78 | BO45: 78 | BP45: 64 | BQ45: 78 | BR45: 64 | BS45: 81 | BT45: 79 | BU45: 81 | BV45: 78 | BW45: 8 | BX45: 7 | BY45: 14 | BZ45: 14 | CA45: 12 | CB45: 71 | CC45: 74 | CD45: 73 | CE45: 73 | CF45: 73 | CG45: 74 | CH45: 78 | CI45: 78 | CJ45: 81 | CK45: 78 | CL45: 81 | CM45: 82 | CN45: 81 | CO45: 80 | CP45: 78 | CQ45: 80 | CR45: 20
A46: 45 | B46: Koke | C46: Midfield | D46: CM | E46: Atletico Madrid | F46: 82 | G46: 20 | H46: Koke | I46: Jorge Resurrección | J46: 83 | K46: 83 | L46: 34500000 | M46: CM,CDM | N46: CM | O46: Spain | P46: https://cdn.sofifa.net/players/193/747/23_60.png | Q46: 30 | R46: 176 | S46: 75 | T46: 2192 | U46: 462 | V46: Atlético de Madrid | W46: 74000 | X46: 70700000 | Y46: CM | Z46: 2024 | AA46: 6 | AB46: 2011 | AC46: - | AD46: Right | AE46: 4 | AF46: 3 | AG46: 3 | AH46: Spain | AI46: https://cdn.sofifa.net/flags/es.png | AJ46: CM | AK46: 8 | AL46: Medium | AM46: Medium | AN46: 70 | AO46: 72 | AP46: 84 | AQ46: 79 | AR46: 78 | AS46: 79 | AT46: 85 | AU46: 69 | AV46: 61 | AW46: 86 | AX46: 56 | AY46: 77 | AZ46: 84 | BA46: 77 | BB46: 84 | BC46: 81 | BD46: 72 | BE46: 69 | BF46: 72 | BG46: 84 | BH46: 81 | BI46: 81 | BJ46: 59 | BK46: 91 | BL46: 75 | BM46: 75 | BN46: 78 | BO46: 82 | BP46: 76 | BQ46: 83 | BR46: 67 | BS46: 85 | BT46: 81 | BU46: 82 | BV46: 70 | BW46: 14 | BX46: 12 | BY46: 5 | BZ46: 10 | CA46: 13 | CB46: 77 | CC46: 78 | CD46: 78 | CE46: 78 | CF46: 78 | CG46: 78 | CH46: 82 | CI46: 83 | CJ46: 83 | CK46: 83 | CL46: 83 | CM46: 83 | CN46: 83 | CO46: 82 | CP46: 80 | CQ46: 82 | CR46: 23
A47: 46 | B47: Xhaka | C47: Midfield | D47: CM | E47: Bayer Leverkusen | F47: 82 | G47: 20 | H47: T. Xhaka | I47: Taulant Xhaka | J47: 70 | K47: 70 | L47: 1100000 | M47: CDM | N47: CDM | O47: Albania | P47: https://cdn.sofifa.net/players/199/504/23_60.png | Q47: 31 | R47: 172 | S47: 72 | T47: 1923 | U47: 409 | V47: FC Basel 1893 | W47: 10000 | X47: 1700000 | Y47: SUB | Z47: 2024 | AA47: 34 | AB47: 2010 | AC47: - | AD47: Right | AE47: 4 | AF47: 3 | AG47: 1 | AH47: - | AI47: - | AJ47: - | AK47: - | AL47: Medium | AM47: High | AN47: 70 | AO47: 62 | AP47: 67 | AQ47: 66 | AR47: 65 | AS47: 79 | AT47: 70 | AU47: 54 | AV47: 50 | AW47: 71 | AX47: 52 | AY47: 65 | AZ47: 53 | BA47: 63 | BB47: 68 | BC47: 66 | BD47: 66 | BE47: 73 | BF47: 67 | BG47: 63 | BH47: 73 | BI47: 73 | BJ47: 71 | BK47: 89 | BL47: 73 | BM47: 75 | BN47: 85 | BO47: 66 | BP47: 61 | BQ47: 61 | BR47: 55 | BS47: 73 | BT47: 67 | BU47: 67 | BV47: 68 | BW47: 11 | BX47: 8 | BY47: 14 | BZ47: 14 | CA47: 11 | CB47: 65 | CC47: 65 | CD47: 64 | CE47: 64 | CF47: 64 | CG47: 65 | CH47: 67 | CI47: 69 | CJ47: 69 | CK47: 69 | CL47: 70 | CM47: 70 | CN47: 70 | CO47: 70 | CP47: 69 | CQ47: 70 | CR47: 19
A48: 47 | B48: Enzo Fernandez | C48: Midfield | D48: CDM | E48: Chelsea | F48: 81 | G48: 20 | H48: E. Fernández | I48: Enzo Fernández | J48: 78 | K48: 87 | L48: 31500000 | M48: CM,CDM | N48: CM | O48: Argentina | P48: https://cdn.sofifa.net/players/247/090/23_60.png | Q48: 21 | R48: 180 | S48: 77 | T48: 2133 | U48: 451 | V48: SL Benfica | W48: 12000 | X48: 69300000 | Y48: CM | Z48: 2027 | AA48: 13 | AB48: 2022 | AC48: - | AD48: Right | AE48: 4 | AF48: 3 | AG48: 1 | AH48: - | AI48: https://cdn.sofifa.net/flags/ar.png | AJ48: - | AK48: - | AL48: High | AM48: High | AN48: 74 | AO48: 71 | AP48: 76 | AQ48: 78 | AR48: 72 | AS48: 80 | AT48: 66 | AU48: 64 | AV48: 66 | AW48: 80 | AX48: 70 | AY48: 77 | AZ48: 74 | BA48: 69 | BB48: 75 | BC48: 80 | BD48: 77 | BE48: 72 | BF48: 76 | BG48: 77 | BH48: 77 | BI48: 83 | BJ48: 70 | BK48: 83 | BL48: 79 | BM48: 73 | BN48: 82 | BO48: 70 | BP48: 79 | BQ48: 80 | BR48: 74 | BS48: 80 | BT48: 72 | BU48: 75 | BV48: 74 | BW48: 8 | BX48: 6 | BY48: 7 | BZ48: 8 | CA48: 10 | CB48: 76 | CC48: 75 | CD48: 76 | CE48: 76 | CF48: 76 | CG48: 75 | CH48: 79 | CI48: 78 | CJ48: 80 | CK48: 78 | CL48: 77 | CM48: 79 | CN48: 77 | CO48: 76 | CP48: 76 | CQ48: 76 | CR48: 18
A49: 48 | B49: Marcel Sabitzer | C49: Midfield | D49: CM | E49: Dortmund | F49: 81 | G49: 20 | H49: M. Sabitzer | I49: Marcel Sabitzer | J49: 80 | K49: 80 | L49: 21000000 | M49: CM,CDM,CAM | N49: CM | O49: Austria | P49: https://cdn.sofifa.net/players/204/923/23_60.png | Q49: 28 | R49: 178 | S49: 76 | T49: 2172 | U49: 453 | V49: FC Bayern München | W49: 67000 | X49: 34700000 | Y49: SUB | Z49: 2025 | AA49: 18 | AB49: 2021 | AC49: - | AD49: Right | AE49: 4 | AF49: 3 | AG49: 3 | AH49: Austria | AI49: https://cdn.sofifa.net/flags/at.png | AJ49: CAM | AK49: 9 | AL49: High | AM49: High | AN49: 72 | AO49: 81 | AP49: 79 | AQ49: 79 | AR49: 66 | AS49: 76 | AT49: 74 | AU49: 79 | AV49: 60 | AW49: 82 | AX49: 81 | AY49: 79 | AZ49: 76 | BA49: 78 | BB49: 81 | BC49: 82 | BD49: 73 | BE49: 71 | BF49: 74 | BG49: 80 | BH49: 77 | BI49: 85 | BJ49: 69 | BK49: 80 | BL49: 75 | BM49: 85 | BN49: 75 | BO49: 65 | BP49: 77 | BQ49: 80 | BR49: 72 | BS49: 79 | BT49: 69 | BU49: 68 | BV49: 59 | BW49: 11 | BX49: 13 | BY49: 14 | BZ49: 15 | CA49: 13 | CB49: 80 | CC49: 78 | CD49: 79 | CE49: 79 | CF49: 79 | CG49: 78 | CH49: 80 | CI49: 80 | CJ49: 80 | CK49: 80 | CL49: 76 | CM49: 78 | CN49: 76 | CO49: 74 | CP49: 72 | CQ49: 74 | CR49: 23
A50: 49 | B50: Lo Celso | C50: Midfield | D50: CAM | E50: Spurs | F50: 81 | G50: 20 | H50: G. Lo Celso | I50: Giovani Lo Celso | J50: 81 | K50: 83 | L50: 31500000 | M50: CM,ST,LM | N50: CAM | O50: Argentina | P50: https://cdn.sofifa.net/players/226/226/23_60.png | Q50: 26 | R50: 177 | S50: 68 | T50: 2162 | U50: 453 | V50: Villarreal CF | W50: 100000 | X50: 0 | Y50: LM | Z50: 2023 | AA50: 17 | AB50: 2020 | AC50: TRUE | AD50: Left | AE50: 3 | AF50: 4 | AG50: 1 | AH50: Argentina | AI50: https://cdn.sofifa.net/flags/ar.png | AJ50: CM | AK50: 20 | AL50: High | AM50: Medium | AN50: 71 | AO50: 75 | AP50: 83 | AQ50: 84 | AR50: 68 | AS50: 72 | AT50: 78 | AU50: 73 | AV50: 62 | AW50: 84 | AX50: 71 | AY50: 85 | AZ50: 82 | BA50: 79 | BB50: 83 | BC50: 85 | BD50: 74 | BE50: 69 | BF50: 81 | BG50: 82 | BH50: 80 | BI50: 82 | BJ50: 56 | BK50: 75 | BL50: 69 | BM50: 74 | BN50: 82 | BO50: 70 | BP50: 75 | BQ50: 85 | BR50: 65 | BS50: 83 | BT50: 64 | BU50: 73 | BV50: 68 | BW50: 10 | BX50: 7 | BY50: 10 | BZ50: 15 | CA50: 14 | CB50: 78 | CC50: 80 | CD50: 80 | CE50: 80 | CF50: 80 | CG50: 80 | CH50: 83 | CI50: 82 | CJ50: 83 | CK50: 82 | CL50: 77 | CM50: 79 | CN50: 77 | CO50: 75 | CP50: 73 | CQ50: 75 | CR50: 21
A51: 50 | B51: Ugarte | C51: Midfield | D51: CDM | E51: PSG | F51: 81 | G51: 20 | H51: M. Ugarte | I51: Manuel Ugarte | J51: 77 | K51: 85 | L51: 23500000 | M51: CM,CDM | N51: CM | O51: Uruguay | P51: https://cdn.sofifa.net/players/253/306/23_60.png | Q51: 21 | R51: 182 | S51: 77 | T51: 1943 | U51: 432 | V51: Sporting CP | W51: 11000 | X51: 51700000 | Y51: CM | Z51: 2026 | AA51: 15 | AB51: 2021 | AC51: - | AD51: Right | AE51: 3 | AF51: 3 | AG51: 1 | AH51: - | AI51: https://cdn.sofifa.net/flags/uy.png | AJ51: - | AK51: - | AL51: High | AM51: High | AN51: 72 | AO51: 63 | AP51: 71 | AQ51: 77 | AR51: 73 | AS51: 76 | AT51: 58 | AU51: 65 | AV51: 39 | AW51: 78 | AX51: 45 | AY51: 79 | AZ51: 54 | BA51: 50 | BB51: 77 | BC51: 79 | BD51: 71 | BE51: 72 | BF51: 69 | BG51: 77 | BH51: 60 | BI51: 62 | BJ51: 53 | BK51: 82 | BL51: 75 | BM51: 65 | BN51: 76 | BO51: 78 | BP51: 73 | BQ51: 75 | BR51: 50 | BS51: 84 | BT51: 77 | BU51: 76 | BV51: 75 | BW51: 6 | BX51: 10 | BY51: 16 | BZ51: 8 | CA51: 13 | CB51: 70 | CC51: 73 | CD51: 73 | CE51: 73 | CF51: 73 | CG51: 73 | CH51: 77 | CI51: 76 | CJ51: 79 | CK51: 76 | CL51: 77 | CM51: 79 | CN51: 77 | CO51: 75 | CP51: 74 | CQ51: 75 | CR51: 19
A52: 51 | B52: Camavinga | C52: Midfield | D52: CM | E52: Real Madrid | F52: 80 | G52: 20 | H52: E. Camavinga | I52: Eduardo Camavinga | J52: 79 | K52: 89 | L52: 38000000 | M52: CM,CDM | N52: CDM | O52: France | P52: https://cdn.sofifa.net/players/248/243/23_60.png | Q52: 19 | R52: 182 | S52: 68 | T52: 2125 | U52: 455 | V52: Real Madrid CF | W52: 78000 | X52: 85500000 | Y52: SUB | Z52: 2027 | AA52: 12 | AB52: 2021 | AC52: - | AD52: Left | AE52: 3 | AF52: 4 | AG52: 3 | AH52: - | AI52: https://cdn.sofifa.net/flags/fr.png | AJ52: - | AK52: - | AL52: High | AM52: High | AN52: 76 | AO52: 66 | AP52: 78 | AQ52: 81 | AR52: 76 | AS52: 78 | AT52: 70 | AU52: 62 | AV52: 64 | AW52: 84 | AX52: 59 | AY52: 80 | AZ52: 72 | BA52: 59 | BB52: 81 | BC52: 83 | BD52: 75 | BE52: 76 | BF52: 81 | BG52: 79 | BH52: 78 | BI52: 73 | BJ52: 70 | BK52: 81 | BL52: 78 | BM52: 69 | BN52: 78 | BO52: 77 | BP52: 73 | BQ52: 77 | BR52: 62 | BS52: 82 | BT52: 75 | BU52: 80 | BV52: 79 | BW52: 12 | BX52: 6 | BY52: 8 | BZ52: 12 | CA52: 12 | CB52: 76 | CC52: 76 | CD52: 76 | CE52: 76 | CF52: 76 | CG52: 76 | CH52: 81 | CI52: 80 | CJ52: 82 | CK52: 80 | CL52: 81 | CM52: 83 | CN52: 81 | CO52: 81 | CP52: 80 | CQ52: 81 | CR52: 21
A53: 52 | B53: Gavi | C53: Midfield | D53: CM | E53: Barcelona | F53: 80 | G53: 20 | H53: Gavi | I53: Pablo Martín Páez Gavira | J53: 79 | K53: 88 | L53: 36000000 | M53: CM,LW,RW | N53: CAM | O53: Spain | P53: https://cdn.sofifa.net/players/264/240/23_60.png | Q53: 17 | R53: 173 | S53: 68 | T53: 2022 | U53: 432 | V53: FC Barcelona | W53: 17000 | X53: 81000000 | Y53: SUB | Z53: 2026 | AA53: 30 | AB53: 2020 | AC53: - | AD53: Right | AE53: 3 | AF53: 3 | AG53: 1 | AH53: - | AI53: https://cdn.sofifa.net/flags/es.png | AJ53: - | AK53: - | AL53: High | AM53: High | AN53: 76 | AO53: 64 | AP53: 77 | AQ53: 83 | AR53: 65 | AS53: 67 | AT53: 69 | AU53: 68 | AV53: 42 | AW53: 83 | AX53: 49 | AY53: 83 | AZ53: 74 | BA53: 47 | BB53: 79 | BC53: 82 | BD53: 77 | BE53: 75 | BF53: 86 | BG53: 79 | BH53: 90 | BI53: 56 | BJ53: 70 | BK53: 79 | BL53: 55 | BM53: 67 | BN53: 82 | BO53: 74 | BP53: 78 | BQ53: 81 | BR53: 51 | BS53: 74 | BT53: 59 | BU53: 72 | BV53: 66 | BW53: 8 | BX53: 10 | BY53: 11 | BZ53: 7 | CA53: 13 | CB53: 71 | CC53: 78 | CD53: 77 | CE53: 77 | CF53: 77 | CG53: 78 | CH53: 81 | CI53: 80 | CJ53: 81 | CK53: 80 | CL53: 76 | CM53: 77 | CN53: 76 | CO53: 74 | CP53: 69 | CQ53: 74 | CR53: 19
A54: 53 | B54: Alexis Mac Allister | C54: Midfield | D54: CM | E54: Liverpool | F54: 78 | G54: 20 | H54: A. Mac Allister | I54: Alexis Mac Allister | J54: 76 | K54: 82 | L54: 12000000 | M54: CAM,CM | N54: CAM | O54: Argentina | P54: https://cdn.sofifa.net/players/239/837/23_60.png | Q54: 23 | R54: 176 | S54: 72 | T54: 2020 | U54: 417 | V54: Brighton & Hove Albion | W54: 49000 | X54: 25200000 | Y54: CM | Z54: 2023 | AA54: 10 | AB54: 2019 | AC54: - | AD54: Right | AE54: 3 | AF54: 3 | AG54: 1 | AH54: - | AI54: https://cdn.sofifa.net/flags/ar.png | AJ54: - | AK54: - | AL54: Medium | AM54: Medium | AN54: 69 | AO54: 77 | AP54: 78 | AQ54: 75 | AR54: 56 | AS54: 62 | AT54: 79 | AU54: 77 | AV54: 61 | AW54: 77 | AX54: 73 | AY54: 75 | AZ54: 83 | BA54: 81 | BB54: 76 | BC54: 78 | BD54: 73 | BE54: 66 | BF54: 71 | BG54: 74 | BH54: 72 | BI54: 76 | BJ54: 64 | BK54: 68 | BL54: 63 | BM54: 80 | BN54: 51 | BO54: 45 | BP54: 77 | BQ54: 77 | BR54: 77 | BS54: 74 | BT54: 65 | BU54: 54 | BV54: 51 | BW54: 7 | BX54: 10 | BY54: 14 | BZ54: 15 | CA54: 10 | CB54: 76 | CC54: 76 | CD54: 76 | CE54: 76 | CF54: 76 | CG54: 76 | CH54: 78 | CI54: 77 | CJ54: 75 | CK54: 77 | CL54: 68 | CM54: 67 | CN54: 68 | CO54: 66 | CP54: 61 | CQ54: 66 | CR54: 20
A55: 54 | B55: N'golo Kante | C55: Midfield | D55: CDM | E55: Chelsea | F55: 88 | G55: 40 | H55: N. Kanté | I55: N'Golo Kanté | J55: 89 | K55: 89 | L55: 72000000 | M55: CDM,CM | N55: CDM | O55: France | P55: https://cdn.sofifa.net/players/215/914/23_60.png | Q55: 31 | R55: 168 | S55: 70 | T55: 2154 | U55: 462 | V55: Chelsea | W55: 220000 | X55: 133199999 | Y55: CM | Z55: 2023 | AA55: 7 | AB55: 2016 | AC55: - | AD55: Right | AE55: 3 | AF55: 2 | AG55: 4 | AH55: France | AI55: https://cdn.sofifa.net/flags/fr.png | AJ55: CDM | AK55: 13 | AL55: Medium | AM55: High | AN55: 72 | AO55: 66 | AP55: 74 | AQ55: 81 | AR55: 87 | AS55: 82 | AT55: 68 | AU55: 65 | AV55: 54 | AW55: 82 | AX55: 56 | AY55: 78 | AZ55: 49 | BA55: 49 | BB55: 76 | BC55: 81 | BD55: 77 | BE55: 68 | BF55: 78 | BG55: 93 | BH55: 92 | BI55: 71 | BJ55: 75 | BK55: 95 | BL55: 72 | BM55: 65 | BN55: 93 | BO55: 91 | BP55: 72 | BQ55: 77 | BR55: 54 | BS55: 84 | BT55: 90 | BU55: 93 | BV55: 86 | BW55: 15 | BX55: 12 | BY55: 10 | BZ55: 7 | CA55: 10 | CB55: 75 | CC55: 76 | CD55: 76 | CE55: 76 | CF55: 76 | CG55: 76 | CH55: 80 | CI55: 81 | CJ55: 84 | CK55: 81 | CL55: 87 | CM55: 89 | CN55: 87 | CO55: 87 | CP55: 87 | CQ55: 87 | CR55: 23
A56: 55 | B56: Daniel Parejo Munoz | C56: Midfield | D56: CM | E56: Villarreal CF | F56: 86 | G56: 30 | H56: Parejo | I56: Daniel Parejo Muñoz | J56: 86 | K56: 86 | L56: 42000000 | M56: CM | N56: CM | O56: Spain | P56: https://cdn.sofifa.net/players/189/513/23_60.png | Q56: 33 | R56: 182 | S56: 74 | T56: 2162 | U56: 442 | V56: Villarreal CF | W56: 64000 | X56: 88200000 | Y56: CM | Z56: 2024 | AA56: 10 | AB56: 2020 | AC56: - | AD56: Right | AE56: 4 | AF56: 3 | AG56: 2 | AH56: - | AI56: https://cdn.sofifa.net/flags/es.png | AJ56: - | AK56: - | AL56: Medium | AM56: Medium | AN56: 50 | AO56: 83 | AP56: 90 | AQ56: 80 | AR56: 71 | AS56: 68 | AT56: 86 | AU56: 83 | AV56: 61 | AW56: 92 | AX56: 72 | AY56: 81 | AZ56: 88 | BA56: 90 | BB56: 90 | BC56: 86 | BD56: 52 | BE56: 49 | BF56: 63 | BG56: 79 | BH56: 72 | BI56: 81 | BJ56: 49 | BK56: 76 | BL56: 70 | BM56: 88 | BN56: 58 | BO56: 80 | BP56: 81 | BQ56: 90 | BR56: 88 | BS56: 85 | BT56: 70 | BU56: 70 | BV56: 69 | BW56: 5 | BX56: 9 | BY56: 12 | BZ56: 14 | CA56: 8 | CB56: 79 | CC56: 80 | CD56: 80 | CE56: 80 | CF56: 80 | CG56: 80 | CH56: 85 | CI56: 82 | CJ56: 86 | CK56: 82 | CL56: 78 | CM56: 81 | CN56: 78 | CO56: 76 | CP56: 73 | CQ56: 76 | CR56: 19
A57: 56 | B57: Paul Pogba | C57: Midfield | D57: CM | E57: Juventus FC | F57: 85 | G57: 30 | H57: P. Pogba | I57: Paul Pogba | J57: 85 | K57: 85 | L57: 52500000 | M57: CM,CDM,LM | N57: CM | O57: France | P57: https://cdn.sofifa.net/players/195/864/23_60.png | Q57: 29 | R57: 191 | S57: 84 | T57: 2170 | U57: 459 | V57: Juventus | W57: 165000 | X57: 89300000 | Y57: SUB | Z57: 2026 | AA57: 10 | AB57: 2022 | AC57: - | AD57: Right | AE57: 4 | AF57: 5 | AG57: 4 | AH57: France | AI57: https://cdn.sofifa.net/flags/fr.png | AJ57: CDM | AK57: 6 | AL57: Medium | AM57: Low | AN57: 67 | AO57: 80 | AP57: 85 | AQ57: 85 | AR57: 62 | AS57: 80 | AT57: 73 | AU57: 74 | AV57: 74 | AW57: 87 | AX57: 84 | AY57: 89 | AZ57: 85 | BA57: 82 | BB57: 92 | BC57: 87 | BD57: 60 | BE57: 72 | BF57: 71 | BG57: 77 | BH57: 65 | BI57: 90 | BJ57: 80 | BK57: 65 | BL57: 88 | BM57: 84 | BN57: 79 | BO57: 62 | BP57: 77 | BQ57: 90 | BR57: 80 | BS57: 85 | BT57: 53 | BU57: 67 | BV57: 63 | BW57: 5 | BX57: 6 | BY57: 2 | BZ57: 4 | CA57: 3 | CB57: 83 | CC57: 80 | CD57: 82 | CE57: 82 | CF57: 82 | CG57: 80 | CH57: 85 | CI57: 83 | CJ57: 85 | CK57: 83 | CL57: 74 | CM57: 78 | CN57: 74 | CO57: 72 | CP57: 73 | CQ57: 72 | CR57: 15
A58: 57 | B58: Musiala | C58: Midfield | D58: CAM | E58: Bayern Munich | F58: 83 | G58: 20 | H58: J. Musiala | I58: Jamal Musiala | J58: 81 | K58: 90 | L58: 55500000 | M58: CM,LM,CAM | N58: CAM | O58: Germany | P58: https://cdn.sofifa.net/players/256/790/23_60.png | Q58: 19 | R58: 183 | S58: 70 | T58: 2012 | U58: 434 | V58: FC Bayern München | W58: 39000 | X58: 102700000 | Y58: SUB | Z58: 2026 | AA58: 42 | AB58: 2020 | AC58: - | AD58: Right | AE58: 4 | AF58: 4 | AG58: 1 | AH58: Germany | AI58: https://cdn.sofifa.net/flags/de.png | AJ58: SUB | AK58: 14 | AL58: Medium | AM58: Medium | AN58: 76 | AO58: 73 | AP58: 75 | AQ58: 87 | AR58: 63 | AS58: 60 | AT58: 66 | AU58: 76 | AV58: 49 | AW58: 83 | AX58: 63 | AY58: 88 | AZ58: 64 | BA58: 48 | BB58: 75 | BC58: 86 | BD58: 81 | BE58: 72 | BF58: 91 | BG58: 82 | BH58: 92 | BI58: 71 | BJ58: 55 | BK58: 77 | BL58: 53 | BM58: 73 | BN58: 59 | BO58: 65 | BP58: 76 | BQ58: 78 | BR58: 51 | BS58: 82 | BT58: 64 | BU58: 63 | BV58: 69 | BW58: 6 | BX58: 9 | BY58: 8 | BZ58: 8 | CA58: 11 | CB58: 76 | CC58: 80 | CD58: 80 | CE58: 80 | CF58: 80 | CG58: 80 | CH58: 83 | CI58: 82 | CJ58: 81 | CK58: 82 | CL58: 75 | CM58: 74 | CN58: 75 | CO58: 73 | CP58: 66 | CQ58: 73 | CR58: 19
A59: 58 | B59: Thibaut Courtois | C59: Goalkeeper | D59: GK | E59: Real Madrid | F59: 90 | G59: 40 | H59: T. Courtois | I59: Thibaut Courtois | J59: 90 | K59: 91 | L59: 90000000 | M59: GK | N59: GK | O59: Belgium | P59: https://cdn.sofifa.net/players/192/119/23_60.png | Q59: 30 | R59: 199 | S59: 96 | T59: 1334 | U59: 473 | V59: Real Madrid CF | W59: 250000 | X59: 191300000 | Y59: GK | Z59: 2026 | AA59: 1 | AB59: 2018 | AC59: - | AD59: Left | AE59: 3 | AF59: 1 | AG59: 4 | AH59: Belgium | AI59: https://cdn.sofifa.net/flags/be.png | AJ59: GK | AK59: 1 | AL59: Medium | AM59: Medium | AN59: 84 | AO59: 89 | AP59: 75 | AQ59: 90 | AR59: 46 | AS59: 89 | AT59: 14 | AU59: 14 | AV59: 13 | AW59: 33 | AX59: 12 | AY59: 13 | AZ59: 19 | BA59: 20 | BB59: 35 | BC59: 23 | BD59: 42 | BE59: 52 | BF59: 63 | BG59: 84 | BH59: 45 | BI59: 56 | BJ59: 68 | BK59: 38 | BL59: 70 | BM59: 17 | BN59: 23 | BO59: 15 | BP59: 13 | BQ59: 44 | BR59: 27 | BS59: 66 | BT59: 20 | BU59: 18 | BV59: 16 | BW59: 84 | BX59: 89 | BY59: 75 | BZ59: 89 | CA59: 90 | CB59: 34 | CC59: 29 | CD59: 31 | CE59: 31 | CF59: 31 | CG59: 29 | CH59: 35 | CI59: 34 | CJ59: 35 | CK59: 34 | CL59: 32 | CM59: 34 | CN59: 32 | CO59: 32 | CP59: 32 | CQ59: 32 | CR59: 90
A60: 59 | B60: Allison | C60: Goalkeeper | D60: GK | E60: Liverpool | F60: 89 | G60: 40 | H60: Allyson | I60: Allyson Aires dos Santos | J60: 68 | K60: 68 | L60: 825000 | M60: CB | N60: CB | O60: Brazil | P60: https://cdn.sofifa.net/players/269/870/23_60.png | Q60: 31 | R60: 186 | S60: 77 | T60: 1604 | U60: 352 | V60: Ümraniyespor | W60: 6000 | X60: 1600000 | Y60: CB | Z60: 2024 | AA60: 33 | AB60: 2022 | AC60: - | AD60: Right | AE60: 3 | AF60: 2 | AG60: 1 | AH60: - | AI60: https://cdn.sofifa.net/flags/br.png | AJ60: - | AK60: - | AL60: Medium | AM60: Medium | AN60: 71 | AO60: 35 | AP60: 49 | AQ60: 58 | AR60: 69 | AS60: 70 | AT60: 41 | AU60: 33 | AV60: 70 | AW60: 55 | AX60: 41 | AY60: 56 | AZ60: 37 | BA60: 28 | BB60: 59 | BC60: 60 | BD60: 73 | BE60: 70 | BF60: 54 | BG60: 70 | BH60: 59 | BI60: 41 | BJ60: 75 | BK60: 62 | BL60: 74 | BM60: 32 | BN60: 68 | BO60: 67 | BP60: 27 | BQ60: 48 | BR60: 48 | BS60: 68 | BT60: 69 | BU60: 68 | BV60: 71 | BW60: 7 | BX60: 7 | BY60: 6 | BZ60: 14 | CA60: 14 | CB60: 53 | CC60: 52 | CD60: 51 | CE60: 51 | CF60: 51 | CG60: 52 | CH60: 54 | CI60: 56 | CJ60: 57 | CK60: 56 | CL60: 64 | CM60: 66 | CN60: 64 | CO60: 67 | CP60: 68 | CQ60: 67 | CR60: 19
A61: 60 | B61: Ederson | C61: Goalkeeper | D61: GK | E61: Manchester City | F61: 89 | G61: 40 | H61: Ederson | I61: Ederson Santana de Moraes | J61: 89 | K61: 91 | L61: 88000000 | M61: GK | N61: GK | O61: Brazil | P61: https://cdn.sofifa.net/players/210/257/23_60.png | Q61: 28 | R61: 188 | S61: 86 | T61: 1583 | U61: 502 | V61: Manchester City | W61: 210000 | X61: 169400000 | Y61: GK | Z61: 2026 | AA61: 31 | AB61: 2017 | AC61: - | AD61: Left | AE61: 3 | AF61: 1 | AG61: 3 | AH61: - | AI61: https://cdn.sofifa.net/flags/br.png | AJ61: - | AK61: - | AL61: Medium | AM61: Medium | AN61: 87 | AO61: 82 | AP61: 93 | AQ61: 88 | AR61: 64 | AS61: 88 | AT61: 20 | AU61: 14 | AV61: 14 | AW61: 61 | AX61: 18 | AY61: 23 | AZ61: 15 | BA61: 20 | BB61: 66 | BC61: 40 | BD61: 64 | BE61: 63 | BF61: 60 | BG61: 88 | BH61: 48 | BI61: 70 | BJ61: 66 | BK61: 41 | BL61: 78 | BM61: 18 | BN61: 38 | BO61: 27 | BP61: 20 | BQ61: 70 | BR61: 51 | BS61: 70 | BT61: 29 | BU61: 15 | BV61: 8 | BW61: 87 | BX61: 82 | BY61: 93 | BZ61: 88 | CA61: 88 | CB61: 43 | CC61: 41 | CD61: 43 | CE61: 43 | CF61: 43 | CG61: 41 | CH61: 50 | CI61: 47 | CJ61: 52 | CK61: 47 | CL61: 40 | CM61: 47 | CN61: 40 | CO61: 39 | CP61: 38 | CQ61: 39 | CR61: 90
A62: 61 | B62: Manuel Neuer | C62: Goalkeeper | D62: GK | E62: Bayern munich | F62: 89 | G62: 40 | H62: M. Neuer | I62: Manuel Neuer | J62: 90 | K62: 90 | L62: 13500000 | M62: GK | N62: GK | O62: Germany | P62: https://cdn.sofifa.net/players/167/495/23_60.png | Q62: 36 | R62: 193 | S62: 93 | T62: 1535 | U62: 501 | V62: FC Bayern München | W62: 72000 | X62: 22300000 | Y62: GK | Z62: 2024 | AA62: 1 | AB62: 2011 | AC62: - | AD62: Right | AE62: 4 | AF62: 1 | AG62: 5 | AH62: Germany | AI62: https://cdn.sofifa.net/flags/de.png | AJ62: GK | AK62: 1 | AL62: Medium | AM62: Medium | AN62: 87 | AO62: 88 | AP62: 91 | AQ62: 88 | AR62: 56 | AS62: 91 | AT62: 15 | AU62: 13 | AV62: 25 | AW62: 60 | AX62: 11 | AY62: 30 | AZ62: 14 | BA62: 11 | BB62: 68 | BC62: 46 | BD62: 54 | BE62: 60 | BF62: 51 | BG62: 87 | BH62: 35 | BI62: 68 | BJ62: 77 | BK62: 43 | BL62: 80 | BM62: 16 | BN62: 29 | BO62: 30 | BP62: 12 | BQ62: 70 | BR62: 47 | BS62: 70 | BT62: 17 | BU62: 10 | BV62: 11 | BW62: 87 | BX62: 88 | BY62: 91 | BZ62: 91 | CA62: 88 | CB62: 43 | CC62: 40 | CD62: 43 | CE62: 43 | CF62: 43 | CG62: 40 | CH62: 50 | CI62: 47 | CJ62: 53 | CK62: 47 | CL62: 39 | CM62: 46 | CN62: 39 | CO62: 38 | CP62: 37 | CQ62: 38 | CR62: 90
A63: 62 | B63: Jan Oblak | C63: Goalkeeper | D63: GK | E63: Atletico Madrid | F63: 88 | G63: 40 | H63: J. Oblak | I63: Jan Oblak | J63: 89 | K63: 91 | L63: 85500000 | M63: GK | N63: GK | O63: Slovenia | P63: https://cdn.sofifa.net/players/200/389/23_60.png | Q63: 29 | R63: 188 | S63: 87 | T63: 1402 | U63: 479 | V63: Atlético de Madrid | W63: 100000 | X63: 181700000 | Y63: GK | Z63: 2023 | AA63: 13 | AB63: 2014 | AC63: - | AD63: Right | AE63: 3 | AF63: 1 | AG63: 5 | AH63: - | AI63: - | AJ63: - | AK63: - | AL63: Medium | AM63: Medium | AN63: 86 | AO63: 90 | AP63: 78 | AQ63: 89 | AR63: 49 | AS63: 87 | AT63: 13 | AU63: 11 | AV63: 15 | AW63: 43 | AX63: 13 | AY63: 12 | AZ63: 13 | BA63: 14 | BB63: 40 | BC63: 30 | BD63: 43 | BE63: 58 | BF63: 65 | BG63: 87 | BH63: 49 | BI63: 59 | BJ63: 77 | BK63: 41 | BL63: 78 | BM63: 12 | BN63: 34 | BO63: 21 | BP63: 11 | BQ63: 65 | BR63: 11 | BS63: 68 | BT63: 27 | BU63: 12 | BV63: 18 | BW63: 86 | BX63: 90 | BY63: 78 | BZ63: 87 | CA63: 89 | CB63: 36 | CC63: 32 | CD63: 34 | CE63: 34 | CF63: 34 | CG63: 32 | CH63: 41 | CI63: 37 | CJ63: 41 | CK63: 37 | CL63: 35 | CM63: 40 | CN63: 35 | CO63: 35 | CP63: 36 | CQ63: 35 | CR63: 90
A64: 63 | B64: Ter Stegen | C64: Goalkeeper | D64: GK | E64: Barcelona | F64: 88 | G64: 40 | H64: M. ter Stegen | I64: Marc-André ter Stegen | J64: 88 | K64: 89 | L64: 68500000 | M64: GK | N64: GK | O64: Germany | P64: https://cdn.sofifa.net/players/192/448/23_60.png | Q64: 30 | R64: 187 | S64: 85 | T64: 1443 | U64: 480 | V64: FC Barcelona | W64: 210000 | X64: 145600000 | Y64: GK | Z64: 2025 | AA64: 1 | AB64: 2014 | AC64: - | AD64: Right | AE64: 4 | AF64: 1 | AG64: 4 | AH64: Germany | AI64: https://cdn.sofifa.net/flags/de.png | AJ64: SUB | AK64: 12 | AL64: Medium | AM64: Medium | AN64: 86 | AO64: 85 | AP64: 87 | AQ64: 90 | AR64: 47 | AS64: 85 | AT64: 18 | AU64: 14 | AV64: 11 | AW64: 61 | AX64: 14 | AY64: 21 | AZ64: 18 | BA64: 12 | BB64: 63 | BC64: 30 | BD64: 45 | BE64: 50 | BF64: 39 | BG64: 85 | BH64: 43 | BI64: 65 | BJ64: 79 | BK64: 35 | BL64: 78 | BM64: 10 | BN64: 43 | BO64: 22 | BP64: 11 | BQ64: 70 | BR64: 25 | BS64: 70 | BT64: 25 | BU64: 13 | BV64: 10 | BW64: 86 | BX64: 85 | BY64: 87 | BZ64: 85 | CA64: 90 | CB64: 38 | CC64: 35 | CD64: 38 | CE64: 38 | CF64: 38 | CG64: 35 | CH64: 45 | CI64: 42 | CJ64: 48 | CK64: 42 | CL64: 36 | CM64: 44 | CN64: 36 | CO64: 34 | CP64: 36 | CQ64: 34 | CR64: 89
A65: 64 | B65: Gianluigi Donnarumma | C65: Goalkeeper | D65: GK | E65: PSG | F65: 88 | G65: 40 | H65: G. Donnarumma | I65: Gianluigi Donnarumma | J65: 88 | K65: 92 | L65: 103500000 | M65: GK | N65: GK | O65: Italy | P65: https://cdn.sofifa.net/players/230/621/23_60.png | Q65: 23 | R65: 196 | S65: 90 | T65: 1375 | U65: 478 | V65: Paris Saint-Germain | W65: 110000 | X65: 199200000 | Y65: GK | Z65: 2026 | AA65: 99 | AB65: 2021 | AC65: - | AD65: Right | AE65: 3 | AF65: 1 | AG65: 3 | AH65: Italy | AI65: https://cdn.sofifa.net/flags/it.png | AJ65: GK | AK65: 21 | AL65: Medium | AM65: Medium | AN65: 90 | AO65: 83 | AP65: 79 | AQ65: 89 | AR65: 52 | AS65: 85 | AT65: 12 | AU65: 12 | AV65: 12 | AW65: 36 | AX65: 8 | AY65: 28 | AZ65: 12 | BA65: 14 | BB65: 34 | BC65: 30 | BD65: 50 | BE65: 55 | BF65: 64 | BG65: 85 | BH65: 38 | BI65: 59 | BJ65: 72 | BK65: 34 | BL65: 72 | BM65: 18 | BN65: 30 | BO65: 26 | BP65: 14 | BQ65: 60 | BR65: 24 | BS65: 65 | BT65: 20 | BU65: 14 | BV65: 16 | BW65: 90 | BX65: 83 | BY65: 79 | BZ65: 85 | CA65: 89 | CB65: 37 | CC65: 34 | CD65: 36 | CE65: 36 | CF65: 36 | CG65: 34 | CH65: 41 | CI65: 38 | CJ65: 40 | CK65: 38 | CL65: 34 | CM65: 37 | CN65: 34 | CO65: 34 | CP65: 34 | CQ65: 34 | CR65: 89
A66: 65 | B66: Mike Maignan | C66: Goalkeeper | D66: GK | E66: AC Milan | F66: 87 | G66: 30 | H66: M. Maignan | I66: Mike Maignan | J66: 87 | K66: 90 | L66: 80000000 | M66: GK | N66: GK | O66: France | P66: https://cdn.sofifa.net/players/215/698/23_60.png | Q66: 26 | R66: 191 | S66: 89 | T66: 1496 | U66: 477 | V66: AC Milan | W66: 90000 | X66: 142000000 | Y66: GK | Z66: 2026 | AA66: 16 | AB66: 2021 | AC66: - | AD66: Right | AE66: 4 | AF66: 1 | AG66: 2 | AH66: France | AI66: https://cdn.sofifa.net/flags/fr.png | AJ66: SUB | AK66: 16 | AL66: Medium | AM66: Medium | AN66: 85 | AO66: 82 | AP66: 85 | AQ66: 89 | AR66: 51 | AS66: 85 | AT66: 18 | AU66: 15 | AV66: 17 | AW66: 57 | AX66: 16 | AY66: 31 | AZ66: 38 | BA66: 16 | BB66: 53 | BC66: 40 | BD66: 50 | BE66: 53 | BF66: 41 | BG66: 85 | BH66: 56 | BI66: 64 | BJ66: 74 | BK66: 39 | BL66: 78 | BM66: 20 | BN66: 35 | BO66: 25 | BP66: 15 | BQ66: 61 | BR66: 15 | BS66: 66 | BT66: 23 | BU66: 16 | BV66: 19 | BW66: 85 | BX66: 82 | BY66: 85 | BZ66: 85 | CA66: 89 | CB66: 40 | CC66: 38 | CD66: 41 | CE66: 41 | CF66: 41 | CG66: 38 | CH66: 46 | CI66: 44 | CJ66: 47 | CK66: 44 | CL66: 38 | CM66: 43 | CN66: 38 | CO66: 36 | CP66: 37 | CQ66: 36 | CR66: 87
A67: 66 | B67: Kevin Trapp | C67: Goalkeeper | D67: GK | E67: Juventus | F67: 86 | G67: 30 | H67: K. Trapp | I67: Kevin Trapp | J67: 86 | K67: 86 | L67: 36000000 | M67: GK | N67: GK | O67: Germany | P67: https://cdn.sofifa.net/players/188/943/23_60.png | Q67: 31 | R67: 189 | S67: 84 | T67: 1252 | U67: 463 | V67: Eintracht Frankfurt | W67: 43000 | X67: 61200000 | Y67: GK | Z67: 2024 | AA67: 1 | AB67: 2019 | AC67: - | AD67: Right | AE67: 4 | AF67: 1 | AG67: 3 | AH67: Germany | AI67: https://cdn.sofifa.net/flags/de.png | AJ67: SUB | AK67: 22 | AL67: Medium | AM67: Medium | AN67: 84 | AO67: 82 | AP67: 79 | AQ67: 87 | AR67: 46 | AS67: 85 | AT67: 13 | AU67: 13 | AV67: 11 | AW67: 25 | AX67: 12 | AY67: 10 | AZ67: 14 | BA67: 12 | BB67: 12 | BC67: 24 | BD67: 43 | BE67: 50 | BF67: 42 | BG67: 83 | BH67: 37 | BI67: 59 | BJ67: 76 | BK67: 45 | BL67: 75 | BM67: 13 | BN67: 30 | BO67: 22 | BP67: 12 | BQ67: 46 | BR67: 17 | BS67: 64 | BT67: 15 | BU67: 14 | BV67: 10 | BW67: 84 | BX67: 82 | BY67: 79 | BZ67: 85 | CA67: 87 | CB67: 33 | CC67: 27 | CD67: 30 | CE67: 30 | CF67: 30 | CG67: 27 | CH67: 32 | CI67: 31 | CJ67: 31 | CK67: 31 | CL67: 31 | CM67: 32 | CN67: 31 | CO67: 31 | CP67: 32 | CQ67: 31 | CR67: 86
A68: 67 | B68: Wojciech Szczeny | C68: Goalkeeper | D68: GK | E68: Juventus | F68: 86 | G68: 30 | H68: W. Szczęsny | I68: Wojciech Szczęsny | J68: 86 | K68: 86 | L68: 33500000 | M68: GK | N68: GK | O68: Poland | P68: https://cdn.sofifa.net/players/186/153/23_60.png | Q68: 32 | R68: 195 | S68: 90 | T68: 1314 | U68: 462 | V68: Juventus | W68: 125000 | X68: 57000000 | Y68: RES | Z68: 2024 | AA68: 1 | AB68: 2017 | AC68: - | AD68: Right | AE68: 3 | AF68: 1 | AG68: 3 | AH68: Poland | AI68: https://cdn.sofifa.net/flags/pl.png | AJ68: GK | AK68: 1 | AL68: Medium | AM68: Medium | AN68: 86 | AO68: 81 | AP68: 73 | AQ68: 87 | AR68: 49 | AS68: 86 | AT68: 12 | AU68: 12 | AV68: 16 | AW68: 32 | AX68: 14 | AY68: 11 | AZ68: 16 | BA68: 14 | BB68: 36 | BC68: 22 | BD68: 51 | BE68: 47 | BF68: 55 | BG68: 82 | BH68: 51 | BI68: 55 | BJ68: 71 | BK68: 45 | BL68: 65 | BM68: 14 | BN68: 40 | BO68: 15 | BP68: 14 | BQ68: 48 | BR68: 18 | BS68: 65 | BT68: 20 | BU68: 13 | BV68: 12 | BW68: 86 | BX68: 81 | BY68: 73 | BZ68: 86 | CA68: 87 | CB68: 34 | CC68: 28 | CD68: 31 | CE68: 31 | CF68: 31 | CG68: 28 | CH68: 35 | CI68: 34 | CJ68: 36 | CK68: 34 | CL68: 31 | CM68: 34 | CN68: 31 | CO68: 31 | CP68: 32 | CQ68: 31 | CR68: 86
A69: 68 | B69: Emiliano Martinez | C69: Goalkeeper | D69: GK | E69: Aston villa | F69: 85 | G69: 30 | H69: E. Martínez | I69: Emiliano Martínez | J69: 84 | K69: 84 | L69: 29000000 | M69: GK | N69: GK | O69: Argentina | P69: https://cdn.sofifa.net/players/202/811/23_60.png | Q69: 29 | R69: 195 | S69: 88 | T69: 1457 | U69: 476 | V69: Aston Villa | W69: 95000 | X69: 55100000 | Y69: GK | Z69: 2027 | AA69: 1 | AB69: 2020 | AC69: - | AD69: Right | AE69: 4 | AF69: 1 | AG69: 3 | AH69: Argentina | AI69: https://cdn.sofifa.net/flags/ar.png | AJ69: GK | AK69: 23 | AL69: Medium | AM69: Medium | AN69: 85 | AO69: 83 | AP69: 82 | AQ69: 85 | AR69: 58 | AS69: 83 | AT69: 22 | AU69: 16 | AV69: 26 | AW69: 50 | AX69: 13 | AY69: 13 | AZ69: 22 | BA69: 20 | BB69: 59 | BC69: 35 | BD69: 59 | BE69: 57 | BF69: 49 | BG69: 80 | BH69: 49 | BI69: 62 | BJ69: 60 | BK69: 40 | BL69: 70 | BM69: 16 | BN69: 37 | BO69: 13 | BP69: 12 | BQ69: 66 | BR69: 42 | BS69: 60 | BT69: 11 | BU69: 20 | BV69: 20 | BW69: 85 | BX69: 83 | BY69: 82 | BZ69: 83 | CA69: 85 | CB69: 39 | CC69: 35 | CD69: 37 | CE69: 37 | CF69: 37 | CG69: 35 | CH69: 44 | CI69: 42 | CJ69: 46 | CK69: 42 | CL69: 36 | CM69: 41 | CN69: 36 | CO69: 36 | CP69: 35 | CQ69: 36 | CR69: 84
A70: 69 | B70: Yan Sommer | C70: Goalkeeper | D70: GK | E70: Bayern munich | F70: 85 | G70: 30 | H70: Y. Sommer | I70: Yann Sommer | J70: 85 | K70: 85 | L70: 17500000 | M70: GK | N70: GK | O70: Switzerland | P70: https://cdn.sofifa.net/players/177/683/23_60.png | Q70: 33 | R70: 183 | S70: 79 | T70: 1356 | U70: 467 | V70: Borussia Mönchengladbach | W70: 40000 | X70: 29800000 | Y70: GK | Z70: 2023 | AA70: 1 | AB70: 2014 | AC70: - | AD70: Right | AE70: 4 | AF70: 1 | AG70: 3 | AH70: - | AI70: https://cdn.sofifa.net/flags/ch.png | AJ70: - | AK70: - | AL70: Medium | AM70: Medium | AN70: 78 | AO70: 81 | AP70: 82 | AQ70: 90 | AR70: 50 | AS70: 86 | AT70: 13 | AU70: 13 | AV70: 10 | AW70: 40 | AX70: 8 | AY70: 15 | AZ70: 12 | BA70: 13 | BB70: 31 | BC70: 25 | BD70: 48 | BE70: 54 | BF70: 55 | BG70: 82 | BH70: 58 | BI70: 62 | BJ70: 73 | BK70: 45 | BL70: 68 | BM70: 12 | BN70: 38 | BO70: 21 | BP70: 15 | BQ70: 64 | BR70: 24 | BS70: 57 | BT70: 9 | BU70: 19 | BV70: 12 | BW70: 78 | BX70: 81 | BY70: 82 | BZ70: 86 | CA70: 90 | CB70: 35 | CC70: 32 | CD70: 34 | CE70: 34 | CF70: 34 | CG70: 32 | CH70: 39 | CI70: 37 | CJ70: 40 | CK70: 37 | CL70: 33 | CM70: 36 | CN70: 33 | CO70: 32 | CP70: 32 | CQ70: 32 | CR70: 85
A71: 70 | B71: Llories | C71: Goalkeeper | D71: GK | E71: Spurs | F71: 85 | G71: 30 | H71: H. Lloris | I71: Hugo Lloris | J71: 87 | K71: 87 | L71: 9000000 | M71: GK | N71: GK | O71: France | P71: https://cdn.sofifa.net/players/167/948/23_60.png | Q71: 35 | R71: 188 | S71: 82 | T71: 1399 | U71: 478 | V71: Tottenham Hotspur | W71: 80000 | X71: 17100000 | Y71: GK | Z71: 2024 | AA71: 1 | AB71: 2012 | AC71: - | AD71: Left | AE71: 1 | AF71: 1 | AG71: 4 | AH71: France | AI71: https://cdn.sofifa.net/flags/fr.png | AJ71: GK | AK71: 1 | AL71: Medium | AM71: Medium | AN71: 88 | AO71: 83 | AP71: 74 | AQ71: 88 | AR71: 61 | AS71: 84 | AT71: 13 | AU71: 10 | AV71: 9 | AW71: 54 | AX71: 15 | AY71: 12 | AZ71: 12 | BA71: 10 | BB71: 55 | BC71: 29 | BD71: 61 | BE71: 62 | BF71: 54 | BG71: 84 | BH71: 56 | BI71: 56 | BJ71: 74 | BK71: 41 | BL71: 43 | BM71: 14 | BN71: 31 | BO71: 25 | BP71: 9 | BQ71: 59 | BR71: 40 | BS71: 59 | BT71: 24 | BU71: 12 | BV71: 18 | BW71: 88 | BX71: 83 | BY71: 74 | BZ71: 84 | CA71: 88 | CB71: 34 | CC71: 33 | CD71: 35 | CE71: 35 | CF71: 35 | CG71: 33 | CH71: 42 | CI71: 40 | CJ71: 44 | CK71: 40 | CL71: 37 | CM71: 41 | CN71: 37 | CO71: 36 | CP71: 32 | CQ71: 36 | CR71: 87
A72: 71 | B72: Kobel | C72: Goalkeeper | D72: GK | E72: Dortmund | F72: 85 | G72: 30 | H72: G. Kobel | I72: Gregor Kobel | J72: 83 | K72: 88 | L72: 44000000 | M72: GK | N72: GK | O72: Switzerland | P72: https://cdn.sofifa.net/players/235/073/23_60.png | Q72: 24 | R72: 195 | S72: 88 | T72: 1251 | U72: 448 | V72: Borussia Dortmund | W72: 40000 | X72: 78100000 | Y72: GK | Z72: 2026 | AA72: 1 | AB72: 2021 | AC72: - | AD72: Right | AE72: 3 | AF72: 1 | AG72: 1 | AH72: - | AI72: https://cdn.sofifa.net/flags/ch.png | AJ72: - | AK72: - | AL72: Medium | AM72: Medium | AN72: 84 | AO72: 80 | AP72: 74 | AQ72: 88 | AR72: 43 | AS72: 79 | AT72: 13 | AU72: 10 | AV72: 13 | AW72: 39 | AX72: 10 | AY72: 24 | AZ72: 13 | BA72: 12 | BB72: 33 | BC72: 34 | BD72: 38 | BE72: 51 | BF72: 37 | BG72: 81 | BH72: 29 | BI72: 56 | BJ72: 68 | BK72: 30 | BL72: 81 | BM72: 10 | BN72: 24 | BO72: 14 | BP72: 10 | BQ72: 59 | BR72: 12 | BS72: 66 | BT72: 15 | BU72: 15 | BV72: 15 | BW72: 84 | BX72: 80 | BY72: 74 | BZ72: 79 | CA72: 88 | CB72: 34 | CC72: 32 | CD72: 34 | CE72: 34 | CF72: 34 | CG72: 32 | CH72: 38 | CI72: 36 | CJ72: 38 | CK72: 36 | CL72: 31 | CM72: 34 | CN72: 31 | CO72: 30 | CP72: 31 | CQ72: 30 | CR72: 84
A73: 72 | B73: Nick Pope | C73: Goalkeeper | D73: GK | E73: Newcastle United | F73: 83 | G73: 20 | H73: N. Pope | I73: Nick Pope | J73: 81 | K73: 81 | L73: 17000000 | M73: GK | N73: GK | O73: England | P73: https://cdn.sofifa.net/players/203/841/23_60.png | Q73: 30 | R73: 199 | S73: 76 | T73: 1286 | U73: 449 | V73: Newcastle United | W73: 75000 | X73: 32299999 | Y73: GK | Z73: 2026 | AA73: 22 | AB73: 2022 | AC73: - | AD73: Right | AE73: 3 | AF73: 1 | AG73: 1 | AH73: England | AI73: https://cdn.sofifa.net/flags/gb-eng.png | AJ73: SUB | AK73: 13 | AL73: Medium | AM73: Medium | AN73: 80 | AO73: 82 | AP73: 75 | AQ73: 83 | AR73: 49 | AS73: 80 | AT73: 11 | AU73: 14 | AV73: 11 | AW73: 29 | AX73: 14 | AY73: 15 | AZ73: 13 | BA73: 12 | BB73: 52 | BC73: 24 | BD73: 50 | BE73: 47 | BF73: 36 | BG73: 76 | BH73: 42 | BI73: 56 | BJ73: 72 | BK73: 37 | BL73: 75 | BM73: 15 | BN73: 36 | BO73: 21 | BP73: 13 | BQ73: 50 | BR73: 22 | BS73: 63 | BT73: 14 | BU73: 15 | BV73: 14 | BW73: 80 | BX73: 82 | BY73: 75 | BZ73: 80 | CA73: 83 | CB73: 33 | CC73: 28 | CD73: 31 | CE73: 31 | CF73: 31 | CG73: 28 | CH73: 34 | CI73: 33 | CJ73: 36 | CK73: 33 | CL73: 30 | CM73: 35 | CN73: 30 | CO73: 29 | CP73: 31 | CQ73: 29 | CR73: 81
A74: 73 | B74: Unai Simon | C74: Goalkeeper | D74: GK | E74: Athletic Bilbao | F74: 83 | G74: 20 | H74: Unai Simón | I74: Unai Simón Mendibil | J74: 83 | K74: 86 | L74: 37000000 | M74: GK | N74: GK | O74: Spain | P74: https://cdn.sofifa.net/players/230/869/23_60.png | Q74: 25 | R74: 190 | S74: 89 | T74: 1311 | U74: 457 | V74: Athletic Club de Bilbao | W74: 30000 | X74: 80500000 | Y74: GK | Z74: 2025 | AA74: 1 | AB74: 2015 | AC74: - | AD74: Right | AE74: 3 | AF74: 1 | AG74: 3 | AH74: Spain | AI74: https://cdn.sofifa.net/flags/es.png | AJ74: GK | AK74: 23 | AL74: Medium | AM74: Medium | AN74: 82 | AO74: 79 | AP74: 77 | AQ74: 85 | AR74: 49 | AS74: 85 | AT74: 16 | AU74: 14 | AV74: 18 | AW74: 41 | AX74: 17 | AY74: 12 | AZ74: 20 | BA74: 14 | BB74: 37 | BC74: 16 | BD74: 48 | BE74: 50 | BF74: 37 | BG74: 77 | BH74: 47 | BI74: 58 | BJ74: 66 | BK74: 44 | BL74: 76 | BM74: 13 | BN74: 29 | BO74: 26 | BP74: 14 | BQ74: 48 | BR74: 24 | BS74: 46 | BT74: 11 | BU74: 18 | BV74: 12 | BW74: 82 | BX74: 79 | BY74: 77 | BZ74: 85 | CA74: 85 | CB74: 35 | CC74: 28 | CD74: 31 | CE74: 31 | CF74: 31 | CG74: 28 | CH74: 35 | CI74: 34 | CJ74: 37 | CK74: 34 | CL74: 33 | CM74: 36 | CN74: 33 | CO74: 32 | CP74: 33 | CQ74: 32 | CR74: 85
A75: 74 | B75: Aaron Ramsdale | C75: Goalkeeper | D75: GK | E75: Southampton | F75: 82 | G75: 20 | H75: A. Ramsdale | I75: Aaron Ramsdale | J75: 82 | K75: 86 | L75: 34500000 | M75: GK | N75: GK | O75: England | P75: https://cdn.sofifa.net/players/233/934/23_60.png | Q75: 24 | R75: 191 | S75: 77 | T75: 1396 | U75: 455 | V75: Arsenal | W75: 62000 | X75: 68100000 | Y75: GK | Z75: 2025 | AA75: 32 | AB75: 2021 | AC75: - | AD75: Right | AE75: 3 | AF75: 1 | AG75: 1 | AH75: England | AI75: https://cdn.sofifa.net/flags/gb-eng.png | AJ75: SUB | AK75: 22 | AL75: Medium | AM75: Medium | AN75: 83 | AO75: 77 | AP75: 85 | AQ75: 84 | AR75: 48 | AS75: 78 | AT75: 15 | AU75: 14 | AV75: 15 | AW75: 54 | AX75: 16 | AY75: 18 | AZ75: 17 | BA75: 16 | BB75: 54 | BC75: 35 | BD75: 47 | BE75: 50 | BF75: 53 | BG75: 80 | BH75: 49 | BI75: 64 | BJ75: 66 | BK75: 35 | BL75: 59 | BM75: 15 | BN75: 35 | BO75: 24 | BP75: 18 | BQ75: 64 | BR75: 25 | BS75: 65 | BT75: 20 | BU75: 16 | BV75: 15 | BW75: 83 | BX75: 77 | BY75: 85 | BZ75: 78 | CA75: 84 | CB75: 37 | CC75: 35 | CD75: 38 | CE75: 38 | CF75: 38 | CG75: 35 | CH75: 43 | CI75: 40 | CJ75: 45 | CK75: 40 | CL75: 35 | CM75: 41 | CN75: 35 | CO75: 34 | CP75: 33 | CQ75: 34 | CR75: 83
A76: 75 | B76: Jordan Pickford | C76: Goalkeeper | D76: GK | E76: Everton | F76: 82 | G76: 20 | H76: J. Pickford | I76: Jordan Pickford | J76: 82 | K76: 84 | L76: 26000000 | M76: GK | N76: GK | O76: England | P76: https://cdn.sofifa.net/players/204/935/23_60.png | Q76: 28 | R76: 185 | S76: 77 | T76: 1503 | U76: 466 | V76: Everton | W76: 45000 | X76: 51400000 | Y76: GK | Z76: 2024 | AA76: 1 | AB76: 2017 | AC76: - | AD76: Left | AE76: 4 | AF76: 1 | AG76: 3 | AH76: England | AI76: https://cdn.sofifa.net/flags/gb-eng.png | AJ76: GK | AK76: 1 | AL76: Medium | AM76: Medium | AN76: 84 | AO76: 77 | AP76: 87 | AQ76: 87 | AR76: 51 | AS76: 80 | AT76: 17 | AU76: 19 | AV76: 15 | AW76: 58 | AX76: 20 | AY76: 14 | AZ76: 18 | BA76: 16 | BB76: 60 | BC76: 40 | BD76: 56 | BE76: 44 | BF76: 57 | BG76: 75 | BH76: 55 | BI76: 65 | BJ76: 77 | BK76: 45 | BL76: 70 | BM76: 13 | BN76: 45 | BO76: 24 | BP76: 18 | BQ76: 69 | BR76: 45 | BS76: 65 | BT76: 21 | BU76: 20 | BV76: 12 | BW76: 84 | BX76: 77 | BY76: 87 | BZ76: 80 | CA76: 87 | CB76: 39 | CC76: 36 | CD76: 39 | CE76: 39 | CF76: 39 | CG76: 36 | CH76: 46 | CI76: 43 | CJ76: 49 | CK76: 43 | CL76: 37 | CM76: 45 | CN76: 37 | CO76: 36 | CP76: 37 | CQ76: 36 | CR76: 84
A77: 76 | B77: Kepa Arrizabalaga | C77: Goalkeeper | D77: GK | E77: Chelsea | F77: 81 | G77: 20 | H77: Kepa | I77: Kepa Arrizabalaga | J77: 80 | K77: 83 | L77: 20500000 | M77: GK | N77: GK | O77: Spain | P77: https://cdn.sofifa.net/players/206/585/23_60.png | Q77: 27 | R77: 186 | S77: 88 | T77: 1308 | U77: 435 | V77: Chelsea | W77: 80000 | X77: 39500000 | Y77: SUB | Z77: 2025 | AA77: 1 | AB77: 2018 | AC77: - | AD77: Right | AE77: 4 | AF77: 1 | AG77: 2 | AH77: - | AI77: https://cdn.sofifa.net/flags/es.png | AJ77: - | AK77: - | AL77: Medium | AM77: Medium | AN77: 79 | AO77: 78 | AP77: 85 | AQ77: 82 | AR77: 34 | AS77: 77 | AT77: 25 | AU77: 11 | AV77: 18 | AW77: 51 | AX77: 18 | AY77: 14 | AZ77: 25 | BA77: 19 | BB77: 51 | BC77: 33 | BD77: 34 | BE77: 33 | BF77: 41 | BG77: 70 | BH77: 39 | BI77: 64 | BJ77: 71 | BK77: 37 | BL77: 51 | BM77: 14 | BN77: 18 | BO77: 21 | BP77: 15 | BQ77: 57 | BR77: 24 | BS77: 63 | BT77: 19 | BU77: 18 | BV77: 16 | BW77: 79 | BX77: 78 | BY77: 85 | BZ77: 77 | CA77: 82 | CB77: 33 | CC77: 31 | CD77: 33 | CE77: 33 | CF77: 33 | CG77: 31 | CH77: 38 | CI77: 36 | CJ77: 42 | CK77: 36 | CL77: 33 | CM77: 37 | CN77: 33 | CO77: 32 | CP77: 30 | CQ77: 32 | CR77: 80
A78: 77 | B78: David De Gea Quintana | C78: Goalkeeper | D78: GK | E78: Manchester United | F78: 87 | G78: 30 | H78: De Gea | I78: David De Gea Quintana | J78: 87 | K78: 87 | L78: 42000000 | M78: GK | N78: GK | O78: Spain | P78: https://cdn.sofifa.net/players/193/080/23_60.png | Q78: 31 | R78: 192 | S78: 76 | T78: 1415 | U78: 468 | V78: Manchester United | W78: 150000 | X78: 79800000 | Y78: GK | Z78: 2023 | AA78: 1 | AB78: 2011 | AC78: - | AD78: Right | AE78: 3 | AF78: 1 | AG78: 4 | AH78: Spain | AI78: https://cdn.sofifa.net/flags/es.png | AJ78: SUB | AK78: 1 | AL78: Medium | AM78: Medium | AN78: 88 | AO78: 80 | AP78: 76 | AQ78: 89 | AR78: 51 | AS78: 84 | AT78: 17 | AU78: 13 | AV78: 21 | AW78: 48 | AX78: 13 | AY78: 18 | AZ78: 21 | BA78: 19 | BB78: 50 | BC78: 34 | BD78: 52 | BE78: 50 | BF78: 63 | BG78: 89 | BH78: 43 | BI78: 57 | BJ78: 67 | BK78: 43 | BL78: 55 | BM78: 12 | BN78: 30 | BO78: 30 | BP78: 12 | BQ78: 53 | BR78: 29 | BS78: 58 | BT78: 25 | BU78: 21 | BV78: 13 | BW78: 88 | BX78: 80 | BY78: 76 | BZ78: 84 | CA78: 89 | CB78: 37 | CC78: 34 | CD78: 36 | CE78: 36 | CF78: 36 | CG78: 34 | CH78: 42 | CI78: 40 | CJ78: 44 | CK78: 40 | CL78: 38 | CM78: 42 | CN78: 38 | CO78: 37 | CP78: 36 | CQ78: 37 | CR78: 87
A79: 78 | B79: Keylor navas | C79: Goalkeeper | D79: GK | E79: NOTTING FOREST | F79: 87 | G79: 30 | H79: K. Navas | I79: Keylor Navas | J79: 88 | K79: 88 | L79: 10000000 | M79: GK | N79: GK | O79: Costa Rica | P79: https://cdn.sofifa.net/players/193/041/23_60.png | Q79: 35 | R79: 185 | S79: 80 | T79: 1428 | U79: 478 | V79: Paris Saint-Germain | W79: 85000 | X79: 18500000 | Y79: SUB | Z79: 2024 | AA79: 1 | AB79: 2019 | AC79: - | AD79: Right | AE79: 3 | AF79: 1 | AG79: 3 | AH79: - | AI79: - | AJ79: - | AK79: - | AL79: Medium | AM79: Medium | AN79: 89 | AO79: 84 | AP79: 75 | AQ79: 89 | AR79: 54 | AS79: 87 | AT79: 11 | AU79: 15 | AV79: 11 | AW79: 40 | AX79: 11 | AY79: 24 | AZ79: 21 | BA79: 15 | BB79: 37 | BC79: 30 | BD79: 54 | BE79: 53 | BF79: 60 | BG79: 85 | BH79: 61 | BI79: 56 | BJ79: 74 | BK79: 39 | BL79: 75 | BM79: 13 | BN79: 32 | BO79: 22 | BP79: 16 | BQ79: 68 | BR79: 25 | BS79: 67 | BT79: 28 | BU79: 14 | BV79: 14 | BW79: 89 | BX79: 84 | BY79: 75 | BZ79: 87 | CA79: 89 | CB79: 37 | CC79: 35 | CD79: 37 | CE79: 37 | CF79: 37 | CG79: 35 | CH79: 43 | CI79: 40 | CJ79: 42 | CK79: 40 | CL79: 35 | CM79: 39 | CN79: 35 | CO79: 34 | CP79: 35 | CQ79: 34 | CR79: 88
A80: 79 | B80: Peter Gulacsy | C80: Goalkeeper | D80: GK | E80: RB LEIPG | F80: 85 | G80: 30 | H80: P. Gulácsi | I80: Péter Gulácsi | J80: 85 | K80: 85 | L80: 26500000 | M80: GK | N80: GK | O80: Hungary | P80: https://cdn.sofifa.net/players/185/122/23_60.png | Q80: 32 | R80: 191 | S80: 86 | T80: 1305 | U80: 456 | V80: RB Leipzig | W80: 65000 | X80: 45100000 | Y80: GK | Z80: 2025 | AA80: 1 | AB80: 2015 | AC80: - | AD80: Right | AE80: 2 | AF80: 1 | AG80: 3 | AH80: Hungary | AI80: https://cdn.sofifa.net/flags/hu.png | AJ80: GK | AK80: 1 | AL80: Medium | AM80: Medium | AN80: 85 | AO80: 84 | AP80: 76 | AQ80: 85 | AR80: 43 | AS80: 83 | AT80: 16 | AU80: 10 | AV80: 23 | AW80: 35 | AX80: 10 | AY80: 19 | AZ80: 18 | BA80: 11 | BB80: 31 | BC80: 25 | BD80: 42 | BE80: 44 | BF80: 41 | BG80: 81 | BH80: 42 | BI80: 57 | BJ80: 67 | BK80: 37 | BL80: 74 | BM80: 12 | BN80: 34 | BO80: 23 | BP80: 11 | BQ80: 44 | BR80: 24 | BS80: 45 | BT80: 25 | BU80: 16 | BV80: 20 | BW80: 85 | BX80: 84 | BY80: 76 | BZ80: 83 | CA80: 85 | CB80: 34 | CC80: 29 | CD80: 31 | CE80: 31 | CF80: 31 | CG80: 29 | CH80: 34 | CI80: 34 | CJ80: 36 | CK80: 34 | CL80: 34 | CM80: 36 | CN80: 34 | CO80: 34 | CP80: 36 | CQ80: 34 | CR80: 85
A81: 80 | B81: Yassine bounou | C81: Goalkeeper | D81: GK | E81: Sevilla FC | F81: 85 | G81: 30 | H81: Y. Bounou | I81: Yassine Bounou | J81: 84 | K81: 84 | L81: 22500000 | M81: GK | N81: GK | O81: Morocco | P81: https://cdn.sofifa.net/players/209/981/23_60.png | Q81: 31 | R81: 192 | S81: 78 | T81: 1262 | U81: 447 | V81: Sevilla FC | W81: 34000 | X81: 47300000 | Y81: GK | Z81: 2025 | AA81: 13 | AB81: 2020 | AC81: - | AD81: Left | AE81: 2 | AF81: 1 | AG81: 1 | AH81: Morocco | AI81: https://cdn.sofifa.net/flags/ma.png | AJ81: GK | AK81: 1 | AL81: Medium | AM81: Medium | AN81: 84 | AO81: 81 | AP81: 76 | AQ81: 86 | AR81: 36 | AS81: 84 | AT81: 15 | AU81: 14 | AV81: 14 | AW81: 39 | AX81: 13 | AY81: 20 | AZ81: 12 | BA81: 19 | BB81: 44 | BC81: 12 | BD81: 37 | BE81: 34 | BF81: 47 | BG81: 80 | BH81: 29 | BI81: 57 | BJ81: 48 | BK81: 43 | BL81: 69 | BM81: 19 | BN81: 25 | BO81: 12 | BP81: 10 | BQ81: 62 | BR81: 24 | BS81: 57 | BT81: 20 | BU81: 18 | BV81: 15 | BW81: 84 | BX81: 81 | BY81: 76 | BZ81: 84 | CA81: 86 | CB81: 31 | CC81: 28 | CD81: 31 | CE81: 31 | CF81: 31 | CG81: 28 | CH81: 35 | CI81: 33 | CJ81: 38 | CK81: 33 | CL81: 30 | CM81: 34 | CN81: 30 | CO81: 29 | CP81: 30 | CQ81: 29 | CR81: 84
A82: 81 | B82: Koen Casteels | C82: Goalkeeper | D82: GK | E82: VFL woldfsburg | F82: 84 | G82: 30 | H82: K. Casteels | I82: Koen Casteels | J82: 84 | K82: 85 | L82: 31500000 | M82: GK | N82: GK | O82: Belgium | P82: https://cdn.sofifa.net/players/192/984/23_60.png | Q82: 30 | R82: 197 | S82: 86 | T82: 1301 | U82: 460 | V82: VfL Wolfsburg | W82: 55000 | X82: 55900000 | Y82: GK | Z82: 2024 | AA82: 1 | AB82: 2015 | AC82: - | AD82: Left | AE82: 2 | AF82: 1 | AG82: 3 | AH82: Belgium | AI82: https://cdn.sofifa.net/flags/be.png | AJ82: SUB | AK82: 13 | AL82: Medium | AM82: Medium | AN82: 84 | AO82: 82 | AP82: 79 | AQ82: 86 | AR82: 45 | AS82: 84 | AT82: 15 | AU82: 15 | AV82: 14 | AW82: 35 | AX82: 13 | AY82: 14 | AZ82: 20 | BA82: 13 | BB82: 37 | BC82: 23 | BD82: 44 | BE82: 46 | BF82: 50 | BG82: 80 | BH82: 43 | BI82: 59 | BJ82: 58 | BK82: 44 | BL82: 72 | BM82: 18 | BN82: 33 | BO82: 16 | BP82: 15 | BQ82: 42 | BR82: 20 | BS82: 40 | BT82: 11 | BU82: 19 | BV82: 17 | BW82: 84 | BX82: 82 | BY82: 79 | BZ82: 84 | CA82: 86 | CB82: 35 | CC82: 29 | CD82: 31 | CE82: 31 | CF82: 31 | CG82: 29 | CH82: 35 | CI82: 34 | CJ82: 36 | CK82: 34 | CL82: 32 | CM82: 35 | CN82: 32 | CO82: 32 | CP82: 32 | CQ82: 32 | CR82: 85
A83: 82 | B83: Kylian Mbappe | C83: Forwards | D83: ST | E83: PSG | F83: 91 | G83: 40 | H83: K. Mbappé | I83: Kylian Mbappé | J83: 91 | K83: 95 | L83: 190500000 | M83: ST,LW | N83: ST | O83: France | P83: https://cdn.sofifa.net/players/231/747/23_60.png | Q83: 23 | R83: 182 | S83: 73 | T83: 2177 | U83: 470 | V83: Paris Saint-Germain | W83: 230000 | X83: 366700000 | Y83: ST | Z83: 2024 | AA83: 7 | AB83: 2018 | AC83: - | AD83: Right | AE83: 4 | AF83: 5 | AG83: 4 | AH83: France | AI83: https://cdn.sofifa.net/flags/fr.png | AJ83: ST | AK83: 10 | AL83: High | AM83: Low | AN83: 97 | AO83: 89 | AP83: 80 | AQ83: 92 | AR83: 36 | AS83: 76 | AT83: 78 | AU83: 93 | AV83: 72 | AW83: 85 | AX83: 83 | AY83: 93 | AZ83: 80 | BA83: 69 | BB83: 71 | BC83: 91 | BD83: 97 | BE83: 97 | BF83: 93 | BG83: 93 | BH83: 81 | BI83: 88 | BJ83: 77 | BK83: 87 | BL83: 76 | BM83: 82 | BN83: 64 | BO83: 38 | BP83: 92 | BQ83: 83 | BR83: 80 | BS83: 88 | BT83: 26 | BU83: 34 | BV83: 32 | BW83: 13 | BX83: 5 | BY83: 7 | BZ83: 11 | CA83: 6 | CB83: 92 | CC83: 90 | CD83: 90 | CE83: 90 | CF83: 90 | CG83: 90 | CH83: 92 | CI83: 92 | CJ83: 84 | CK83: 92 | CL83: 70 | CM83: 66 | CN83: 70 | CO83: 66 | CP83: 57 | CQ83: 66 | CR83: 21
A84: 83 | B84: Robert Lewandowski | C84: Forwards | D84: ST | E84: Barcelona | F84: 91 | G84: 40 | H84: R. Lewandowski | I84: Robert Lewandowski | J84: 91 | K84: 91 | L84: 84000000 | M84: ST | N84: ST | O84: Poland | P84: https://cdn.sofifa.net/players/188/545/23_60.png | Q84: 33 | R84: 185 | S84: 81 | T84: 2205 | U84: 458 | V84: FC Barcelona | W84: 420000 | X84: 172200000 | Y84: ST | Z84: 2025 | AA84: 9 | AB84: 2022 | AC84: - | AD84: Right | AE84: 4 | AF84: 4 | AG84: 5 | AH84: Poland | AI84: https://cdn.sofifa.net/flags/pl.png | AJ84: ST | AK84: 9 | AL84: High | AM84: Medium | AN84: 75 | AO84: 91 | AP84: 79 | AQ84: 86 | AR84: 44 | AS84: 83 | AT84: 71 | AU84: 94 | AV84: 91 | AW84: 84 | AX84: 89 | AY84: 85 | AZ84: 79 | BA84: 85 | BB84: 70 | BC84: 89 | BD84: 76 | BE84: 75 | BF84: 77 | BG84: 93 | BH84: 82 | BI84: 91 | BJ84: 85 | BK84: 76 | BL84: 87 | BM84: 84 | BN84: 81 | BO84: 49 | BP84: 94 | BQ84: 81 | BR84: 90 | BS84: 88 | BT84: 35 | BU84: 42 | BV84: 19 | BW84: 15 | BX84: 6 | BY84: 12 | BZ84: 8 | CA84: 10 | CB84: 91 | CC84: 85 | CD84: 88 | CE84: 88 | CF84: 88 | CG84: 85 | CH84: 88 | CI84: 86 | CJ84: 83 | CK84: 86 | CL84: 67 | CM84: 69 | CN84: 67 | CO84: 64 | CP84: 63 | CQ84: 64 | CR84: 22
A85: 84 | B85: Lionel Messi | C85: Forwards | D85: RW | E85: PSG | F85: 91 | G85: 40 | H85: L. Messi | I85: Lionel Messi | J85: 91 | K85: 91 | L85: 54000000 | M85: RW | N85: CAM | O85: Argentina | P85: https://cdn.sofifa.net/players/158/023/23_60.png | Q85: 35 | R85: 169 | S85: 67 | T85: 2190 | U85: 452 | V85: Paris Saint-Germain | W85: 195000 | X85: 99900000 | Y85: RW | Z85: 2023 | AA85: 30 | AB85: 2021 | AC85: - | AD85: Left | AE85: 4 | AF85: 4 | AG85: 5 | AH85: Argentina | AI85: https://cdn.sofifa.net/flags/ar.png | AJ85: RW | AK85: 10 | AL85: Low | AM85: Low | AN85: 81 | AO85: 89 | AP85: 90 | AQ85: 94 | AR85: 34 | AS85: 64 | AT85: 84 | AU85: 90 | AV85: 70 | AW85: 91 | AX85: 88 | AY85: 95 | AZ85: 93 | BA85: 93 | BB85: 90 | BC85: 93 | BD85: 87 | BE85: 76 | BF85: 91 | BG85: 92 | BH85: 95 | BI85: 86 | BJ85: 68 | BK85: 70 | BL85: 68 | BM85: 91 | BN85: 44 | BO85: 40 | BP85: 93 | BQ85: 94 | BR85: 75 | BS85: 96 | BT85: 20 | BU85: 35 | BV85: 24 | BW85: 6 | BX85: 11 | BY85: 15 | BZ85: 14 | CA85: 8 | CB85: 90 | CC85: 90 | CD85: 91 | CE85: 91 | CF85: 91 | CG85: 90 | CH85: 91 | CI85: 91 | CJ85: 88 | CK85: 91 | CL85: 67 | CM85: 66 | CN85: 67 | CO85: 62 | CP85: 53 | CQ85: 62 | CR85: 22
A86: 85 | B86: Karim Benzema | C86: Forwards | D86: CF | E86: Al-Ittihad | F86: 91 | G86: 40 | H86: K. Benzema | I86: Karim Benzema | J86: 91 | K86: 91 | L86: 64000000 | M86: CF,ST | N86: CF | O86: France | P86: https://cdn.sofifa.net/players/165/153/23_60.png | Q86: 34 | R86: 185 | S86: 81 | T86: 2147 | U86: 455 | V86: Real Madrid CF | W86: 450000 | X86: 131199999 | Y86: CF | Z86: 2023 | AA86: 9 | AB86: 2009 | AC86: - | AD86: Right | AE86: 4 | AF86: 4 | AG86: 4 | AH86: France | AI86: https://cdn.sofifa.net/flags/fr.png | AJ86: ST | AK86: 19 | AL86: Medium | AM86: Medium | AN86: 80 | AO86: 88 | AP86: 83 | AQ86: 87 | AR86: 39 | AS86: 78 | AT86: 75 | AU86: 92 | AV86: 90 | AW86: 89 | AX86: 88 | AY86: 87 | AZ86: 82 | BA86: 73 | BB86: 76 | BC86: 91 | BD86: 79 | BE86: 80 | BF86: 78 | BG86: 92 | BH86: 72 | BI86: 87 | BJ86: 79 | BK86: 82 | BL86: 82 | BM86: 80 | BN86: 63 | BO86: 39 | BP86: 92 | BQ86: 89 | BR86: 84 | BS86: 90 | BT86: 43 | BU86: 24 | BV86: 18 | BW86: 13 | BX86: 11 | BY86: 5 | BZ86: 5 | CA86: 7 | CB86: 91 | CC86: 87 | CD86: 89 | CE86: 89 | CF86: 89 | CG86: 87 | CH86: 91 | CI86: 89 | CJ86: 84 | CK86: 89 | CL86: 67 | CM86: 67 | CN86: 67 | CO86: 63 | CP86: 58 | CQ86: 63 | CR86: 21
A87: 86 | B87: Mohamed Salah | C87: Forwards | D87: RW | E87: Liverpool | F87: 89 | G87: 40 | H87: M. Salah | I87: Mohamed Salah | J87: 90 | K87: 90 | L87: 115500000 | M87: RW | N87: RW | O87: Egypt | P87: https://cdn.sofifa.net/players/209/331/23_60.png | Q87: 30 | R87: 175 | S87: 71 | T87: 2226 | U87: 471 | V87: Liverpool | W87: 270000 | X87: 213700000 | Y87: RW | Z87: 2023 | AA87: 11 | AB87: 2017 | AC87: - | AD87: Left | AE87: 3 | AF87: 4 | AG87: 4 | AH87: - | AI87: - | AJ87: - | AK87: - | AL87: High | AM87: Medium | AN87: 90 | AO87: 89 | AP87: 82 | AQ87: 90 | AR87: 45 | AS87: 75 | AT87: 80 | AU87: 93 | AV87: 59 | AW87: 84 | AX87: 84 | AY87: 90 | AZ87: 84 | BA87: 69 | BB87: 77 | BC87: 88 | BD87: 89 | BE87: 91 | BF87: 90 | BG87: 93 | BH87: 91 | BI87: 83 | BJ87: 69 | BK87: 87 | BL87: 75 | BM87: 85 | BN87: 63 | BO87: 55 | BP87: 92 | BQ87: 85 | BR87: 86 | BS87: 92 | BT87: 38 | BU87: 43 | BV87: 41 | BW87: 14 | BX87: 14 | BY87: 9 | BZ87: 11 | CA87: 14 | CB87: 89 | CC87: 88 | CD87: 88 | CE87: 88 | CF87: 88 | CG87: 88 | CH87: 90 | CI87: 90 | CJ87: 85 | CK87: 90 | CL87: 74 | CM87: 71 | CN87: 74 | CO87: 70 | CP87: 61 | CQ87: 70 | CR87: 25
A88: 87 | B88: Harry Kane | C88: Forwards | D88: ST | E88: Spurs | F88: 89 | G88: 40 | H88: H. Kane | I88: Harry Kane | J88: 89 | K88: 89 | L88: 105500000 | M88: ST | N88: ST | O88: England | P88: https://cdn.sofifa.net/players/202/126/23_60.png | Q88: 28 | R88: 188 | S88: 89 | T88: 2193 | U88: 453 | V88: Tottenham Hotspur | W88: 240000 | X88: 200500000 | Y88: ST | Z88: 2024 | AA88: 10 | AB88: 2010 | AC88: - | AD88: Right | AE88: 5 | AF88: 3 | AG88: 4 | AH88: England | AI88: https://cdn.sofifa.net/flags/gb-eng.png | AJ88: ST | AK88: 9 | AL88: High | AM88: High | AN88: 68 | AO88: 91 | AP88: 83 | AQ88: 82 | AR88: 47 | AS88: 82 | AT88: 80 | AU88: 93 | AV88: 85 | AW88: 84 | AX88: 87 | AY88: 83 | AZ88: 82 | BA88: 65 | BB88: 85 | BC88: 84 | BD88: 67 | BE88: 69 | BF88: 68 | BG88: 92 | BH88: 71 | BI88: 92 | BJ88: 79 | BK88: 83 | BL88: 83 | BM88: 86 | BN88: 80 | BO88: 44 | BP88: 94 | BQ88: 87 | BR88: 92 | BS88: 92 | BT88: 50 | BU88: 36 | BV88: 38 | BW88: 8 | BX88: 10 | BY88: 11 | BZ88: 14 | CA88: 11 | CB88: 89 | CC88: 84 | CD88: 86 | CE88: 86 | CF88: 86 | CG88: 84 | CH88: 88 | CI88: 86 | CJ88: 84 | CK88: 86 | CL88: 69 | CM88: 71 | CN88: 69 | CO88: 66 | CP88: 64 | CQ88: 66 | CR88: 23
A89: 88 | B89: Erling Haaland | C89: Forwards | D89: ST | E89: Manchester City | F89: 89 | G89: 40 | H89: E. Haaland | I89: Erling Haaland | J89: 88 | K89: 94 | L89: 148000000 | M89: ST | N89: ST | O89: Norway | P89: https://cdn.sofifa.net/players/239/085/23_60.png | Q89: 21 | R89: 195 | S89: 94 | T89: 2120 | U89: 461 | V89: Manchester City | W89: 220000 | X89: 303400000 | Y89: ST | Z89: 2027 | AA89: 9 | AB89: 2022 | AC89: - | AD89: Left | AE89: 3 | AF89: 3 | AG89: 4 | AH89: Norway | AI89: https://cdn.sofifa.net/flags/no.png | AJ89: ST | AK89: 9 | AL89: High | AM89: Medium | AN89: 89 | AO89: 91 | AP89: 65 | AQ89: 80 | AR89: 49 | AS89: 87 | AT89: 47 | AU89: 94 | AV89: 79 | AW89: 74 | AX89: 88 | AY89: 78 | AZ89: 77 | BA89: 62 | BB89: 53 | BC89: 82 | BD89: 82 | BE89: 94 | BF89: 76 | BG89: 88 | BH89: 72 | BI89: 94 | BJ89: 74 | BK89: 81 | BL89: 93 | BM89: 87 | BN89: 85 | BO89: 43 | BP89: 89 | BQ89: 74 | BR89: 76 | BS89: 85 | BT89: 44 | BU89: 53 | BV89: 29 | BW89: 7 | BX89: 14 | BY89: 13 | BZ89: 11 | CA89: 7 | CB89: 90 | CC89: 80 | CD89: 84 | CE89: 84 | CF89: 84 | CG89: 80 | CH89: 83 | CI89: 80 | CJ89: 76 | CK89: 80 | CL89: 65 | CM89: 67 | CN89: 65 | CO89: 64 | CP89: 65 | CQ89: 64 | CR89: 22
A90: 89 | B90: Neymar | C90: Forwards | D90: LW | E90: PSG | F90: 89 | G90: 40 | H90: Neymar Jr | I90: Neymar da Silva Santos Jr. | J90: 89 | K90: 89 | L90: 99500000 | M90: LW | N90: LW | O90: Brazil | P90: https://cdn.sofifa.net/players/190/871/23_60.png | Q90: 30 | R90: 175 | S90: 68 | T90: 2157 | U90: 446 | V90: Paris Saint-Germain | W90: 200000 | X90: 184100000 | Y90: LW | Z90: 2025 | AA90: 10 | AB90: 2017 | AC90: - | AD90: Right | AE90: 5 | AF90: 5 | AG90: 5 | AH90: - | AI90: https://cdn.sofifa.net/flags/br.png | AJ90: - | AK90: - | AL90: High | AM90: Medium | AN90: 87 | AO90: 83 | AP90: 85 | AQ90: 93 | AR90: 37 | AS90: 61 | AT90: 84 | AU90: 83 | AV90: 63 | AW90: 85 | AX90: 86 | AY90: 95 | AZ90: 88 | BA90: 87 | BB90: 81 | BC90: 94 | BD90: 88 | BE90: 86 | BF90: 93 | BG90: 88 | BH90: 82 | BI90: 79 | BJ90: 62 | BK90: 79 | BL90: 52 | BM90: 81 | BN90: 63 | BO90: 37 | BP90: 86 | BQ90: 89 | BR90: 91 | BS90: 93 | BT90: 35 | BU90: 32 | BV90: 29 | BW90: 9 | BX90: 9 | BY90: 15 | BZ90: 15 | CA90: 11 | CB90: 85 | CC90: 88 | CD90: 88 | CE90: 88 | CF90: 88 | CG90: 88 | CH90: 89 | CI90: 89 | CJ90: 85 | CK90: 89 | CL90: 69 | CM90: 66 | CN90: 69 | CO90: 64 | CP90: 53 | CQ90: 64 | CR90: 23
A91: 90 | B91: Sadio Mane | C91: Forwards | D91: CF | E91: Al-Nasar | F91: 89 | G91: 40 | H91: S. Mané | I91: Sadio Mané | J91: 89 | K91: 89 | L91: 99500000 | M91: LM,CF | N91: LM | O91: Senegal | P91: https://cdn.sofifa.net/players/208/722/23_60.png | Q91: 30 | R91: 174 | S91: 69 | T91: 2188 | U91: 462 | V91: FC Bayern München | W91: 145000 | X91: 164200000 | Y91: ST | Z91: 2025 | AA91: 17 | AB91: 2022 | AC91: - | AD91: Right | AE91: 4 | AF91: 4 | AG91: 4 | AH91: - | AI91: - | AJ91: - | AK91: - | AL91: High | AM91: Medium | AN91: 90 | AO91: 83 | AP91: 80 | AQ91: 88 | AR91: 44 | AS91: 77 | AT91: 78 | AU91: 86 | AV91: 84 | AW91: 84 | AX91: 75 | AY91: 88 | AZ91: 77 | BA91: 64 | BB91: 71 | BC91: 86 | BD91: 91 | BE91: 90 | BF91: 93 | BG91: 91 | BH91: 88 | BI91: 83 | BJ91: 87 | BK91: 85 | BL91: 72 | BM91: 78 | BN91: 75 | BO91: 35 | BP91: 90 | BQ91: 84 | BR91: 75 | BS91: 84 | BT91: 42 | BU91: 42 | BV91: 38 | BW91: 10 | BX91: 10 | BY91: 15 | BZ91: 7 | CA91: 14 | CB91: 89 | CC91: 86 | CD91: 87 | CE91: 87 | CF91: 87 | CG91: 86 | CH91: 89 | CI91: 89 | CJ91: 82 | CK91: 89 | CL91: 71 | CM91: 68 | CN91: 71 | CO91: 68 | CP91: 62 | CQ91: 68 | CR91: 22
A92: 91 | B92: Heun-min Son | C92: Forwards | D92: LW | E92: Spurs | F92: 88 | G92: 40 | H92: H. Son | I92: Heung Min Son | J92: 89 | K92: 89 | L92: 101000000 | M92: LW,LM | N92: LW | O92: Korea Republic | P92: https://cdn.sofifa.net/players/200/104/23_60.png | Q92: 29 | R92: 183 | S92: 78 | T92: 2141 | U92: 456 | V92: Tottenham Hotspur | W92: 240000 | X92: 191900000 | Y92: LW | Z92: 2025 | AA92: 7 | AB92: 2015 | AC92: - | AD92: Right | AE92: 5 | AF92: 4 | AG92: 4 | AH92: - | AI92: - | AJ92: - | AK92: - | AL92: High | AM92: Medium | AN92: 88 | AO92: 89 | AP92: 82 | AQ92: 86 | AR92: 42 | AS92: 69 | AT92: 83 | AU92: 91 | AV92: 68 | AW92: 84 | AX92: 79 | AY92: 87 | AZ92: 85 | BA92: 74 | BB92: 74 | BC92: 84 | BD92: 85 | BE92: 90 | BF92: 85 | BG92: 91 | BH92: 76 | BI92: 88 | BJ92: 60 | BK92: 88 | BL92: 64 | BM92: 89 | BN92: 62 | BO92: 39 | BP92: 91 | BQ92: 84 | BR92: 73 | BS92: 89 | BT92: 47 | BU92: 34 | BV92: 33 | BW92: 11 | BX92: 13 | BY92: 13 | BZ92: 6 | CA92: 10 | CB92: 88 | CC92: 87 | CD92: 87 | CE92: 87 | CF92: 87 | CG92: 87 | CH92: 89 | CI92: 89 | CJ92: 83 | CK92: 89 | CL92: 71 | CM92: 67 | CN92: 71 | CO92: 67 | CP92: 57 | CQ92: 67 | CR92: 22
A93: 92 | B93: Cristiano Ronaldo | C93: Forwards | D93: ST | E93: Al-Nassar | F93: 88 | G93: 40 | H93: Cristiano Ronaldo | I93: C. Ronaldo dos Santos Aveiro | J93: 90 | K93: 90 | L93: 41000000 | M93: ST | N93: ST | O93: Portugal | P93: https://cdn.sofifa.net/players/020/801/23_60.png | Q93: 37 | R93: 187 | S93: 83 | T93: 2159 | U93: 445 | V93: Manchester United | W93: 220000 | X93: 77900000 | Y93: SUB | Z93: 2023 | AA93: 7 | AB93: 2021 | AC93: - | AD93: Right | AE93: 4 | AF93: 5 | AG93: 5 | AH93: Portugal | AI93: https://cdn.sofifa.net/flags/pt.png | AJ93: ST | AK93: 7 | AL93: High | AM93: Low | AN93: 81 | AO93: 92 | AP93: 78 | AQ93: 85 | AR93: 34 | AS93: 75 | AT93: 80 | AU93: 93 | AV93: 90 | AW93: 80 | AX93: 86 | AY93: 85 | AZ93: 81 | BA93: 79 | BB93: 75 | BC93: 88 | BD93: 79 | BE93: 83 | BF93: 77 | BG93: 94 | BH93: 67 | BI93: 93 | BJ93: 95 | BK93: 76 | BL93: 77 | BM93: 90 | BN93: 63 | BO93: 29 | BP93: 95 | BQ93: 76 | BR93: 90 | BS93: 95 | BT93: 24 | BU93: 32 | BV93: 24 | BW93: 7 | BX93: 11 | BY93: 15 | BZ93: 14 | CA93: 11 | CB93: 90 | CC93: 86 | CD93: 88 | CE93: 88 | CF93: 88 | CG93: 86 | CH93: 88 | CI93: 87 | CJ93: 81 | CK93: 87 | CL93: 65 | CM93: 62 | CN93: 65 | CO93: 61 | CP93: 56 | CQ93: 61 | CR93: 23
A94: 93 | B94: Paulo Dybala | C94: Forwards | D94: CF | E94: Roma | F94: 86 | G94: 30 | H94: P. Dybala | I94: Paulo Dybala | J94: 86 | K94: 86 | L94: 69500000 | M94: CF,CAM | N94: CAM | O94: Argentina | P94: https://cdn.sofifa.net/players/211/110/23_60.png | Q94: 28 | R94: 177 | S94: 75 | T94: 2108 | U94: 439 | V94: Roma | W94: 130000 | X94: 118200000 | Y94: RF | Z94: 2025 | AA94: 21 | AB94: 2022 | AC94: - | AD94: Left | AE94: 3 | AF94: 4 | AG94: 3 | AH94: Argentina | AI94: https://cdn.sofifa.net/flags/ar.png | AJ94: SUB | AK94: 21 | AL94: High | AM94: Low | AN94: 80 | AO94: 85 | AP94: 85 | AQ94: 90 | AR94: 40 | AS94: 59 | AT94: 82 | AU94: 83 | AV94: 58 | AW94: 86 | AX94: 88 | AY94: 90 | AZ94: 89 | BA94: 88 | BB94: 79 | BC94: 93 | BD94: 84 | BE94: 76 | BF94: 88 | BG94: 79 | BH94: 90 | BI94: 84 | BJ94: 74 | BK94: 68 | BL94: 60 | BM94: 89 | BN94: 43 | BO94: 42 | BP94: 82 | BQ94: 91 | BR94: 84 | BS94: 79 | BT94: 32 | BU94: 41 | BV94: 39 | BW94: 5 | BX94: 4 | BY94: 4 | BZ94: 5 | CA94: 8 | CB94: 84 | CC94: 86 | CD94: 85 | CE94: 85 | CF94: 85 | CG94: 86 | CH94: 86 | CI94: 86 | CJ94: 84 | CK94: 86 | CL94: 68 | CM94: 66 | CN94: 68 | CO94: 64 | CP94: 54 | CQ94: 64 | CR94: 17
A95: 94 | B95: Vinicius Junior | C95: Forwards | D95: LW | E95: Real Madrid | F95: 86 | G95: 30 | H95: Vinícius Jr. | I95: Vinícius José de Oliveira Júnior | J95: 86 | K95: 92 | L95: 109000000 | M95: LW | N95: LW | O95: Brazil | P95: https://cdn.sofifa.net/players/238/794/23_60.png | Q95: 21 | R95: 176 | S95: 73 | T95: 1985 | U95: 434 | V95: Real Madrid CF | W95: 200000 | X95: 245300000 | Y95: LW | Z95: 2025 | AA95: 20 | AB95: 2018 | AC95: - | AD95: Right | AE95: 4 | AF95: 5 | AG95: 2 | AH95: - | AI95: https://cdn.sofifa.net/flags/br.png | AJ95: - | AK95: - | AL95: High | AM95: Medium | AN95: 95 | AO95: 79 | AP95: 74 | AQ95: 90 | AR95: 29 | AS95: 67 | AT95: 72 | AU95: 84 | AV95: 50 | AW95: 75 | AX95: 72 | AY95: 92 | AZ95: 77 | BA95: 62 | BB95: 73 | BC95: 89 | BD95: 95 | BE95: 95 | BF95: 94 | BG95: 82 | BH95: 83 | BI95: 76 | BJ95: 75 | BK95: 84 | BL95: 62 | BM95: 76 | BN95: 58 | BO95: 26 | BP95: 82 | BQ95: 75 | BR95: 65 | BS95: 79 | BT95: 32 | BU95: 25 | BV95: 18 | BW95: 5 | BX95: 7 | BY95: 7 | BZ95: 7 | CA95: 10 | CB95: 81 | CC95: 85 | CD95: 84 | CE95: 84 | CF95: 84 | CG95: 85 | CH95: 85 | CI95: 86 | CJ95: 77 | CK95: 86 | CL95: 63 | CM95: 58 | CN95: 63 | CO95: 58 | CP95: 47 | CQ95: 58 | CR95: 17
A96: 95 | B96: Ciro Immobile | C96: Forwards | D96: ST | E96: Lazio | F96: 86 | G96: 30 | H96: C. Immobile | I96: Ciro Immobile | J96: 86 | K96: 86 | L96: 55000000 | M96: ST | N96: ST | O96: Italy | P96: https://cdn.sofifa.net/players/192/387/23_60.png | Q96: 32 | R96: 185 | S96: 85 | T96: 2060 | U96: 434 | V96: Lazio | W96: 100000 | X96: 93500000 | Y96: ST | Z96: 2025 | AA96: 17 | AB96: 2016 | AC96: - | AD96: Right | AE96: 4 | AF96: 3 | AG96: 4 | AH96: Italy | AI96: https://cdn.sofifa.net/flags/it.png | AJ96: ST | AK96: 17 | AL96: High | AM96: Medium | AN96: 85 | AO96: 87 | AP96: 68 | AQ96: 80 | AR96: 39 | AS96: 75 | AT96: 55 | AU96: 91 | AV96: 81 | AW96: 79 | AX96: 85 | AY96: 79 | AZ96: 70 | BA96: 58 | BB96: 57 | BC96: 81 | BD96: 84 | BE96: 86 | BF96: 75 | BG96: 87 | BH96: 84 | BI96: 86 | BJ96: 82 | BK96: 78 | BL96: 74 | BM96: 80 | BN96: 73 | BO96: 40 | BP96: 90 | BQ96: 71 | BR96: 88 | BS96: 76 | BT96: 34 | BU96: 33 | BV96: 32 | BW96: 6 | BX96: 8 | BY96: 15 | BZ96: 12 | CA96: 6 | CB96: 86 | CC96: 80 | CD96: 83 | CE96: 83 | CF96: 83 | CG96: 80 | CH96: 83 | CI96: 81 | CJ96: 76 | CK96: 81 | CL96: 64 | CM96: 62 | CN96: 64 | CO96: 61 | CP96: 58 | CQ96: 61 | CR96: 20
A97: 96 | B97: Lautaro Martinez | C97: Forwards | D97: ST | E97: Inter Milan | F97: 86 | G97: 30 | H97: L. Martínez | I97: Lautaro Martínez | J97: 86 | K97: 90 | L97: 98500000 | M97: ST | N97: ST | O97: Argentina | P97: https://cdn.sofifa.net/players/231/478/23_60.png | Q97: 24 | R97: 174 | S97: 72 | T97: 2163 | U97: 455 | V97: Inter | W97: 110000 | X97: 169900000 | Y97: ST | Z97: 2026 | AA97: 10 | AB97: 2018 | AC97: - | AD97: Right | AE97: 4 | AF97: 4 | AG97: 3 | AH97: Argentina | AI97: https://cdn.sofifa.net/flags/ar.png | AJ97: ST | AK97: 22 | AL97: High | AM97: Medium | AN97: 83 | AO97: 83 | AP97: 72 | AQ97: 85 | AR97: 48 | AS97: 84 | AT97: 58 | AU97: 88 | AV97: 84 | AW97: 76 | AX97: 90 | AY97: 84 | AZ97: 78 | BA97: 54 | BB97: 73 | BC97: 86 | BD97: 86 | BE97: 80 | BF97: 86 | BG97: 89 | BH97: 89 | BI97: 80 | BJ97: 89 | BK97: 80 | BL97: 84 | BM97: 76 | BN97: 90 | BO97: 45 | BP97: 86 | BQ97: 80 | BR97: 74 | BS97: 86 | BT97: 55 | BU97: 31 | BV97: 44 | BW97: 11 | BX97: 8 | BY97: 8 | BZ97: 8 | CA97: 13 | CB97: 88 | CC97: 82 | CD97: 84 | CE97: 84 | CF97: 84 | CG97: 82 | CH97: 85 | CI97: 83 | CJ97: 79 | CK97: 83 | CL97: 68 | CM97: 69 | CN97: 68 | CO97: 66 | CP97: 65 | CQ97: 66 | CR97: 22
A98: 97 | B98: Phil Foden | C98: Forwards | D98: LW | E98: Manchester City | F98: 85 | G98: 30 | H98: P. Foden | I98: Phil Foden | J98: 85 | K98: 92 | L98: 109500000 | M98: LW,CF,CAM | N98: CAM | O98: England | P98: https://cdn.sofifa.net/players/237/692/23_60.png | Q98: 22 | R98: 171 | S98: 69 | T98: 2083 | U98: 445 | V98: Manchester City | W98: 180000 | X98: 224500000 | Y98: LW | Z98: 2024 | AA98: 47 | AB98: 2016 | AC98: - | AD98: Left | AE98: 3 | AF98: 4 | AG98: 3 | AH98: England | AI98: https://cdn.sofifa.net/flags/gb-eng.png | AJ98: RW | AK98: 20 | AL98: High | AM98: High | AN98: 82 | AO98: 78 | AP98: 81 | AQ98: 88 | AR98: 56 | AS98: 60 | AT98: 76 | AU98: 79 | AV98: 47 | AW98: 85 | AX98: 59 | AY98: 87 | AZ98: 73 | BA98: 68 | BB98: 81 | BC98: 91 | BD98: 86 | BE98: 78 | BF98: 91 | BG98: 83 | BH98: 91 | BI98: 82 | BJ98: 49 | BK98: 83 | BL98: 47 | BM98: 77 | BN98: 64 | BO98: 59 | BP98: 82 | BQ98: 85 | BR98: 64 | BS98: 84 | BT98: 58 | BU98: 59 | BV98: 47 | BW98: 8 | BX98: 15 | BY98: 6 | BZ98: 10 | CA98: 13 | CB98: 80 | CC98: 84 | CD98: 83 | CE98: 83 | CF98: 83 | CG98: 84 | CH98: 88 | CI98: 87 | CJ98: 85 | CK98: 87 | CL98: 75 | CM98: 74 | CN98: 75 | CO98: 72 | CP98: 62 | CQ98: 72 | CR98: 22
A99: 98 | B99: Raheem Sterling | C99: Forwards | D99: LW | E99: Chelsea | F99: 85 | G99: 30 | H99: R. Sterling | I99: Raheem Sterling | J99: 86 | K99: 86 | L99: 72500000 | M99: LW,RW | N99: LW | O99: England | P99: https://cdn.sofifa.net/players/202/652/23_60.png | Q99: 27 | R99: 170 | S99: 69 | T99: 2102 | U99: 446 | V99: Chelsea | W99: 195000 | X99: 134100000 | Y99: ST | Z99: 2027 | AA99: 17 | AB99: 2022 | AC99: - | AD99: Right | AE99: 3 | AF99: 4 | AG99: 4 | AH99: England | AI99: https://cdn.sofifa.net/flags/gb-eng.png | AJ99: LW | AK99: 7 | AL99: High | AM99: Medium | AN99: 90 | AO99: 80 | AP99: 78 | AQ99: 86 | AR99: 45 | AS99: 67 | AT99: 79 | AU99: 82 | AV99: 46 | AW99: 83 | AX99: 67 | AY99: 86 | AZ99: 79 | BA99: 72 | BB99: 67 | BC99: 84 | BD99: 94 | BE99: 86 | BF99: 94 | BG99: 91 | BH99: 93 | BI99: 78 | BJ99: 57 | BK99: 79 | BL99: 65 | BM99: 80 | BN99: 59 | BO99: 30 | BP99: 91 | BQ99: 80 | BR99: 70 | BS99: 77 | BT99: 47 | BU99: 53 | BV99: 47 | BW99: 15 | BX99: 12 | BY99: 12 | BZ99: 15 | CA99: 9 | CB99: 83 | CC99: 85 | CD99: 85 | CE99: 85 | CF99: 85 | CG99: 85 | CH99: 86 | CI99: 86 | CJ99: 80 | CK99: 86 | CL99: 71 | CM99: 67 | CN99: 71 | CO99: 68 | CP99: 58 | CQ99: 68 | CR99: 24
A100: 99 | B100: Romelu Lukaku | C100: Forwards | D100: ST | E100: Chelsea | F100: 85 | G100: 30 | H100: R. Lukaku | I100: Romelu Lukaku | J100: 86 | K100: 86 | L100: 68000000 | M100: ST | N100: ST | O100: Belgium | P100: https://cdn.sofifa.net/players/192/505/23_60.png | Q100: 29 | R100: 191 | S100: 94 | T100: 2034 | U100: 437 | V100: Inter | W100: 200000 | X100: 0 | Y100: ST | Z100: 2023 | AA100: 90 | AB100: 2021 | AC100: TRUE | AD100: Left | AE100: 4 | AF100: 3 | AG100: 4 | AH100: Belgium | AI100: https://cdn.sofifa.net/flags/be.png | AJ100: ST | AK100: 9 | AL100: Medium | AM100: Low | AN100: 80 | AO100: 85 | AP100: 75 | AQ100: 77 | AR100: 38 | AS100: 82 | AT100: 73 | AU100: 88 | AV100: 87 | AW100: 78 | AX100: 79 | AY100: 82 | AZ100: 78 | BA100: 66 | BB100: 70 | BC100: 78 | BD100: 72 | BE100: 86 | BF100: 59 | BG100: 86 | BH100: 52 | BI100: 87 | BJ100: 74 | BK100: 67 | BL100: 95 | BM100: 75 | BN100: 71 | BO100: 27 | BP100: 86 | BQ100: 75 | BR100: 88 | BS100: 82 | BT100: 30 | BU100: 41 | BV100: 30 | BW100: 8 | BX100: 15 | BY100: 14 | BZ100: 7 | CA100: 10 | CB100: 86 | CC100: 80 | CD100: 82 | CE100: 82 | CF100: 82 | CG100: 80 | CH100: 82 | CI100: 82 | CJ100: 76 | CK100: 82 | CL100: 63 | CM100: 62 | CN100: 63 | CO100: 60 | CP100: 59 | CQ100: 60 | CR100: 22
...

Sheet Auction_Log
A1: Search: | B1: mess
A2: {=IF($B$1="", "", IFERROR(TRANSPOSE(_xlfn._xlws.FILTER(Master_List!$A$2:$A$200, ISNUMBER(SEARCH($B$1, Master_List!$B$2:$B$200)))), ""))} -> 84
A3: {=IF($B$1="", "", IFERROR(TRANSPOSE(_xlfn._xlws.FILTER(Master_List!$B$2:$B$200, ISNUMBER(SEARCH($B$1, Master_List!$B$2:$B$200)))), ""))} -> Lionel Messi
A5: Player ID | B5: Player Sold | C5: Category | D5: Winning Team No | E5: Sale Price
B6: =IF(A6="","", _xlfn.XLOOKUP(A6, Master_List!A:A, Master_List!B:B, "Invalid ID")) | C6: =IF(B6="","",_xlfn.XLOOKUP(B6, Master_List!B:B, Master_List!C:C, "Not Found"))
B7: =IF(A7="","", _xlfn.XLOOKUP(A7, Master_List!A:A, Master_List!B:B, "Invalid ID")) | C7: =IF(B7="","",_xlfn.XLOOKUP(B7, Master_List!B:B, Master_List!C:C, "Not Found"))
B8: =IF(A8="","", _xlfn.XLOOKUP(A8, Master_List!A:A, Master_List!B:B, "Invalid ID")) | C8: =IF(B8="","",_xlfn.XLOOKUP(B8, Master_List!B:B, Master_List!C:C, "Not Found"))
B9: =IF(A9="","", _xlfn.XLOOKUP(A9, Master_List!A:A, Master_List!B:B, "Invalid ID")) | C9: =IF(B9="","",_xlfn.XLOOKUP(B9, Master_List!B:B, Master_List!C:C, "Not Found"))
B10: =IF(A10="","", _xlfn.XLOOKUP(A10, Master_List!A:A, Master_List!B:B, "Invalid ID")) | C10: =IF(B10="","",_xlfn.XLOOKUP(B10, Master_List!B:B, Master_List!C:C, "Not Found"))
B11: =IF(A11="","", _xlfn.XLOOKUP(A11, Master_List!A:A, Master_List!B:B, "Invalid ID")) | C11: =IF(B11="","",_xlfn.XLOOKUP(B11, Master_List!B:B, Master_List!C:C, "Not Found"))
B12: =IF(A12="","", _xlfn.XLOOKUP(A12, Master_List!A:A, Master_List!B:B, "Invalid ID")) | C12: =IF(B12="","",_xlfn.XLOOKUP(B12, Master_List!B:B, Master_List!C:C, "Not Found"))
B13: =IF(A13="","", _xlfn.XLOOKUP(A13, Master_List!A:A, Master_List!B:B, "Invalid ID")) | C13: =IF(B13="","",_xlfn.XLOOKUP(B13, Master_List!B:B, Master_List!C:C, "Not Found"))
B14: =IF(A14="","", _xlfn.XLOOKUP(A14, Master_List!A:A, Master_List!B:B, "Invalid ID")) | C14: =IF(B14="","",_xlfn.XLOOKUP(B14, Master_List!B:B, Master_List!C:C, "Not Found"))
B15: =IF(A15="","", _xlfn.XLOOKUP(A15, Master_List!A:A, Master_List!B:B, "Invalid ID")) | C15: =IF(B15="","",_xlfn.XLOOKUP(B15, Master_List!B:B, Master_List!C:C, "Not Found"))
B16: =IF(A16="","", _xlfn.XLOOKUP(A16, Master_List!A:A, Master_List!B:B, "Invalid ID")) | C16: =IF(B16="","",_xlfn.XLOOKUP(B16, Master_List!B:B, Master_List!C:C, "Not Found"))
B17: =IF(A17="","", _xlfn.XLOOKUP(A17, Master_List!A:A, Master_List!B:B, "Invalid ID")) | C17: =IF(B17="","",_xlfn.XLOOKUP(B17, Master_List!B:B, Master_List!C:C, "Not Found"))
... B307: =IF(A307="","", _xlfn.XLOOKUP(A307, Master_List!A:A, Master_List!B:B, "Invalid ID")) | C307: =IF(B307="","",_xlfn.XLOOKUP(B307, Master_List!B:B, Master_List!C:C, "Not Found"))
C308: =IF(B308="","",_xlfn.XLOOKUP(B308, Master_List!B:B, Master_List!C:C, "Not Found"))
C309: =IF(B309="","",_xlfn.XLOOKUP(B309, Master_List!B:B, Master_List!C:C, "Not Found"))
C310: =IF(B310="","",_xlfn.XLOOKUP(B310, Master_List!B:B, Master_List!C:C, "Not Found"))

Sheet Dashboard
A1: Team No | B1: Team Name | C1: Starting Purse | D1: Total Spent | E1: Remaining Purse | F1: Roster Size | G1: Forwards | H1: Midfield | I1: Defender | J1: Goalkeeper | K1: Squad Status
A2: 1 | B2: A | C2: 900 | D2: =SUMIF(Auction_Log!D:D, A2, Auction_Log!E:E) -> 0 | E2: =C2-D2 -> 900 | F2: =COUNTIF(Auction_Log!D:D, A2) -> 0 | G2: =COUNTIFS(Auction_Log!D:D, A2, Auction_Log!C:C, "Forwards") -> 0 | H2: =COUNTIFS(Auction_Log!D:D, A2, Auction_Log!C:C, "Midfield") -> 0 | I2: =COUNTIFS(Auction_Log!D:D, A2, Auction_Log!C:C, "Defender") -> 0 | J2: =COUNTIFS(Auction_Log!D:D, A2, Auction_Log!C:C, "Goalkeeper") -> 0 | K2: =IF(F2>16, "🛑 OVER MAX (16)", IF(G2>4, "🛑 MAX FW (4)", IF(H2>5, "🛑 MAX MF (5)", IF(I2>5, "🛑 MAX DF (5)", IF(J2>2, "🛑 MAX GK (2)", IF(AND(F2>=11, G2>=2, H2>=2, I2>=3, J2>=1), "✅ COMPLETE", "⏳ DRAFTING")))))) -> ⏳ DRAFTING
A3: 2 | B3: B | C3: 900 | D3: =SUMIF(Auction_Log!D:D, A3, Auction_Log!E:E) -> 0 | E3: =C3-D3 -> 900 | F3: =COUNTIF(Auction_Log!D:D, A3) -> 0 | G3: =COUNTIFS(Auction_Log!D:D, A3, Auction_Log!C:C, "Forwards") -> 0 | H3: =COUNTIFS(Auction_Log!D:D, A3, Auction_Log!C:C, "Midfield") -> 0 | I3: =COUNTIFS(Auction_Log!D:D, A3, Auction_Log!C:C, "Defender") -> 0 | J3: =COUNTIFS(Auction_Log!D:D, A3, Auction_Log!C:C, "Goalkeeper") -> 0 | K3: =IF(F3>16, "🛑 OVER MAX (16)", IF(G3>4, "🛑 MAX FW (4)", IF(H3>5, "🛑 MAX MF (5)", IF(I3>5, "🛑 MAX DF (5)", IF(J3>2, "🛑 MAX GK (2)", IF(AND(F3>=11, G3>=2, H3>=2, I3>=3, J3>=1), "✅ COMPLETE", "⏳ DRAFTING")))))) -> ⏳ DRAFTING
A4: 3 | B4: C | C4: 900 | D4: =SUMIF(Auction_Log!D:D, A4, Auction_Log!E:E) -> 0 | E4: =C4-D4 -> 900 | F4: =COUNTIF(Auction_Log!D:D, A4) -> 0 | G4: =COUNTIFS(Auction_Log!D:D, A4, Auction_Log!C:C, "Forwards") -> 0 | H4: =COUNTIFS(Auction_Log!D:D, A4, Auction_Log!C:C, "Midfield") -> 0 | I4: =COUNTIFS(Auction_Log!D:D, A4, Auction_Log!C:C, "Defender") -> 0 | J4: =COUNTIFS(Auction_Log!D:D, A4, Auction_Log!C:C, "Goalkeeper") -> 0 | K4: =IF(F4>16, "🛑 OVER MAX (16)", IF(G4>4, "🛑 MAX FW (4)", IF(H4>5, "🛑 MAX MF (5)", IF(I4>5, "🛑 MAX DF (5)", IF(J4>2, "🛑 MAX GK (2)", IF(AND(F4>=11, G4>=2, H4>=2, I4>=3, J4>=1), "✅ COMPLETE", "⏳ DRAFTING")))))) -> ⏳ DRAFTING
A5: 4 | B5: D | C5: 900 | D5: =SUMIF(Auction_Log!D:D, A5, Auction_Log!E:E) -> 0 | E5: =C5-D5 -> 900 | F5: =COUNTIF(Auction_Log!D:D, A5) -> 0 | G5: =COUNTIFS(Auction_Log!D:D, A5, Auction_Log!C:C, "Forwards") -> 0 | H5: =COUNTIFS(Auction_Log!D:D, A5, Auction_Log!C:C, "Midfield") -> 0 | I5: =COUNTIFS(Auction_Log!D:D, A5, Auction_Log!C:C, "Defender") -> 0 | J5: =COUNTIFS(Auction_Log!D:D, A5, Auction_Log!C:C, "Goalkeeper") -> 0 | K5: =IF(F5>16, "🛑 OVER MAX (16)", IF(G5>4, "🛑 MAX FW (4)", IF(H5>5, "🛑 MAX MF (5)", IF(I5>5, "🛑 MAX DF (5)", IF(J5>2, "🛑 MAX GK (2)", IF(AND(F5>=11, G5>=2, H5>=2, I5>=3, J5>=1), "✅ COMPLETE", "⏳ DRAFTING")))))) -> ⏳ DRAFTING
A6: 5 | B6: E | C6: 900 | D6: =SUMIF(Auction_Log!D:D, A6, Auction_Log!E:E) -> 0 | E6: =C6-D6 -> 900 | F6: =COUNTIF(Auction_Log!D:D, A6) -> 0 | G6: =COUNTIFS(Auction_Log!D:D, A6, Auction_Log!C:C, "Forwards") -> 0 | H6: =COUNTIFS(Auction_Log!D:D, A6, Auction_Log!C:C, "Midfield") -> 0 | I6: =COUNTIFS(Auction_Log!D:D, A6, Auction_Log!C:C, "Defender") -> 0 | J6: =COUNTIFS(Auction_Log!D:D, A6, Auction_Log!C:C, "Goalkeeper") -> 0 | K6: =IF(F6>16, "🛑 OVER MAX (16)", IF(G6>4, "🛑 MAX FW (4)", IF(H6>5, "🛑 MAX MF (5)", IF(I6>5, "🛑 MAX DF (5)", IF(J6>2, "🛑 MAX GK (2)", IF(AND(F6>=11, G6>=2, H6>=2, I6>=3, J6>=1), "✅ COMPLETE", "⏳ DRAFTING")))))) -> ⏳ DRAFTING
A7: 6 | B7: F | C7: 900 | D7: =SUMIF(Auction_Log!D:D, A7, Auction_Log!E:E) -> 0 | E7: =C7-D7 -> 900 | F7: =COUNTIF(Auction_Log!D:D, A7) -> 0 | G7: =COUNTIFS(Auction_Log!D:D, A7, Auction_Log!C:C, "Forwards") -> 0 | H7: =COUNTIFS(Auction_Log!D:D, A7, Auction_Log!C:C, "Midfield") -> 0 | I7: =COUNTIFS(Auction_Log!D:D, A7, Auction_Log!C:C, "Defender") -> 0 | J7: =COUNTIFS(Auction_Log!D:D, A7, Auction_Log!C:C, "Goalkeeper") -> 0 | K7: =IF(F7>16, "🛑 OVER MAX (16)", IF(G7>4, "🛑 MAX FW (4)", IF(H7>5, "🛑 MAX MF (5)", IF(I7>5, "🛑 MAX DF (5)", IF(J7>2, "🛑 MAX GK (2)", IF(AND(F7>=11, G7>=2, H7>=2, I7>=3, J7>=1), "✅ COMPLETE", "⏳ DRAFTING")))))) -> ⏳ DRAFTING
A8: 7 | B8: G | C8: 900 | D8: =SUMIF(Auction_Log!D:D, A8, Auction_Log!E:E) -> 0 | E8: =C8-D8 -> 900 | F8: =COUNTIF(Auction_Log!D:D, A8) -> 0 | G8: =COUNTIFS(Auction_Log!D:D, A8, Auction_Log!C:C, "Forwards") -> 0 | H8: =COUNTIFS(Auction_Log!D:D, A8, Auction_Log!C:C, "Midfield") -> 0 | I8: =COUNTIFS(Auction_Log!D:D, A8, Auction_Log!C:C, "Defender") -> 0 | J8: =COUNTIFS(Auction_Log!D:D, A8, Auction_Log!C:C, "Goalkeeper") -> 0 | K8: =IF(F8>16, "🛑 OVER MAX (16)", IF(G8>4, "🛑 MAX FW (4)", IF(H8>5, "🛑 MAX MF (5)", IF(I8>5, "🛑 MAX DF (5)", IF(J8>2, "🛑 MAX GK (2)", IF(AND(F8>=11, G8>=2, H8>=2, I8>=3, J8>=1), "✅ COMPLETE", "⏳ DRAFTING")))))) -> ⏳ DRAFTING
A9: 8 | B9: H | C9: 900 | D9: =SUMIF(Auction_Log!D:D, A9, Auction_Log!E:E) -> 0 | E9: =C9-D9 -> 900 | F9: =COUNTIF(Auction_Log!D:D, A9) -> 0 | G9: =COUNTIFS(Auction_Log!D:D, A9, Auction_Log!C:C, "Forwards") -> 0 | H9: =COUNTIFS(Auction_Log!D:D, A9, Auction_Log!C:C, "Midfield") -> 0 | I9: =COUNTIFS(Auction_Log!D:D, A9, Auction_Log!C:C, "Defender") -> 0 | J9: =COUNTIFS(Auction_Log!D:D, A9, Auction_Log!C:C, "Goalkeeper") -> 0 | K9: =IF(F9>16, "🛑 OVER MAX (16)", IF(G9>4, "🛑 MAX FW (4)", IF(H9>5, "🛑 MAX MF (5)", IF(I9>5, "🛑 MAX DF (5)", IF(J9>2, "🛑 MAX GK (2)", IF(AND(F9>=11, G9>=2, H9>=2, I9>=3, J9>=1), "✅ COMPLETE", "⏳ DRAFTING")))))) -> ⏳ DRAFTING
A10: 9 | B10: I | C10: 900 | D10: =SUMIF(Auction_Log!D:D, A10, Auction_Log!E:E) -> 0 | E10: =C10-D10 -> 900 | F10: =COUNTIF(Auction_Log!D:D, A10) -> 0 | G10: =COUNTIFS(Auction_Log!D:D, A10, Auction_Log!C:C, "Forwards") -> 0 | H10: =COUNTIFS(Auction_Log!D:D, A10, Auction_Log!C:C, "Midfield") -> 0 | I10: =COUNTIFS(Auction_Log!D:D, A10, Auction_Log!C:C, "Defender") -> 0 | J10: =COUNTIFS(Auction_Log!D:D, A10, Auction_Log!C:C, "Goalkeeper") -> 0 | K10: =IF(F10>16, "🛑 OVER MAX (16)", IF(G10>4, "🛑 MAX FW (4)", IF(H10>5, "🛑 MAX MF (5)", IF(I10>5, "🛑 MAX DF (5)", IF(J10>2, "🛑 MAX GK (2)", IF(AND(F10>=11, G10>=2, H10>=2, I10>=3, J10>=1), "✅ COMPLETE", "⏳ DRAFTING")))))) -> ⏳ DRAFTING
A11: 10 | B11: J | C11: 900 | D11: =SUMIF(Auction_Log!D:D, A11, Auction_Log!E:E) -> 0 | E11: =C11-D11 -> 900 | F11: =COUNTIF(Auction_Log!D:D, A11) -> 0 | G11: =COUNTIFS(Auction_Log!D:D, A11, Auction_Log!C:C, "Forwards") -> 0 | H11: =COUNTIFS(Auction_Log!D:D, A11, Auction_Log!C:C, "Midfield") -> 0 | I11: =COUNTIFS(Auction_Log!D:D, A11, Auction_Log!C:C, "Defender") -> 0 | J11: =COUNTIFS(Auction_Log!D:D, A11, Auction_Log!C:C, "Goalkeeper") -> 0 | K11: =IF(F11>16, "🛑 OVER MAX (16)", IF(G11>4, "🛑 MAX FW (4)", IF(H11>5, "🛑 MAX MF (5)", IF(I11>5, "🛑 MAX DF (5)", IF(J11>2, "🛑 MAX GK (2)", IF(AND(F11>=11, G11>=2, H11>=2, I11>=3, J11>=1), "✅ COMPLETE", "⏳ DRAFTING")))))) -> ⏳ DRAFTING

Sheet Team Profile
A1: Team: | B1: 1
A2: Team Name | B2: Starting Purse | C2: Total Spent | D2: Remaining | E2: Total Roster
A3: =_xlfn.XLOOKUP(B1, Dashboard!A2:A11, Dashboard!B2:B11, "Team " & B1) -> A | B3: =_xlfn.XLOOKUP(B1, Dashboard!A2:A11, Dashboard!C2:C11, 0) -> 900 | C3: =_xlfn.XLOOKUP(B1, Dashboard!A2:A11, Dashboard!D2:D11, 0) -> 0 | D3: =_xlfn.XLOOKUP(B1, Dashboard!A2:A11, Dashboard!E2:E11, 0) -> 900 | E3: =_xlfn.XLOOKUP(B1, Dashboard!A2:A11, Dashboard!F2:F11, 0) & " / 16" -> 0 / 16
A4: Position Role | B4: Drafted | C4: Min Requirement | D4: Min Needed | E4: Max Cap | F4: Max Extra
A5: Forwards (FW) | B5: =COUNTIFS(Auction_Log!D5:D200, B1, Auction_Log!C5:C200, "Forwards") -> 0 | C5: 2 | D5: =MAX(0, 2 - B5) -> 2 | E5: 4 | F5: =MAX(0, 4 - B5) -> 4
A6: Midfielders (MF) | B6: =COUNTIFS(Auction_Log!D5:D200, B1, Auction_Log!C5:C200, "Midfield") -> 0 | C6: 2 | D6: =MAX(0, 2 - B6) -> 2 | E6: 5 | F6: =MAX(0, 5 - B6) -> 5
A7: Defenders (DF) | B7: =COUNTIFS(Auction_Log!D5:D200, B1, Auction_Log!C5:C200, "Defender") -> 0 | C7: 3 | D7: =MAX(0, 3 - B7) -> 3 | E7: 5 | F7: =MAX(0, 5 - B7) -> 5
A8: Goalkeepers (GK) | B8: =COUNTIFS(Auction_Log!D5:D200, B1, Auction_Log!C5:C200, "Goalkeeper") -> 0 | C8: 1 | D8: =MAX(0, 1 - B8) -> 1 | E8: 2 | F8: =MAX(0, 2 - B8) -> 2
A9: TOTAL SQUAD | B9: =SUM(B5:B8) -> 0 | C9: 8 | D9: =SUM(D5:D8) -> 8 | E9: 16 | F9: =16 - B9 -> 16
